Workbook

Sheet Account-Overview
A1: Account | B1: Name
A2: 2003100005 | B2: Revenue (DE)
A3: 2003100006 | B3: Revenue (PL)
A4: 2003100007 | B4: Revenue (NL)
A5: 2211200001 | B5: COGS (DE)
A6: 2211200002 | B6: COGS (PL)
A7: 2211200003 | B7: COGS (NL)
A8: 2201201000 | B8: COGS (Others)
A9: 2690200007 | B9: Payment (PayPal)
A10: 2690200010 | B10: Payment (Credit Card)
A11: 2532300000 | B11: Warehouse
A12: 2530200000 | B12: Distribution (Different Carriers)
A13: 2530300000 | B13: Distribution (Package Material)
... A28: 2616100000 | B28: Insurance (Others)

Sheet Actuals (from Accounting)
A1: Year | B1: Account | C1: January | D1: February | E1: March | F1: April | G1: May | H1: June | I1: July | J1: August | K1: September | L1: October | M1: November | N1: December | O1: January1 | P1: February1 | Q1: March1 | R1: April1 | S1: May1 | T1: June1
A2: 2024 | B2: 2003100005 | C2: 15253265 | D2: 21088786 | E2: 28741336 | F2: 26580933 | G2: 23988357 | H2: 19024409 | I2: 14219294 | J2: 17479568 | K2: 30454509 | L2: 27409176 | M2: 29731108 | N2: 28260518 | O2: 0 | P2: 0 | Q2: 0 | R2: 0 | S2: 0 | T2: 0
A3: 2024 | B3: 2003100006 | C3: 1147673.5 | D3: 1358569.8 | E3: 1865549.3 | F3: 1798307 | G3: 1442012 | H3: 1276426.2 | I3: 924149.82 | J3: 1275012.3 | K3: 1870121.8 | L3: 1872141.1 | M3: 2161137.1 | N3: 1688403.1 | O3: 0 | P3: 0 | Q3: 0 | R3: 0 | S3: 0 | T3: 0
A4: 2024 | B4: 2003100007 | C4: 1501984.7 | D4: 1151264 | E4: 1470333.5 | F4: 1628563.7 | G4: 1562604.2 | H4: 1485195.2 | I4: 1131820.6 | J4: 821780.29 | K4: 1303688 | L4: 1535434.2 | M4: 1544790.7 | N4: 1497762.4 | O4: 0 | P4: 0 | Q4: 0 | R4: 0 | S4: 0 | T4: 0
A5: 2024 | B5: 2211200001 | C5: -9336788.7 | D5: -12888477 | E5: -17560390 | F5: -16154015 | G5: -14572288 | H5: -11649165 | I5: -8686540.3 | J5: -10685746 | K5: -18480801 | L5: -16614972 | M5: -18080350 | N5: -17253624 | O5: 0 | P5: 0 | Q5: 0 | R5: 0 | S5: 0 | T5: 0
A6: 2024 | B6: 2211200002 | C6: -723645.01 | D6: -851880.09 | E6: -1172064.4 | F6: -1119928.5 | G6: -903671.54 | H6: -811095.83 | I6: -590189.53 | J6: -805823.52 | K6: -1178511 | L6: -1166665.6 | M6: -1349252 | N6: -1055502.8 | O6: 0 | P6: 0 | Q6: 0 | R6: 0 | S6: 0 | T6: 0
A7: 2024 | B7: 2211200003 | C7: -927479.01 | D7: -704715.47 | E7: -891741.66 | F7: -997120.08 | G7: -960150.55 | H7: -920083.11 | I7: -707533.23 | J7: -510035.97 | K7: -798532.14 | L7: -934751.91 | M7: -940569.68 | N7: -919269.08 | O7: 0 | P7: 0 | Q7: 0 | R7: 0 | S7: 0 | T7: 0
A8: 2024 | B8: 2201201000 | C8: -11398.766 | D8: -8839.5313 | E8: -11413.751 | F8: -12483.943 | G8: -11682.298 | H8: -11405.387 | I8: -8858.316 | J8: -6168.2206 | K8: -9898.6361 | L8: -11587.222 | M8: -11659.339 | N8: -11282.471 | O8: 0 | P8: 0 | Q8: 0 | R8: 0 | S8: 0 | T8: 0
A9: 2024 | B9: 2690200007 | C9: -317875.15 | D9: -409768.76 | E9: -568307.74 | F9: -511261.7 | G9: -467668.53 | H9: -381856.68 | I9: -285451.9 | J9: -344870.89 | K9: -596806.46 | L9: -546218.25 | M9: -589848.29 | N9: -565735.58 | O9: 0 | P9: 0 | Q9: 0 | R9: 0 | S9: 0 | T9: 0
A10: 2024 | B10: 2690200010 | C10: -67059.167 | D10: -87119.242 | E10: -123829.24 | F10: -118127.48 | G10: -111368.2 | H10: -89145.295 | I10: -65228.703 | J10: -72627.059 | K10: -113058.29 | L10: -120163.85 | M10: -120876.87 | N10: -106978.36 | O10: 0 | P10: 0 | Q10: 0 | R10: 0 | S10: 0 | T10: 0
A11: 2024 | B11: 2532300000 | C11: -1470207.6 | D11: -1932725.4 | E11: -2446516.2 | F11: -2307060.7 | G11: -2092614.8 | H11: -1618297.1 | I11: -1227654.4 | J11: -1435279 | K11: -2829668 | L11: -2625300.9 | M11: -2833430 | N11: -2614443.6 | O11: 0 | P11: 0 | Q11: 0 | R11: 0 | S11: 0 | T11: 0
A12: 2024 | B12: 2530200000 | C12: -2543368 | D12: -3367126.1 | E12: -4541273.2 | F12: -4159371.2 | G12: -3748647.3 | H12: -2917515.8 | I12: -2140880.4 | J12: -2608054.6 | K12: -4996800.5 | L12: -4648491.5 | M12: -4971882.1 | N12: -4596069.3 | O12: 0 | P12: 0 | Q12: 0 | R12: 0 | S12: 0 | T12: 0
A13: 2024 | B13: 2530300000 | C13: -154319.05 | D13: -138813.12 | E13: -181299.38 | F13: -177292.38 | G13: -165542.04 | H13: -180245.46 | I13: -147634.99 | J13: -106385.89 | K13: -134150.12 | L13: -155344.32 | M13: -184420.58 | N13: -175151.4 | O13: 0 | P13: 0 | Q13: 0 | R13: 0 | S13: 0 | T13: 0
... A55: 2025 | B55: 2616100000 | C55: 0 | D55: 0 | E55: 0 | F55: 0 | G55: 0 | H55: 0 | I55: 0 | J55: 0 | K55: 0 | L55: 0 | M55: 0 | N55: 0 | O55: 0 | P55: 0 | Q55: -38153.678 | R55: 0 | S55: 0 | T55: 0

Sheet Budget (from Controlling)
D2: 2025-01_est | E2: 2025-02_est | F2: 2025-03_est | G2: 2025-04_est | H2: 2025-05_est | I2: 2025-06_est | J2: 2025-07_est | K2: 2025-08_est | L2: 2025-09_est | M2: 2025-10_est | N2: 2025-11_est | O2: 2025-12_est
D3: 2025-01 | E3: 2025-02 | F3: 2025-03 | G3: 2025-04 | H3: 2025-05 | I3: 2025-06 | J3: 2025-07 | K3: 2025-08 | L3: 2025-09 | M3: 2025-10 | N3: 2025-11 | O3: 2025-12
B6: Revenue | D6: 18928135 | E6: 24920142 | F6: 33841465 | G6: 31628225 | H6: 28396608 | I6: 22853546 | J6: 16910000 | K6: 20320263 | L6: 37167699 | M6: 34279014 | N6: 37110362 | O6: 34586887
B7: COGS | D7: -11379261 | E7: -14940672 | F7: -20325399 | G7: -18975129 | H7: -17054296 | I7: -13728918 | J7: -10145183 | K7: -12170512 | L7: -22281428 | M7: -20527855 | N7: -22204998 | O7: -20700361
B8: Gross Profit | D8: =SUM(D6:D7) -> 7548874.2 | E8: =SUM(E6:E7) -> 9979469.8 | F8: =SUM(F6:F7) -> 13516066 | G8: =SUM(G6:G7) -> 12653096 | H8: =SUM(H6:H7) -> 11342312 | I8: =SUM(I6:I7) -> 9124628 | J8: =SUM(J6:J7) -> 6764816.7 | K8: =SUM(K6:K7) -> 8149750.4 | ... O8: =SUM(O6:O7) -> 13886526
B10: Payment | D10: -425933.52 | E10: -560769.66 | F10: -761523.23 | G10: -711719.41 | H10: -638999.42 | I10: -514265.74 | J10: -380520.1 | K10: -457260.11 | L10: -836372.36 | M10: -771369.24 | N10: -835082.12 | O10: -778297.2
B11: Warehouse | D11: -1666186.2 | E11: -2162748 | F11: -2853089.8 | G11: -2627283.8 | H11: -2288427.7 | I11: -1841723 | J11: -1320813.6 | K11: -1612377.2 | L11: -3179597.4 | M11: -3017477.5 | N11: -3312722.4 | O11: -2958815.8
B12: Distribution | D12: -2929859.4 | E12: -3825209.2 | F12: -5107316.1 | G12: -4732498.8 | H12: -4248955.4 | I12: -3331116 | J12: -2399352.2 | K12: -2857021.6 | L12: -5753135.9 | M12: -5394433.7 | N12: -5792129.6 | O12: -5309041.8
B13: Variable Costs | D13: =SUM(D10:D12) -> -5021979.2 | E13: =SUM(E10:E12) -> -6548726.8 | F13: =SUM(F10:F12) -> -8721929.1 | G13: =SUM(G10:G12) -> -8071502 | H13: =SUM(H10:H12) -> -7176382.5 | I13: =SUM(I10:I12) -> -5687104.7 | J13: =SUM(J10:J12) -> -4100685.9 | K13: =SUM(K10:K12) -> -4926659 | ... O13: =SUM(O10:O12) -> -9046154.8
B15: Conribution Profit | D15: =D8+D13 -> 2526895 | E15: =E8+E13 -> 3430743 | F15: =F8+F13 -> 4794137 | G15: =G8+G13 -> 4581593.7 | H15: =H8+H13 -> 4165929.9 | I15: =I8+I13 -> 3437523.3 | J15: =J8+J13 -> 2664130.8 | K15: =K8+K13 -> 3223091.5 | ... O15: =O8+O13 -> 4840371
B17: Labour | D17: -1539741.9 | E17: -1539741.9 | F17: -1539741.9 | G17: -1539741.9 | H17: -1539741.9 | I17: -1539741.9 | J17: -1539741.9 | K17: -1539741.9 | L17: -1539741.9 | M17: -1539741.9 | N17: -1539741.9 | O17: -1539741.9
B18: Marketing | D18: -594389.75 | E18: -654755.05 | F18: -762497.05 | G18: -798901.17 | H18: -718701.62 | I18: -679298.94 | J18: -550659.44 | K18: -500280.19 | L18: -797141.99 | M18: -1042540.7 | N18: -931217.07 | O18: -690225.44
B19: Rent | D19: -98844.252 | E19: -98844.252 | F19: -98581.501 | G19: -98581.501 | H19: -98581.501 | I19: -98586.819 | J19: -98771.161 | K19: -98940.654 | L19: -98732.897 | M19: -98732.897 | N19: -98732.897 | O19: -98732.897
B20: Consulting | D20: -17658.309 | E20: -12474.306 | F20: -15709.406 | G20: -14632.893 | H20: -16361.729 | I20: -20406.098 | J20: -16432.215 | K20: -13968.284 | L20: -16171.699 | M20: -18664.331 | N20: -14523.632 | O20: -35025.621
B21: Travel | D21: -14849.6 | E21: -10407.952 | F21: 0 | G21: -4454.3095 | H21: -8445.1326 | I21: -8833.1198 | J21: -11727.665 | K21: -2298.7739 | L21: 0 | M21: -12002.445 | N21: -6081.5051 | O21: -7952.3431
B22: Insurances | D22: -103700.17 | E22: -44373.95 | F22: -67523.009 | G22: -26145.365 | H22: -27428.697 | I22: -63358.628 | J22: -41498.1 | K22: -39352.454 | L22: -36790.466 | M22: -38847.113 | N22: -40944.658 | O22: -42889.018
B23: OPEX | D23: =SUM(D17:D22) -> -2369184 | E23: =SUM(E17:E22) -> -2360597.4 | F23: =SUM(F17:F22) -> -2484052.9 | G23: =SUM(G17:G22) -> -2482457.1 | H23: =SUM(H17:H22) -> -2409260.6 | I23: =SUM(I17:I22) -> -2410225.5 | J23: =SUM(J17:J22) -> -2258830.5 | K23: =SUM(K17:K22) -> -2194582.3 | ... O23: =SUM(O17:O22) -> -2414567.2
B25: EBITDA | D25: =D15+D23 -> 157711.02 | E25: =E15+E23 -> 1070145.6 | F25: =F15+F23 -> 2310084.2 | G25: =G15+G23 -> 2099136.6 | H25: =H15+H23 -> 1756669.3 | I25: =I15+I23 -> 1027297.8 | J25: =J15+J23 -> 405300.31 | K25: =K15+K23 -> 1028509.2 | ... O25: =O15+O23 -> 2425803.8

Sheet Rev_by_region
A1: Account | B1: Name | E1: Year | F1: Account | G1: January | H1: February | I1: March | J1: April | K1: May | L1: June | M1: July | N1: August | O1: September | P1: October | Q1: November | R1: December | S1: January1 | T1: February1 | U1: March1 | V1: April1 | W1: May1 | X1: June1 | Y1: SUM TOTAL | Z1: Kolumna1 | AC1: Year | AD1: 2025
A2: 2003100005 | B2: Revenue (DE) | E2: 2024 | F2: 2003100005 | G2: 15253265 | H2: 21088786 | I2: 28741336 | J2: 26580933 | K2: 23988357 | L2: 19024409 | M2: 14219294 | N2: 17479568 | O2: 30454509 | P2: 27409176 | Q2: 29731108 | R2: 28260518 | S2: 0 | T2: 0 | U2: 0 | V2: 0 | W2: 0 | X2: 0 | Y2: =SUM(tActuals7[[#This Row],[January]:[June1]]) -> 2.8223126e+08 | Z2: =_xlfn.XLOOKUP(tActuals7[[#This Row],[Account]],A:A,B:B) -> Revenue (DE)
A3: 2003100006 | B3: Revenue (PL) | E3: 2024 | F3: 2003100006 | G3: 1147673.5 | H3: 1358569.8 | I3: 1865549.3 | J3: 1798307 | K3: 1442012 | L3: 1276426.2 | M3: 924149.82 | N3: 1275012.3 | O3: 1870121.8 | P3: 1872141.1 | Q3: 2161137.1 | R3: 1688403.1 | S3: 0 | T3: 0 | U3: 0 | V3: 0 | W3: 0 | X3: 0 | Y3: =SUM(tActuals7[[#This Row],[January]:[June1]]) -> 18679503 | Z3: =_xlfn.XLOOKUP(tActuals7[[#This Row],[Account]],A:A,B:B) -> Revenue (PL) | AC3: Etykiety wierszy | AD3: Suma z SUM TOTAL | AE3: Suma z SUM TOTAL2
A4: 2003100007 | B4: Revenue (NL) | E4: 2024 | F4: 2003100007 | G4: 1501984.7 | H4: 1151264 | I4: 1470333.5 | J4: 1628563.7 | K4: 1562604.2 | L4: 1485195.2 | M4: 1131820.6 | N4: 821780.29 | O4: 1303688 | P4: 1535434.2 | Q4: 1544790.7 | R4: 1497762.4 | S4: 0 | T4: 0 | U4: 0 | V4: 0 | W4: 0 | X4: 0 | Y4: =SUM(tActuals7[[#This Row],[January]:[June1]]) -> 16635222 | Z4: =_xlfn.XLOOKUP(tActuals7[[#This Row],[Account]],A:A,B:B) -> Revenue (NL) | AC4: Revenue (DE) | AD4: 1.2108928e+08 | AE4: 0.87773764
A5: 2211200001 | B5: COGS (DE) | E5: 2024 | F5: 2211200001 | G5: -9336788.7 | H5: -12888477 | I5: -17560390 | J5: -16154015 | K5: -14572288 | L5: -11649165 | M5: -8686540.3 | N5: -10685746 | O5: -18480801 | P5: -16614972 | Q5: -18080350 | R5: -17253624 | S5: 0 | T5: 0 | U5: 0 | V5: 0 | W5: 0 | X5: 0 | Y5: =SUM(tActuals7[[#This Row],[January]:[June1]]) -> -1.7196316e+08 | Z5: =_xlfn.XLOOKUP(tActuals7[[#This Row],[Account]],A:A,B:B) -> COGS (DE) | AC5: Revenue (NL) | AD5: 8839307.5 | AE5: 0.064073324
A6: 2211200002 | B6: COGS (PL) | E6: 2024 | F6: 2211200002 | G6: -723645.01 | H6: -851880.09 | I6: -1172064.4 | J6: -1119928.5 | K6: -903671.54 | L6: -811095.83 | M6: -590189.53 | N6: -805823.52 | O6: -1178511 | P6: -1166665.6 | Q6: -1349252 | R6: -1055502.8 | S6: 0 | T6: 0 | U6: 0 | V6: 0 | W6: 0 | X6: 0 | Y6: =SUM(tActuals7[[#This Row],[January]:[June1]]) -> -11728230 | Z6: =_xlfn.XLOOKUP(tActuals7[[#This Row],[Account]],A:A,B:B) -> COGS (PL) | AC6: Revenue (PL) | AD6: 8027534.2 | AE6: 0.058189039
A7: 2211200003 | B7: COGS (NL) | E7: 2024 | F7: 2211200003 | G7: -927479.01 | H7: -704715.47 | I7: -891741.66 | J7: -997120.08 | K7: -960150.55 | L7: -920083.11 | M7: -707533.23 | N7: -510035.97 | O7: -798532.14 | P7: -934751.91 | Q7: -940569.68 | R7: -919269.08 | S7: 0 | T7: 0 | U7: 0 | V7: 0 | W7: 0 | X7: 0 | Y7: =SUM(tActuals7[[#This Row],[January]:[June1]]) -> -10211982 | Z7: =_xlfn.XLOOKUP(tActuals7[[#This Row],[Account]],A:A,B:B) -> COGS (NL) | AC7: Suma końcowa | AD7: 1.3795612e+08 | AE7: 1
A8: 2201201000 | B8: COGS (Others) | E8: 2024 | F8: 2201201000 | G8: -11398.766 | H8: -8839.5313 | I8: -11413.751 | J8: -12483.943 | K8: -11682.298 | L8: -11405.387 | M8: -8858.316 | N8: -6168.2206 | O8: -9898.6361 | P8: -11587.222 | Q8: -11659.339 | R8: -11282.471 | S8: 0 | T8: 0 | U8: 0 | V8: 0 | W8: 0 | X8: 0 | Y8: =SUM(tActuals7[[#This Row],[January]:[June1]]) -> -126677.88 | Z8: =_xlfn.XLOOKUP(tActuals7[[#This Row],[Account]],A:A,B:B) -> COGS (Others)
A9: 2690200007 | B9: Payment (PayPal) | E9: 2024 | F9: 2690200007 | G9: -317875.15 | H9: -409768.76 | I9: -568307.74 | J9: -511261.7 | K9: -467668.53 | L9: -381856.68 | M9: -285451.9 | N9: -344870.89 | O9: -596806.46 | P9: -546218.25 | Q9: -589848.29 | R9: -565735.58 | S9: 0 | T9: 0 | U9: 0 | V9: 0 | W9: 0 | X9: 0 | Y9: =SUM(tActuals7[[#This Row],[January]:[June1]]) -> -5585669.9 | Z9: =_xlfn.XLOOKUP(tActuals7[[#This Row],[Account]],A:A,B:B) -> Payment (PayPal)
A10: 2690200010 | B10: Payment (Credit Card) | E10: 2024 | F10: 2690200010 | G10: -67059.167 | H10: -87119.242 | I10: -123829.24 | J10: -118127.48 | K10: -111368.2 | L10: -89145.295 | M10: -65228.703 | N10: -72627.059 | O10: -113058.29 | P10: -120163.85 | Q10: -120876.87 | R10: -106978.36 | S10: 0 | T10: 0 | U10: 0 | V10: 0 | W10: 0 | X10: 0 | Y10: =SUM(tActuals7[[#This Row],[January]:[June1]]) -> -1195581.8 | Z10: =_xlfn.XLOOKUP(tActuals7[[#This Row],[Account]],A:A,B:B) -> Payment (Credit Card)
A11: 2532300000 | B11: Warehouse | E11: 2024 | F11: 2532300000 | G11: -1470207.6 | H11: -1932725.4 | I11: -2446516.2 | J11: -2307060.7 | K11: -2092614.8 | L11: -1618297.1 | M11: -1227654.4 | N11: -1435279 | O11: -2829668 | P11: -2625300.9 | Q11: -2833430 | R11: -2614443.6 | S11: 0 | T11: 0 | U11: 0 | V11: 0 | W11: 0 | X11: 0 | Y11: =SUM(tActuals7[[#This Row],[January]:[June1]]) -> -25433198 | Z11: =_xlfn.XLOOKUP(tActuals7[[#This Row],[Account]],A:A,B:B) -> Warehouse
A12: 2530200000 | B12: Distribution (Different Carriers) | E12: 2024 | F12: 2530200000 | G12: -2543368 | H12: -3367126.1 | I12: -4541273.2 | J12: -4159371.2 | K12: -3748647.3 | L12: -2917515.8 | M12: -2140880.4 | N12: -2608054.6 | O12: -4996800.5 | P12: -4648491.5 | Q12: -4971882.1 | R12: -4596069.3 | S12: 0 | T12: 0 | U12: 0 | V12: 0 | W12: 0 | X12: 0 | Y12: =SUM(tActuals7[[#This Row],[January]:[June1]]) -> -45239480 | Z12: =_xlfn.XLOOKUP(tActuals7[[#This Row],[Account]],A:A,B:B) -> Distribution (Different Carriers)
A13: 2530300000 | B13: Distribution (Package Material) | E13: 2024 | F13: 2530300000 | G13: -154319.05 | H13: -138813.12 | I13: -181299.38 | J13: -177292.38 | K13: -165542.04 | L13: -180245.46 | M13: -147634.99 | N13: -106385.89 | O13: -134150.12 | P13: -155344.32 | Q13: -184420.58 | R13: -175151.4 | S13: 0 | T13: 0 | U13: 0 | V13: 0 | W13: 0 | X13: 0 | Y13: =SUM(tActuals7[[#This Row],[January]:[June1]]) -> -1900598.7 | Z13: =_xlfn.XLOOKUP(tActuals7[[#This Row],[Account]],A:A,B:B) -> Distribution (Package Material)
A14: 2400210100 | B14: Labour (Salaries) | E14: 2024 | F14: 2400210100 | G14: -1523819.5 | H14: -1531111.2 | I14: -1521637.5 | J14: -1512990.6 | K14: -1508750 | L14: -1508440.2 | M14: -1507887.8 | N14: -1511575.3 | O14: -1540696.4 | P14: -1547838.8 | Q14: -1548569.4 | R14: -1550788.7 | S14: 0 | T14: 0 | U14: 0 | V14: 0 | W14: 0 | X14: 0 | Y14: =SUM(tActuals7[[#This Row],[January]:[June1]]) -> -18314105 | Z14: =_xlfn.XLOOKUP(tActuals7[[#This Row],[Account]],A:A,B:B) -> Labour (Salaries)
A15: 2400210200 | B15: Labour (Bonuses) | E15: 2024 | F15: 2400210200 | G15: -407.01103 | H15: -429.98273 | I15: -15309.257 | J15: -582.6386 | K15: -637.25739 | L15: -9051.042 | M15: -379.34589 | N15: -890.07291 | O15: -26666.753 | P15: -527.99439 | Q15: -441.8799 | R15: -89019.466 | S15: 0 | T15: 0 | U15: 0 | V15: 0 | W15: 0 | X15: 0 | Y15: =SUM(tActuals7[[#This Row],[January]:[June1]]) -> -144342.7 | Z15: =_xlfn.XLOOKUP(tActuals7[[#This Row],[Account]],A:A,B:B) -> Labour (Bonuses)
A16: 2400210120 | B16: Labour (Social Contributions) | E16: 2024 | F16: 2400210120 | G16: -30909.525 | H16: -31057.429 | I16: -30865.263 | J16: -30689.869 | K16: -30603.851 | L16: -30597.566 | M16: -30586.362 | N16: -30661.159 | O16: -31251.86 | P16: -31396.736 | Q16: -31411.557 | R16: -31456.573 | S16: 0 | T16: 0 | U16: 0 | V16: 0 | W16: 0 | X16: 0 | Y16: =SUM(tActuals7[[#This Row],[January]:[June1]]) -> -371487.75 | Z16: =_xlfn.XLOOKUP(tActuals7[[#This Row],[Account]],A:A,B:B) -> Labour (Social Contributions)
A17: 2546100100 | B17: Marketing (Google) | E17: 2024 | F17: 2546100100 | G17: -358802.71 | H17: -376107.33 | I17: -445681.78 | J17: -475436.64 | K17: -384962.22 | L17: -366630.69 | M17: -268498.33 | N17: -227638.35 | O17: -413490.11 | P17: -381830.95 | Q17: -394643.56 | R17: -372706.14 | S17: 0 | T17: 0 | U17: 0 | V17: 0 | W17: 0 | X17: 0 | Y17: =SUM(tActuals7[[#This Row],[January]:[June1]]) -> -4466428.8 | Z17: =_xlfn.XLOOKUP(tActuals7[[#This Row],[Account]],A:A,B:B) -> Marketing (Google)
A18: 2544601400 | B18: Marketing (Meta) | E18: 2024 | F18: 2544601400 | G18: -109605.3 | H18: -118609.1 | I18: -123117.27 | J18: -116028.83 | K18: -97509.605 | L18: -92866.29 | M18: -84998.737 | N18: -96952.953 | O18: -156020.27 | P18: -168444.87 | Q18: -176087.6 | R18: -142666.18 | S18: 0 | T18: 0 | U18: 0 | V18: 0 | W18: 0 | X18: 0 | Y18: =SUM(tActuals7[[#This Row],[January]:[June1]]) -> -1482907 | Z18: =_xlfn.XLOOKUP(tActuals7[[#This Row],[Account]],A:A,B:B) -> Marketing (Meta)
A19: 2544600140 | B19: Marketing (Flyers) | E19: 2024 | F19: 2544600140 | G19: -77705.213 | H19: -102457.96 | I19: -122105.31 | J19: -131622.64 | K19: -165518.77 | L19: -157636.92 | M19: -149852.47 | N19: -136552.84 | O19: -133810.26 | P19: -374669.91 | Q19: -263362.75 | R19: -108238.57 | S19: 0 | T19: 0 | U19: 0 | V19: 0 | W19: 0 | X19: 0 | Y19: =SUM(tActuals7[[#This Row],[January]:[June1]]) -> -1923533.6 | Z19: =_xlfn.XLOOKUP(tActuals7[[#This Row],[Account]],A:A,B:B) -> Marketing (Flyers)
... A28: 2616100000 | B28: Insurance (Others) | E28: 2024 | F28: 2616100000 | G28: 0 | H28: 0 | I28: -36964.048 | J28: 0 | K28: 0 | L28: 0 | M28: 0 | N28: 0 | O28: 0 | P28: 0 | Q28: 0 | R28: 0 | S28: 0 | T28: 0 | U28: 0 | V28: 0 | W28: 0 | X28: 0 | Y28: =SUM(tActuals7[[#This Row],[January]:[June1]]) -> -36964.048 | Z28: =_xlfn.XLOOKUP(tActuals7[[#This Row],[Account]],A:A,B:B) -> Insurance (Others)
E29: 2025 | F29: 2003100005 | G29: 0 | H29: 0 | I29: 0 | J29: 0 | K29: 0 | L29: 0 | M29: 0 | N29: 0 | O29: 0 | P29: 0 | Q29: 0 | R29: 0 | S29: 15587142 | T29: 21550395 | U29: 25921509 | V29: 19150184 | W29: 20358144 | X29: 18521908 | Y29: =SUM(tActuals7[[#This Row],[January]:[June1]]) -> 1.2108928e+08 | Z29: =_xlfn.XLOOKUP(tActuals7[[#This Row],[Account]],A:A,B:B) -> Revenue (DE)
E30: 2025 | F30: 2003100006 | G30: 0 | H30: 0 | I30: 0 | J30: 0 | K30: 0 | L30: 0 | M30: 0 | N30: 0 | O30: 0 | P30: 0 | Q30: 0 | R30: 0 | S30: 1162130.5 | T30: 1375683.2 | U30: 1741665.9 | V30: 1276638.9 | W30: 1297552.5 | X30: 1173863.2 | Y30: =SUM(tActuals7[[#This Row],[January]:[June1]]) -> 8027534.2 | Z30: =_xlfn.XLOOKUP(tActuals7[[#This Row],[Account]],A:A,B:B) -> Revenue (PL)
E31: 2025 | F31: 2003100007 | G31: 0 | H31: 0 | I31: 0 | J31: 0 | K31: 0 | L31: 0 | M31: 0 | N31: 0 | O31: 0 | P31: 0 | Q31: 0 | R31: 0 | S31: 1520904.8 | T31: 1165766.2 | U31: 1397252.6 | V31: 1562865.4 | W31: 1748359.8 | X31: 1444158.7 | Y31: =SUM(tActuals7[[#This Row],[January]:[June1]]) -> 8839307.5 | Z31: =_xlfn.XLOOKUP(tActuals7[[#This Row],[Account]],A:A,B:B) -> Revenue (NL)
E32: 2025 | F32: 2211200001 | G32: 0 | H32: 0 | I32: 0 | J32: 0 | K32: 0 | L32: 0 | M32: 0 | N32: 0 | O32: 0 | P32: 0 | Q32: 0 | R32: 0 | S32: -9511517.2 | T32: -13135651 | U32: -15677777 | V32: -11529761 | W32: -12207980 | X32: -11216654 | Y32: =SUM(tActuals7[[#This Row],[January]:[June1]]) -> -73279341 | Z32: =_xlfn.XLOOKUP(tActuals7[[#This Row],[Account]],A:A,B:B) -> COGS (DE)
E33: 2025 | F33: 2211200002 | G33: 0 | H33: 0 | I33: 0 | J33: 0 | K33: 0 | L33: 0 | M33: 0 | N33: 0 | O33: 0 | P33: 0 | Q33: 0 | R33: 0 | S33: -729894.79 | T33: -860147.63 | U33: -1085322.4 | V33: -790838.16 | W33: -806592.59 | X33: -734792.93 | Y33: =SUM(tActuals7[[#This Row],[January]:[June1]]) -> -5007588.5 | Z33: =_xlfn.XLOOKUP(tActuals7[[#This Row],[Account]],A:A,B:B) -> COGS (PL)
E34: 2025 | F34: 2211200003 | G34: 0 | H34: 0 | I34: 0 | J34: 0 | K34: 0 | L34: 0 | M34: 0 | N34: 0 | O34: 0 | P34: 0 | Q34: 0 | R34: 0 | S34: -927464.08 | T34: -705415.86 | U34: -844968.04 | V34: -951185.12 | W34: -1063118.2 | X34: -883462.25 | Y34: =SUM(tActuals7[[#This Row],[January]:[June1]]) -> -5375613.6 | Z34: =_xlfn.XLOOKUP(tActuals7[[#This Row],[Account]],A:A,B:B) -> COGS (NL)
E35: 2025 | F35: 2201201000 | G35: 0 | H35: 0 | I35: 0 | J35: 0 | K35: 0 | L35: 0 | M35: 0 | N35: 0 | O35: 0 | P35: 0 | Q35: 0 | R35: 0 | S35: -11611.85 | T35: -8922.8194 | U35: -10794.898 | V35: -12371.127 | W35: -13693.741 | X35: -11170.573 | Y35: =SUM(tActuals7[[#This Row],[January]:[June1]]) -> -68565.008 | Z35: =_xlfn.XLOOKUP(tActuals7[[#This Row],[Account]],A:A,B:B) -> COGS (Others)
E36: 2025 | F36: 2690200007 | G36: 0 | H36: 0 | I36: 0 | J36: 0 | K36: 0 | L36: 0 | M36: 0 | N36: 0 | O36: 0 | P36: 0 | Q36: 0 | R36: 0 | S36: -329966.84 | T36: -444477.29 | U36: -530386.96 | V36: -380806.03 | W36: -409564.15 | X36: -367756.22 | Y36: =SUM(tActuals7[[#This Row],[January]:[June1]]) -> -2462957.5 | Z36: =_xlfn.XLOOKUP(tActuals7[[#This Row],[Account]],A:A,B:B) -> Payment (PayPal)
E37: 2025 | F37: 2690200010 | G37: 0 | H37: 0 | I37: 0 | J37: 0 | K37: 0 | L37: 0 | M37: 0 | N37: 0 | O37: 0 | P37: 0 | Q37: 0 | R37: 0 | S37: -74250.497 | T37: -90525.202 | U37: -120810.01 | V37: -111996.6 | W37: -114779.62 | X37: -104151.27 | Y37: =SUM(tActuals7[[#This Row],[January]:[June1]]) -> -616513.2 | Z37: =_xlfn.XLOOKUP(tActuals7[[#This Row],[Account]],A:A,B:B) -> Payment (Credit Card)
E38: 2025 | F38: 2532300000 | G38: 0 | H38: 0 | I38: 0 | J38: 0 | K38: 0 | L38: 0 | M38: 0 | N38: 0 | O38: 0 | P38: 0 | Q38: 0 | R38: 0 | S38: -1830023.9 | T38: -2405737.7 | U38: -2768479.8 | V38: -2084666.6 | W38: -2202174.6 | X38: -1982751.8 | Y38: =SUM(tActuals7[[#This Row],[January]:[June1]]) -> -13273834 | Z38: =_xlfn.XLOOKUP(tActuals7[[#This Row],[Account]],A:A,B:B) -> Warehouse
E39: 2025 | F39: 2530200000 | G39: 0 | H39: 0 | I39: 0 | J39: 0 | K39: 0 | L39: 0 | M39: 0 | N39: 0 | O39: 0 | P39: 0 | Q39: 0 | R39: 0 | S39: -2778072.5 | T39: -3677847.8 | U39: -4284234.9 | V39: -3178369.1 | W39: -3385070.5 | X39: -3050680.7 | Y39: =SUM(tActuals7[[#This Row],[January]:[June1]]) -> -20354275 | Z39: =_xlfn.XLOOKUP(tActuals7[[#This Row],[Account]],A:A,B:B) -> Distribution (Different Carriers)
E40: 2025 | F40: 2530300000 | G40: 0 | H40: 0 | I40: 0 | J40: 0 | K40: 0 | L40: 0 | M40: 0 | N40: 0 | O40: 0 | P40: 0 | Q40: 0 | R40: 0 | S40: -156074.89 | T40: -140392.53 | U40: -180733.36 | V40: -163355.03 | W40: -185825.34 | X40: -148540.53 | Y40: =SUM(tActuals7[[#This Row],[January]:[June1]]) -> -974921.69 | Z40: =_xlfn.XLOOKUP(tActuals7[[#This Row],[Account]],A:A,B:B) -> Distribution (Package Material)
... E55: 2025 | F55: 2616100000 | G55: 0 | H55: 0 | I55: 0 | J55: 0 | K55: 0 | L55: 0 | M55: 0 | N55: 0 | O55: 0 | P55: 0 | Q55: 0 | R55: 0 | S55: 0 | T55: 0 | U55: -38153.678 | V55: 0 | W55: 0 | X55: 0 | Y55: =SUM(tActuals7[[#This Row],[January]:[June1]]) -> -38153.678 | Z55: =_xlfn.XLOOKUP(tActuals7[[#This Row],[Account]],A:A,B:B) -> Insurance (Others)

Sheet Budget (from Controlling)_copy
C1: 2025.01 | D1: 2025.02 | E1: 2025.03 | F1: 2025.04 | G1: 2025.05 | H1: 2025.06 | I1: 2025.07 | J1: 2025.08 | K1: 2025.09 | L1: 2025.10 | M1: 2025.11 | N1: 2025.12
C2: 2025-01_est | D2: 2025-02_est | E2: 2025-03_est | F2: 2025-04_est | G2: 2025-05_est | H2: 2025-06_est | I2: 2025-07_est | J2: 2025-08_est | K2: 2025-09_est | L2: 2025-10_est | M2: 2025-11_est | N2: 2025-12_est
C3: 2025-01 | D3: 2025-02 | E3: 2025-03 | F3: 2025-04 | G3: 2025-05 | H3: 2025-06 | I3: 2025-07 | J3: 2025-08 | K3: 2025-09 | L3: 2025-10 | M3: 2025-11 | N3: 2025-12
B4: Revenue | C4: 18928135 | D4: 24920142 | E4: 33841465 | F4: 31628225 | G4: 28396608 | H4: 22853546 | I4: 16910000 | J4: 20320263 | K4: 37167699 | L4: 34279014 | M4: 37110362 | N4: 34586887
B5: COGS | C5: -11379261 | D5: -14940672 | E5: -20325399 | F5: -18975129 | G5: -17054296 | H5: -13728918 | I5: -10145183 | J5: -12170512 | K5: -22281428 | L5: -20527855 | M5: -22204998 | N5: -20700361
B6: Gross Profit | C6: =SUM(C4:C5) -> 7548874.2 | D6: =SUM(D4:D5) -> 9979469.8 | E6: =SUM(E4:E5) -> 13516066 | F6: =SUM(F4:F5) -> 12653096 | G6: =SUM(G4:G5) -> 11342312 | H6: =SUM(H4:H5) -> 9124628 | I6: =SUM(I4:I5) -> 6764816.7 | J6: =SUM(J4:J5) -> 8149750.4 | ... N6: =SUM(N4:N5) -> 13886526
B7: Payment | C7: -425933.52 | D7: -560769.66 | E7: -761523.23 | F7: -711719.41 | G7: -638999.42 | H7: -514265.74 | I7: -380520.1 | J7: -457260.11 | K7: -836372.36 | L7: -771369.24 | M7: -835082.12 | N7: -778297.2
B8: Warehouse | C8: -1666186.2 | D8: -2162748 | E8: -2853089.8 | F8: -2627283.8 | G8: -2288427.7 | H8: -1841723 | I8: -1320813.6 | J8: -1612377.2 | K8: -3179597.4 | L8: -3017477.5 | M8: -3312722.4 | N8: -2958815.8
B9: Distribution | C9: -2929859.4 | D9: -3825209.2 | E9: -5107316.1 | F9: -4732498.8 | G9: -4248955.4 | H9: -3331116 | I9: -2399352.2 | J9: -2857021.6 | K9: -5753135.9 | L9: -5394433.7 | M9: -5792129.6 | N9: -5309041.8
B10: Variable Costs | C10: =SUM(C7:C9) -> -5021979.2 | D10: =SUM(D7:D9) -> -6548726.8 | E10: =SUM(E7:E9) -> -8721929.1 | F10: =SUM(F7:F9) -> -8071502 | G10: =SUM(G7:G9) -> -7176382.5 | H10: =SUM(H7:H9) -> -5687104.7 | I10: =SUM(I7:I9) -> -4100685.9 | J10: =SUM(J7:J9) -> -4926659 | ... N10: =SUM(N7:N9) -> -9046154.8
B11: Contribution Profit | C11: =C6+C10 -> 2526895 | D11: =D6+D10 -> 3430743 | E11: =E6+E10 -> 4794137 | F11: =F6+F10 -> 4581593.7 | G11: =G6+G10 -> 4165929.9 | H11: =H6+H10 -> 3437523.3 | I11: =I6+I10 -> 2664130.8 | J11: =J6+J10 -> 3223091.5 | ... N11: =N6+N10 -> 4840371
B12: Labour | C12: -1539741.9 | D12: -1539741.9 | E12: -1539741.9 | F12: -1539741.9 | G12: -1539741.9 | H12: -1539741.9 | I12: -1539741.9 | J12: -1539741.9 | K12: -1539741.9 | L12: -1539741.9 | M12: -1539741.9 | N12: -1539741.9
B13: Marketing | C13: -594389.75 | D13: -654755.05 | E13: -762497.05 | F13: -798901.17 | G13: -718701.62 | H13: -679298.94 | I13: -550659.44 | J13: -500280.19 | K13: -797141.99 | L13: -1042540.7 | M13: -931217.07 | N13: -690225.44
B14: Rent | C14: -98844.252 | D14: -98844.252 | E14: -98581.501 | F14: -98581.501 | G14: -98581.501 | H14: -98586.819 | I14: -98771.161 | J14: -98940.654 | K14: -98732.897 | L14: -98732.897 | M14: -98732.897 | N14: -98732.897
B15: Consulting | C15: -17658.309 | D15: -12474.306 | E15: -15709.406 | F15: -14632.893 | G15: -16361.729 | H15: -20406.098 | I15: -16432.215 | J15: -13968.284 | K15: -16171.699 | L15: -18664.331 | M15: -14523.632 | N15: -35025.621
B16: Travel | C16: -14849.6 | D16: -10407.952 | E16: 0 | F16: -4454.3095 | G16: -8445.1326 | H16: -8833.1198 | I16: -11727.665 | J16: -2298.7739 | K16: 0 | L16: -12002.445 | M16: -6081.5051 | N16: -7952.3431
B17: Insurances | C17: -103700.17 | D17: -44373.95 | E17: -67523.009 | F17: -26145.365 | G17: -27428.697 | H17: -63358.628 | I17: -41498.1 | J17: -39352.454 | K17: -36790.466 | L17: -38847.113 | M17: -40944.658 | N17: -42889.018
B18: OPEX | C18: =SUM(C12:C17) -> -2369184 | D18: =SUM(D12:D17) -> -2360597.4 | E18: =SUM(E12:E17) -> -2484052.9 | F18: =SUM(F12:F17) -> -2482457.1 | G18: =SUM(G12:G17) -> -2409260.6 | H18: =SUM(H12:H17) -> -2410225.5 | I18: =SUM(I12:I17) -> -2258830.5 | J18: =SUM(J12:J17) -> -2194582.3 | ... N18: =SUM(N12:N17) -> -2414567.2
B19: EBITDA | C19: =C11+C18 -> 157711.02 | D19: =D11+D18 -> 1070145.6 | E19: =E11+E18 -> 2310084.2 | F19: =F11+F18 -> 2099136.6 | G19: =G11+G18 -> 1756669.3 | H19: =H11+H18 -> 1027297.8 | I19: =I11+I18 -> 405300.31 | J19: =J11+J18 -> 1028509.2 | ... N19: =N11+N18 -> 2425803.8

Sheet tActuals
A1: Year | B1: Account | C1: Year_month | D1: Month | E1: Account_description | F1: Value
A2: 2024 | B2: 2003100005 | C2: 2024.01 | D2: January | E2: =_xlfn.XLOOKUP(tActuals_1[[#This Row],[Account]],'Account-Overview'!A:A,'Account-Overview'!B:B) -> Revenue (DE) | F2: 15253265
A3: 2024 | B3: 2003100005 | C3: 2024.02 | D3: February | E3: =_xlfn.XLOOKUP(tActuals_1[[#This Row],[Account]],'Account-Overview'!A:A,'Account-Overview'!B:B) -> Revenue (DE) | F3: 21088786
A4: 2024 | B4: 2003100005 | C4: 2024.03 | D4: March | E4: =_xlfn.XLOOKUP(tActuals_1[[#This Row],[Account]],'Account-Overview'!A:A,'Account-Overview'!B:B) -> Revenue (DE) | F4: 28741336
A5: 2024 | B5: 2003100005 | C5: 2024.04 | D5: April | E5: =_xlfn.XLOOKUP(tActuals_1[[#This Row],[Account]],'Account-Overview'!A:A,'Account-Overview'!B:B) -> Revenue (DE) | F5: 26580933
A6: 2024 | B6: 2003100005 | C6: 2024.05 | D6: May | E6: =_xlfn.XLOOKUP(tActuals_1[[#This Row],[Account]],'Account-Overview'!A:A,'Account-Overview'!B:B) -> Revenue (DE) | F6: 23988357
A7: 2024 | B7: 2003100005 | C7: 2024.06 | D7: June | E7: =_xlfn.XLOOKUP(tActuals_1[[#This Row],[Account]],'Account-Overview'!A:A,'Account-Overview'!B:B) -> Revenue (DE) | F7: 19024409
A8: 2024 | B8: 2003100005 | C8: 2024.07 | D8: July | E8: =_xlfn.XLOOKUP(tActuals_1[[#This Row],[Account]],'Account-Overview'!A:A,'Account-Overview'!B:B) -> Revenue (DE) | F8: 14219294
A9: 2024 | B9: 2003100005 | C9: 2024.08 | D9: August | E9: =_xlfn.XLOOKUP(tActuals_1[[#This Row],[Account]],'Account-Overview'!A:A,'Account-Overview'!B:B) -> Revenue (DE) | F9: 17479568
A10: 2024 | B10: 2003100005 | C10: 2024.09 | D10: September | E10: =_xlfn.XLOOKUP(tActuals_1[[#This Row],[Account]],'Account-Overview'!A:A,'Account-Overview'!B:B) -> Revenue (DE) | F10: 30454509 | I10: P&L ACTUALS | J10: Etykiety kolumn
A11: 2024 | B11: 2003100005 | C11: 2024.10 | D11: October | E11: =_xlfn.XLOOKUP(tActuals_1[[#This Row],[Account]],'Account-Overview'!A:A,'Account-Overview'!B:B) -> Revenue (DE) | F11: 27409176 | I11: CATEGORY | J11: 2024.01 | K11: 2024.02 | L11: 2024.03 | M11: 2024.04 | N11: 2024.05 | O11: 2024.06 | P11: 2024.07 | Q11: 2024.08 | R11: 2024.09 | S11: 2024.10 | T11: 2024.11 | U11: 2024.12 | V11: 2025.01 | W11: 2025.02 | X11: 2025.03 | Y11: 2025.04 | Z11: 2025.05 | AA11: 2025.06
A12: 2024 | B12: 2003100005 | C12: 2024.11 | D12: November | E12: =_xlfn.XLOOKUP(tActuals_1[[#This Row],[Account]],'Account-Overview'!A:A,'Account-Overview'!B:B) -> Revenue (DE) | F12: 29731108 | I12: Revenue (DE) | J12: 15253265 | K12: 21088786 | L12: 28741336 | M12: 26580933 | N12: 23988357 | O12: 19024409 | P12: 14219294 | Q12: 17479568 | R12: 30454509 | S12: 27409176 | T12: 29731108 | U12: 28260518 | V12: 15587142 | W12: 21550395 | X12: 25921509 | Y12: 19150184 | Z12: 20358144 | AA12: 18521908
A13: 2024 | B13: 2003100005 | C13: 2024.12 | D13: December | E13: =_xlfn.XLOOKUP(tActuals_1[[#This Row],[Account]],'Account-Overview'!A:A,'Account-Overview'!B:B) -> Revenue (DE) | F13: 28260518 | I13: Revenue (NL) | J13: 1501984.7 | K13: 1151264 | L13: 1470333.5 | M13: 1628563.7 | N13: 1562604.2 | O13: 1485195.2 | P13: 1131820.6 | Q13: 821780.29 | R13: 1303688 | S13: 1535434.2 | T13: 1544790.7 | U13: 1497762.4 | V13: 1520904.8 | W13: 1165766.2 | X13: 1397252.6 | Y13: 1562865.4 | Z13: 1748359.8 | AA13: 1444158.7
A14: 2024 | B14: 2003100006 | C14: 2024.01 | D14: January | E14: =_xlfn.XLOOKUP(tActuals_1[[#This Row],[Account]],'Account-Overview'!A:A,'Account-Overview'!B:B) -> Revenue (PL) | F14: 1147673.5 | I14: Revenue (PL) | J14: 1147673.5 | K14: 1358569.8 | L14: 1865549.3 | M14: 1798307 | N14: 1442012 | O14: 1276426.2 | P14: 924149.82 | Q14: 1275012.3 | R14: 1870121.8 | S14: 1872141.1 | T14: 2161137.1 | U14: 1688403.1 | V14: 1162130.5 | W14: 1375683.2 | X14: 1741665.9 | Y14: 1276638.9 | Z14: 1297552.5 | AA14: 1173863.2
A15: 2024 | B15: 2003100006 | C15: 2024.02 | D15: February | E15: =_xlfn.XLOOKUP(tActuals_1[[#This Row],[Account]],'Account-Overview'!A:A,'Account-Overview'!B:B) -> Revenue (PL) | F15: 1358569.8 | I15: REVENUE | J15: 17902923 | K15: 23598619 | L15: 32077218 | M15: 30007803 | N15: 26992974 | O15: 21786031 | P15: 16275265 | Q15: 19576361 | R15: 33628318 | S15: 30816752 | T15: 33437036 | U15: 31446684 | V15: 18270177 | W15: 24091845 | X15: 29060428 | Y15: 21989689 | Z15: 23404056 | AA15: 21139929
A16: 2024 | B16: 2003100006 | C16: 2024.03 | D16: March | E16: =_xlfn.XLOOKUP(tActuals_1[[#This Row],[Account]],'Account-Overview'!A:A,'Account-Overview'!B:B) -> Revenue (PL) | F16: 1865549.3 | I16: COGS (DE) | J16: -9336788.7 | K16: -12888477 | L16: -17560390 | M16: -16154015 | N16: -14572288 | O16: -11649165 | P16: -8686540.3 | Q16: -10685746 | R16: -18480801 | S16: -16614972 | T16: -18080350 | U16: -17253624 | V16: -9511517.2 | W16: -13135651 | X16: -15677777 | Y16: -11529761 | Z16: -12207980 | AA16: -11216654
A17: 2024 | B17: 2003100006 | C17: 2024.04 | D17: April | E17: =_xlfn.XLOOKUP(tActuals_1[[#This Row],[Account]],'Account-Overview'!A:A,'Account-Overview'!B:B) -> Revenue (PL) | F17: 1798307 | I17: COGS (NL) | J17: -927479.01 | K17: -704715.47 | L17: -891741.66 | M17: -997120.08 | N17: -960150.55 | O17: -920083.11 | P17: -707533.23 | Q17: -510035.97 | R17: -798532.14 | S17: -934751.91 | T17: -940569.68 | U17: -919269.08 | V17: -927464.08 | W17: -705415.86 | X17: -844968.04 | Y17: -951185.12 | Z17: -1063118.2 | AA17: -883462.25
A18: 2024 | B18: 2003100006 | C18: 2024.05 | D18: May | E18: =_xlfn.XLOOKUP(tActuals_1[[#This Row],[Account]],'Account-Overview'!A:A,'Account-Overview'!B:B) -> Revenue (PL) | F18: 1442012 | I18: COGS (PL) | J18: -723645.01 | K18: -851880.09 | L18: -1172064.4 | M18: -1119928.5 | N18: -903671.54 | O18: -811095.83 | P18: -590189.53 | Q18: -805823.52 | R18: -1178511 | S18: -1166665.6 | T18: -1349252 | U18: -1055502.8 | V18: -729894.79 | W18: -860147.63 | X18: -1085322.4 | Y18: -790838.16 | Z18: -806592.59 | AA18: -734792.93
A19: 2024 | B19: 2003100006 | C19: 2024.06 | D19: June | E19: =_xlfn.XLOOKUP(tActuals_1[[#This Row],[Account]],'Account-Overview'!A:A,'Account-Overview'!B:B) -> Revenue (PL) | F19: 1276426.2 | I19: COGS (Others) | J19: -11398.766 | K19: -8839.5313 | L19: -11413.751 | M19: -12483.943 | N19: -11682.298 | O19: -11405.387 | P19: -8858.316 | Q19: -6168.2206 | R19: -9898.6361 | S19: -11587.222 | T19: -11659.339 | U19: -11282.471 | V19: -11611.85 | W19: -8922.8194 | X19: -10794.898 | Y19: -12371.127 | Z19: -13693.741 | AA19: -11170.573
A20: 2024 | B20: 2003100006 | C20: 2024.07 | D20: July | E20: =_xlfn.XLOOKUP(tActuals_1[[#This Row],[Account]],'Account-Overview'!A:A,'Account-Overview'!B:B) -> Revenue (PL) | F20: 924149.82 | I20: COGS | J20: -10999312 | K20: -14453912 | L20: -19635609 | M20: -18283548 | N20: -16447792 | O20: -13391749 | P20: -9993121.4 | Q20: -12007774 | R20: -20467743 | S20: -18727977 | T20: -20381831 | U20: -19239678 | V20: -11180488 | W20: -14710137 | X20: -17618863 | Y20: -13284156 | Z20: -14091385 | AA20: -12846079
A21: 2024 | B21: 2003100006 | C21: 2024.08 | D21: August | E21: =_xlfn.XLOOKUP(tActuals_1[[#This Row],[Account]],'Account-Overview'!A:A,'Account-Overview'!B:B) -> Revenue (PL) | F21: 1275012.3 | I21: GROSS PROFIT | J21: 6903611.9 | K21: 9144707 | L21: 12441609 | M21: 11724256 | N21: 10545181 | O21: 8394281.6 | P21: 6282143.3 | Q21: 7568586.8 | R21: 13160576 | S21: 12088775 | T21: 13055205 | U21: 12207006 | V21: 7089689.1 | W21: 9381707.1 | X21: 11441565 | Y21: 8705533.2 | Z21: 9312671.2 | AA21: 8293850.2
A22: 2024 | B22: 2003100006 | C22: 2024.09 | D22: September | E22: =_xlfn.XLOOKUP(tActuals_1[[#This Row],[Account]],'Account-Overview'!A:A,'Account-Overview'!B:B) -> Revenue (PL) | F22: 1870121.8 | I22: Payment (Credit Card) | J22: -67059.167 | K22: -87119.242 | L22: -123829.24 | M22: -118127.48 | N22: -111368.2 | O22: -89145.295 | P22: -65228.703 | Q22: -72627.059 | R22: -113058.29 | S22: -120163.85 | T22: -120876.87 | U22: -106978.36 | V22: -74250.497 | W22: -90525.202 | X22: -120810.01 | Y22: -111996.6 | Z22: -114779.62 | AA22: -104151.27
A23: 2024 | B23: 2003100006 | C23: 2024.10 | D23: October | E23: =_xlfn.XLOOKUP(tActuals_1[[#This Row],[Account]],'Account-Overview'!A:A,'Account-Overview'!B:B) -> Revenue (PL) | F23: 1872141.1 | I23: Payment (PayPal) | J23: -317875.15 | K23: -409768.76 | L23: -568307.74 | M23: -511261.7 | N23: -467668.53 | O23: -381856.68 | P23: -285451.9 | Q23: -344870.89 | R23: -596806.46 | S23: -546218.25 | T23: -589848.29 | U23: -565735.58 | V23: -329966.84 | W23: -444477.29 | X23: -530386.96 | Y23: -380806.03 | Z23: -409564.15 | AA23: -367756.22
... A41: 2024 | B41: 2211200001 | C41: 2024.04 | D41: April | E41: =_xlfn.XLOOKUP(tActuals_1[[#This Row],[Account]],'Account-Overview'!A:A,'Account-Overview'!B:B) -> COGS (DE) | F41: -16154015 | I41: RENT | J41: -97865.596 | K41: -97865.596 | L41: -97605.447 | M41: -97605.447 | N41: -97605.447 | O41: -97610.712 | P41: -97793.229 | Q41: -97961.043 | R41: -97755.343 | S41: -97755.343 | T41: -97755.343 | U41: -97755.343 | V41: -96777.79 | W41: -96777.79 | X41: -96777.79 | Y41: -96777.79 | Z41: -96777.79 | AA41: -96777.79
A42: 2024 | B42: 2211200001 | C42: 2024.05 | D42: May | E42: =_xlfn.XLOOKUP(tActuals_1[[#This Row],[Account]],'Account-Overview'!A:A,'Account-Overview'!B:B) -> COGS (DE) | F42: -14572288 | I42: TRAVEL | J42: -12827.643 | K42: -8990.7803 | M42: -3847.8 | N42: -7295.2231 | O42: -7630.381 | P42: -10130.798 | Q42: -1985.7673 | S42: -10368.163 | T42: -5253.4328 | U42: -6869.533 | V42: -12843.86 | W42: -9002.1466 | X42: -674.07031 | Y42: -782.94744 | Z42: -1103.4935 | AA42: -4852.5611
A43: 2024 | B43: 2211200001 | C43: 2024.06 | D43: June | E43: =_xlfn.XLOOKUP(tActuals_1[[#This Row],[Account]],'Account-Overview'!A:A,'Account-Overview'!B:B) -> COGS (DE) | F43: -11649165 | I43: Consulting (BCG, KPMG, etc.) | J43: -11832.966 | K43: -10668.467 | L43: -18729.566 | M43: -13879.426 | N43: -6075.531 | O43: -16220.159 | P43: -11514.542 | Q43: -11156.684 | R43: -13266.537 | S43: -6528.434 | T43: -12028.489 | U43: -31238.467 | V43: -11847.926 | W43: -8517.8596 | X43: -2207.6099 | Y43: -7067.7178 | Z43: -12834.947 | AA43: -22129.993
A44: 2024 | B44: 2211200001 | C44: 2024.07 | D44: July | E44: =_xlfn.XLOOKUP(tActuals_1[[#This Row],[Account]],'Account-Overview'!A:A,'Account-Overview'!B:B) -> COGS (DE) | F44: -8686540.3 | I44: Consulting (for different IT-Tools) | J44: -5825.3423 | K44: -1805.8393 | L44: -9079.84 | M44: -10433.467 | N44: -10286.198 | O44: -3214.2198 | P44: -4135.1871 | Q44: -2146.4432 | R44: -2135.0813 | S44: -11247.119 | T44: -1803.5413 | U44: -2119.2666 | V44: -5832.7069 | W44: -1808.1222 | X44: -7327.0033 | Y44: -7621.5549 | Z44: -2082.0939 | AA44: -2059.2141
A45: 2024 | B45: 2211200001 | C45: 2024.08 | D45: August | E45: =_xlfn.XLOOKUP(tActuals_1[[#This Row],[Account]],'Account-Overview'!A:A,'Account-Overview'!B:B) -> COGS (DE) | F45: -10685746 | I45: CONSULTING | J45: -17658.309 | K45: -12474.306 | L45: -27809.406 | M45: -24312.893 | N45: -16361.729 | O45: -19434.379 | P45: -15649.729 | Q45: -13303.127 | R45: -15401.618 | S45: -17775.553 | T45: -13832.03 | U45: -33357.734 | V45: -17680.633 | W45: -10325.982 | X45: -9534.6132 | Y45: -14689.273 | Z45: -14917.041 | AA45: -24189.207
A46: 2024 | B46: 2211200001 | C46: 2024.09 | D46: September | E46: =_xlfn.XLOOKUP(tActuals_1[[#This Row],[Account]],'Account-Overview'!A:A,'Account-Overview'!B:B) -> COGS (DE) | F46: -18480801 | I46: Insurance (Cyber Security) | J46: -71770.09 | K46: -13956.65 | O46: -33073.329 | P46: -8268.3293 | Q46: -8268.3293 | R46: -8268.3293 | S46: -8268.3293 | T46: -8268.3293 | U46: -8268.3293 | V46: -71860.823 | W46: -13974.294 | X46: -9383.546 | Y46: -10880.322 | Z46: -10131.934 | AA46: -10131.934
A47: 2024 | B47: 2211200001 | C47: 2024.10 | D47: October | E47: =_xlfn.XLOOKUP(tActuals_1[[#This Row],[Account]],'Account-Overview'!A:A,'Account-Overview'!B:B) -> COGS (DE) | F47: -16614972 | I47: Insurance (Legal Protection) | J47: -26991.974 | K47: -28304.255 | L47: -27343.58 | M47: -24900.348 | N47: -26122.569 | O47: -27268.221 | P47: -31253.671 | Q47: -29210.199 | R47: -26770.209 | S47: -28728.921 | T47: -30726.583 | U47: -30158.355 | V47: -27026.097 | W47: -28340.038 | X47: -28256.017 | Y47: -25741.913 | Z47: -24393.041 | AA47: -25141.214
A48: 2024 | B48: 2211200001 | C48: 2024.11 | D48: November | E48: =_xlfn.XLOOKUP(tActuals_1[[#This Row],[Account]],'Account-Overview'!A:A,'Account-Overview'!B:B) -> COGS (DE) | F48: -18080350 | I48: Insurance (Others) | L48: -36964.048 | X48: -38153.678
A49: 2024 | B49: 2211200001 | C49: 2024.12 | D49: December | E49: =_xlfn.XLOOKUP(tActuals_1[[#This Row],[Account]],'Account-Overview'!A:A,'Account-Overview'!B:B) -> COGS (DE) | F49: -17253624 | I49: INSURANCES | J49: -98762.063 | K49: -42260.905 | L49: -64307.628 | M49: -24900.348 | N49: -26122.569 | O49: -60341.551 | P49: -39522 | Q49: -37478.528 | R49: -35038.539 | S49: -36997.25 | T49: -38994.912 | U49: -38426.684 | V49: -98886.921 | W49: -42314.332 | X49: -75793.241 | Y49: -36622.235 | Z49: -34524.975 | AA49: -35273.148
A50: 2024 | B50: 2211200002 | C50: 2024.01 | D50: January | E50: =_xlfn.XLOOKUP(tActuals_1[[#This Row],[Account]],'Account-Overview'!A:A,'Account-Overview'!B:B) -> COGS (PL) | F50: -723645.01 | I50: OPEX | J50: -2337754.1 | K50: -2336110.8 | L50: -2470148.5 | M50: -2441566.2 | N50: -2359059.9 | O50: -2367964.6 | P50: -2216584.3 | Q50: -2161406.6 | R50: -2491803.1 | S50: -2716996.9 | T50: -2606554.9 | U50: -2492744.5 | V50: -2373063.5 | W50: -2356777.3 | X50: -2462522.4 | Y50: -2392504 | Z50: -2294704.4 | AA50: -2309268.9
A51: 2024 | B51: 2211200002 | C51: 2024.02 | D51: February | E51: =_xlfn.XLOOKUP(tActuals_1[[#This Row],[Account]],'Account-Overview'!A:A,'Account-Overview'!B:B) -> COGS (PL) | F51: -851880.09 | I51: EBITDA | J51: 13028.88 | K51: 873043.63 | L51: 2110234.7 | M51: 2009576 | N51: 1600280.8 | O51: 839256.71 | P51: 198708.63 | Q51: 839962.82 | R51: 1998289 | S51: 1276259.2 | T51: 1748192.1 | U51: 1655883 | V51: -451763.03 | W51: 265949.31 | X51: 1094397.7 | Y51: 393835.88 | Z51: 720552.52 | AA51: 330700.68
A52: 2024 | B52: 2211200002 | C52: 2024.03 | D52: March | E52: =_xlfn.XLOOKUP(tActuals_1[[#This Row],[Account]],'Account-Overview'!A:A,'Account-Overview'!B:B) -> COGS (PL) | F52: -1172064.4
A53: 2024 | B53: 2211200002 | C53: 2024.04 | D53: April | E53: =_xlfn.XLOOKUP(tActuals_1[[#This Row],[Account]],'Account-Overview'!A:A,'Account-Overview'!B:B) -> COGS (PL) | F53: -1119928.5
A54: 2024 | B54: 2211200002 | C54: 2024.05 | D54: May | E54: =_xlfn.XLOOKUP(tActuals_1[[#This Row],[Account]],'Account-Overview'!A:A,'Account-Overview'!B:B) -> COGS (PL) | F54: -903671.54
A55: 2024 | B55: 2211200002 | C55: 2024.06 | D55: June | E55: =_xlfn.XLOOKUP(tActuals_1[[#This Row],[Account]],'Account-Overview'!A:A,'Account-Overview'!B:B) -> COGS (PL) | F55: -811095.83
A56: 2024 | B56: 2211200002 | C56: 2024.07 | D56: July | E56: =_xlfn.XLOOKUP(tActuals_1[[#This Row],[Account]],'Account-Overview'!A:A,'Account-Overview'!B:B) -> COGS (PL) | F56: -590189.53
A57: 2024 | B57: 2211200002 | C57: 2024.08 | D57: August | E57: =_xlfn.XLOOKUP(tActuals_1[[#This Row],[Account]],'Account-Overview'!A:A,'Account-Overview'!B:B) -> COGS (PL) | F57: -805823.52
A58: 2024 | B58: 2211200002 | C58: 2024.09 | D58: September | E58: =_xlfn.XLOOKUP(tActuals_1[[#This Row],[Account]],'Account-Overview'!A:A,'Account-Overview'!B:B) -> COGS (PL) | F58: -1178511
A59: 2024 | B59: 2211200002 | C59: 2024.10 | D59: October | E59: =_xlfn.XLOOKUP(tActuals_1[[#This Row],[Account]],'Account-Overview'!A:A,'Account-Overview'!B:B) -> COGS (PL) | F59: -1166665.6
A60: 2024 | B60: 2211200002 | C60: 2024.11 | D60: November | E60: =_xlfn.XLOOKUP(tActuals_1[[#This Row],[Account]],'Account-Overview'!A:A,'Account-Overview'!B:B) -> COGS (PL) | F60: -1349252
A61: 2024 | B61: 2211200002 | C61: 2024.12 | D61: December | E61: =_xlfn.XLOOKUP(tActuals_1[[#This Row],[Account]],'Account-Overview'!A:A,'Account-Overview'!B:B) -> COGS (PL) | F61: -1055502.8
A62: 2024 | B62: 2211200003 | C62: 2024.01 | D62: January | E62: =_xlfn.XLOOKUP(tActuals_1[[#This Row],[Account]],'Account-Overview'!A:A,'Account-Overview'!B:B) -> COGS (NL) | F62: -927479.01
A63: 2024 | B63: 2211200003 | C63: 2024.02 | D63: February | E63: =_xlfn.XLOOKUP(tActuals_1[[#This Row],[Account]],'Account-Overview'!A:A,'Account-Overview'!B:B) -> COGS (NL) | F63: -704715.47
... A466: 2025 | B466: 2616100000 | C466: 2025.03 | D466: March1 | E466: =_xlfn.XLOOKUP(tActuals_1[[#This Row],[Account]],'Account-Overview'!A:A,'Account-Overview'!B:B) -> Insurance (Others) | F466: -38153.678

Sheet P&L ACTUALS
A2: CATEGORY | B2: 2024.01 | C2: 2024.02 | D2: 2024.03 | E2: 2024.04 | F2: 2024.05 | G2: 2024.06 | H2: 2024.07 | I2: 2024.08 | J2: 2024.09 | K2: 2024.10 | L2: 2024.11 | M2: 2024.12 | N2: 2025.01 | O2: 2025.02 | P2: 2025.03 | Q2: 2025.04 | R2: 2025.05 | S2: 2025.06
A3: =tActuals!I12 -> Revenue (DE) | B3: =tActuals!J12 -> 15253265 | C3: =tActuals!K12 -> 21088786 | D3: =tActuals!L12 -> 28741336 | E3: =tActuals!M12 -> 26580933 | F3: =tActuals!N12 -> 23988357 | G3: =tActuals!O12 -> 19024409 | H3: =tActuals!P12 -> 14219294 | ... S3: =tActuals!AA12 -> 18521908
A4: =tActuals!I13 -> Revenue (NL) | B4: =tActuals!J13 -> 1501984.7 | C4: =tActuals!K13 -> 1151264 | D4: =tActuals!L13 -> 1470333.5 | E4: =tActuals!M13 -> 1628563.7 | F4: =tActuals!N13 -> 1562604.2 | G4: =tActuals!O13 -> 1485195.2 | H4: =tActuals!P13 -> 1131820.6 | ... S4: =tActuals!AA13 -> 1444158.7
A5: =tActuals!I14 -> Revenue (PL) | B5: =tActuals!J14 -> 1147673.5 | C5: =tActuals!K14 -> 1358569.8 | D5: =tActuals!L14 -> 1865549.3 | E5: =tActuals!M14 -> 1798307 | F5: =tActuals!N14 -> 1442012 | G5: =tActuals!O14 -> 1276426.2 | H5: =tActuals!P14 -> 924149.82 | ... S5: =tActuals!AA14 -> 1173863.2
A6: =tActuals!I15 -> REVENUE | B6: =tActuals!J15 -> 17902923 | C6: =tActuals!K15 -> 23598619 | D6: =tActuals!L15 -> 32077218 | E6: =tActuals!M15 -> 30007803 | F6: =tActuals!N15 -> 26992974 | G6: =tActuals!O15 -> 21786031 | H6: =tActuals!P15 -> 16275265 | ... S6: =tActuals!AA15 -> 21139929
A7: =tActuals!I16 -> COGS (DE) | B7: =tActuals!J16 -> -9336788.7 | C7: =tActuals!K16 -> -12888477 | D7: =tActuals!L16 -> -17560390 | E7: =tActuals!M16 -> -16154015 | F7: =tActuals!N16 -> -14572288 | G7: =tActuals!O16 -> -11649165 | H7: =tActuals!P16 -> -8686540.3 | ... S7: =tActuals!AA16 -> -11216654
A8: =tActuals!I17 -> COGS (NL) | B8: =tActuals!J17 -> -927479.01 | C8: =tActuals!K17 -> -704715.47 | D8: =tActuals!L17 -> -891741.66 | E8: =tActuals!M17 -> -997120.08 | F8: =tActuals!N17 -> -960150.55 | G8: =tActuals!O17 -> -920083.11 | H8: =tActuals!P17 -> -707533.23 | ... S8: =tActuals!AA17 -> -883462.25
A9: =tActuals!I18 -> COGS (PL) | B9: =tActuals!J18 -> -723645.01 | C9: =tActuals!K18 -> -851880.09 | D9: =tActuals!L18 -> -1172064.4 | E9: =tActuals!M18 -> -1119928.5 | F9: =tActuals!N18 -> -903671.54 | G9: =tActuals!O18 -> -811095.83 | H9: =tActuals!P18 -> -590189.53 | ... S9: =tActuals!AA18 -> -734792.93
A10: =tActuals!I19 -> COGS (Others) | B10: =tActuals!J19 -> -11398.766 | C10: =tActuals!K19 -> -8839.5313 | D10: =tActuals!L19 -> -11413.751 | E10: =tActuals!M19 -> -12483.943 | F10: =tActuals!N19 -> -11682.298 | G10: =tActuals!O19 -> -11405.387 | H10: =tActuals!P19 -> -8858.316 | ... S10: =tActuals!AA19 -> -11170.573
A11: =tActuals!I20 -> COGS | B11: =tActuals!J20 -> -10999312 | C11: =tActuals!K20 -> -14453912 | D11: =tActuals!L20 -> -19635609 | E11: =tActuals!M20 -> -18283548 | F11: =tActuals!N20 -> -16447792 | G11: =tActuals!O20 -> -13391749 | H11: =tActuals!P20 -> -9993121.4 | ... S11: =tActuals!AA20 -> -12846079
A12: =tActuals!I21 -> GROSS PROFIT | B12: =tActuals!J21 -> 6903611.9 | C12: =tActuals!K21 -> 9144707 | D12: =tActuals!L21 -> 12441609 | E12: =tActuals!M21 -> 11724256 | F12: =tActuals!N21 -> 10545181 | G12: =tActuals!O21 -> 8394281.6 | H12: =tActuals!P21 -> 6282143.3 | ... S12: =tActuals!AA21 -> 8293850.2
A13: =tActuals!I22 -> Payment (Credit Card) | B13: =tActuals!J22 -> -67059.167 | C13: =tActuals!K22 -> -87119.242 | D13: =tActuals!L22 -> -123829.24 | E13: =tActuals!M22 -> -118127.48 | F13: =tActuals!N22 -> -111368.2 | G13: =tActuals!O22 -> -89145.295 | H13: =tActuals!P22 -> -65228.703 | ... S13: =tActuals!AA22 -> -104151.27
A14: =tActuals!I23 -> Payment (PayPal) | B14: =tActuals!J23 -> -317875.15 | C14: =tActuals!K23 -> -409768.76 | D14: =tActuals!L23 -> -568307.74 | E14: =tActuals!M23 -> -511261.7 | F14: =tActuals!N23 -> -467668.53 | G14: =tActuals!O23 -> -381856.68 | H14: =tActuals!P23 -> -285451.9 | ... S14: =tActuals!AA23 -> -367756.22
... A42: =tActuals!I51 -> EBITDA | B42: =tActuals!J51 -> 13028.88 | C42: =tActuals!K51 -> 873043.63 | D42: =tActuals!L51 -> 2110234.7 | E42: =tActuals!M51 -> 2009576 | F42: =tActuals!N51 -> 1600280.8 | G42: =tActuals!O51 -> 839256.71 | H42: =tActuals!P51 -> 198708.63 | ... S42: =tActuals!AA51 -> 330700.68

Sheet P&L ACTUALS+EST
A2: CATEGORY | B2: 2024.01_act | C2: 2024.02_act | D2: 2024.03_act | E2: 2024.04_act | F2: 2024.05_act | G2: 2024.06_act | H2: 2024.07_act | I2: 2024.08_act | J2: 2024.09_act | K2: 2024.10_act | L2: 2024.11_act | M2: 2024.12_act | N2: 2025.01_act | O2: 2025.02_act | P2: 2025.03_act | Q2: 2025.04_act | R2: 2025.05_act | S2: 2025.06_act | T2: 2025.01_est | U2: 2025.02_est | V2: 2025.03_est | W2: 2025.04_est | X2: 2025.05_est | Y2: 2025.06_est
A3: REVENUE | B3: =_xlfn.XLOOKUP($A3,'P&L ACTUALS'!$A:$A,'P&L ACTUALS'!B:B,0) -> 17902923 | C3: =_xlfn.XLOOKUP($A3,'P&L ACTUALS'!$A:$A,'P&L ACTUALS'!C:C,0) -> 23598619 | D3: =_xlfn.XLOOKUP($A3,'P&L ACTUALS'!$A:$A,'P&L ACTUALS'!D:D,0) -> 32077218 | E3: =_xlfn.XLOOKUP($A3,'P&L ACTUALS'!$A:$A,'P&L ACTUALS'!E:E,0) -> 30007803 | F3: =_xlfn.XLOOKUP($A3,'P&L ACTUALS'!$A:$A,'P&L ACTUALS'!F:F,0) -> 26992974 | G3: =_xlfn.XLOOKUP($A3,'P&L ACTUALS'!$A:$A,'P&L ACTUALS'!G:G,0) -> 21786031 | H3: =_xlfn.XLOOKUP($A3,'P&L ACTUALS'!$A:$A,'P&L ACTUALS'!H:H,0) -> 16275265 | I3: =_xlfn.XLOOKUP($A3,'P&L ACTUALS'!$A:$A,'P&L ACTUALS'!I:I,0) -> 19576361 | J3: =_xlfn.XLOOKUP($A3,'P&L ACTUALS'!$A:$A,'P&L ACTUALS'!J:J,0) -> 33628318 | K3: =_xlfn.XLOOKUP($A3,'P&L ACTUALS'!$A:$A,'P&L ACTUALS'!K:K,0) -> 30816752 | L3: =_xlfn.XLOOKUP($A3,'P&L ACTUALS'!$A:$A,'P&L ACTUALS'!L:L,0) -> 33437036 | M3: =_xlfn.XLOOKUP($A3,'P&L ACTUALS'!$A:$A,'P&L ACTUALS'!M:M,0) -> 31446684 | N3: =_xlfn.XLOOKUP($A3,'P&L ACTUALS'!$A:$A,'P&L ACTUALS'!N:N,0) -> 18270177 | O3: =_xlfn.XLOOKUP($A3,'P&L ACTUALS'!$A:$A,'P&L ACTUALS'!O:O,0) -> 24091845 | P3: =_xlfn.XLOOKUP($A3,'P&L ACTUALS'!$A:$A,'P&L ACTUALS'!P:P,0) -> 29060428 | Q3: =_xlfn.XLOOKUP($A3,'P&L ACTUALS'!$A:$A,'P&L ACTUALS'!Q:Q,0) -> 21989689 | R3: =_xlfn.XLOOKUP($A3,'P&L ACTUALS'!$A:$A,'P&L ACTUALS'!R:R,0) -> 23404056 | S3: =_xlfn.XLOOKUP($A3,'P&L ACTUALS'!$A:$A,'P&L ACTUALS'!S:S,0) -> 21139929 | T3: =_xlfn.XLOOKUP(TRIM($A3),'Budget (from Controlling)_copy'!$B:$B,'Budget (from Controlling)_copy'!C:C,0) -> 18928135 | U3: =_xlfn.XLOOKUP(TRIM($A3),'Budget (from Controlling)_copy'!$B:$B,'Budget (from Controlling)_copy'!D:D,0) -> 24920142 | V3: =_xlfn.XLOOKUP(TRIM($A3),'Budget (from Controlling)_copy'!$B:$B,'Budget (from Controlling)_copy'!E:E,0) -> 33841465 | W3: =_xlfn.XLOOKUP(TRIM($A3),'Budget (from Controlling)_copy'!$B:$B,'Budget (from Controlling)_copy'!F:F,0) -> 31628225 | X3: =_xlfn.XLOOKUP(TRIM($A3),'Budget (from Controlling)_copy'!$B:$B,'Budget (from Controlling)_copy'!G:G,0) -> 28396608 | Y3: =_xlfn.XLOOKUP(TRIM($A3),'Budget (from Controlling)_copy'!$B:$B,'Budget (from Controlling)_copy'!H:H,0) -> 22853546
A4: COGS | B4: =_xlfn.XLOOKUP($A4,'P&L ACTUALS'!$A:$A,'P&L ACTUALS'!B:B,0) -> -10999312 | C4: =_xlfn.XLOOKUP($A4,'P&L ACTUALS'!$A:$A,'P&L ACTUALS'!C:C,0) -> -14453912 | D4: =_xlfn.XLOOKUP($A4,'P&L ACTUALS'!$A:$A,'P&L ACTUALS'!D:D,0) -> -19635609 | E4: =_xlfn.XLOOKUP($A4,'P&L ACTUALS'!$A:$A,'P&L ACTUALS'!E:E,0) -> -18283548 | F4: =_xlfn.XLOOKUP($A4,'P&L ACTUALS'!$A:$A,'P&L ACTUALS'!F:F,0) -> -16447792 | G4: =_xlfn.XLOOKUP($A4,'P&L ACTUALS'!$A:$A,'P&L ACTUALS'!G:G,0) -> -13391749 | H4: =_xlfn.XLOOKUP($A4,'P&L ACTUALS'!$A:$A,'P&L ACTUALS'!H:H,0) -> -9993121.4 | I4: =_xlfn.XLOOKUP($A4,'P&L ACTUALS'!$A:$A,'P&L ACTUALS'!I:I,0) -> -12007774 | J4: =_xlfn.XLOOKUP($A4,'P&L ACTUALS'!$A:$A,'P&L ACTUALS'!J:J,0) -> -20467743 | K4: =_xlfn.XLOOKUP($A4,'P&L ACTUALS'!$A:$A,'P&L ACTUALS'!K:K,0) -> -18727977 | L4: =_xlfn.XLOOKUP($A4,'P&L ACTUALS'!$A:$A,'P&L ACTUALS'!L:L,0) -> -20381831 | M4: =_xlfn.XLOOKUP($A4,'P&L ACTUALS'!$A:$A,'P&L ACTUALS'!M:M,0) -> -19239678 | N4: =_xlfn.XLOOKUP($A4,'P&L ACTUALS'!$A:$A,'P&L ACTUALS'!N:N,0) -> -11180488 | O4: =_xlfn.XLOOKUP($A4,'P&L ACTUALS'!$A:$A,'P&L ACTUALS'!O:O,0) -> -14710137 | P4: =_xlfn.XLOOKUP($A4,'P&L ACTUALS'!$A:$A,'P&L ACTUALS'!P:P,0) -> -17618863 | Q4: =_xlfn.XLOOKUP($A4,'P&L ACTUALS'!$A:$A,'P&L ACTUALS'!Q:Q,0) -> -13284156 | R4: =_xlfn.XLOOKUP($A4,'P&L ACTUALS'!$A:$A,'P&L ACTUALS'!R:R,0) -> -14091385 | S4: =_xlfn.XLOOKUP($A4,'P&L ACTUALS'!$A:$A,'P&L ACTUALS'!S:S,0) -> -12846079 | T4: =_xlfn.XLOOKUP(TRIM($A4),'Budget (from Controlling)_copy'!$B:$B,'Budget (from Controlling)_copy'!C:C,0) -> -11379261 | U4: =_xlfn.XLOOKUP(TRIM($A4),'Budget (from Controlling)_copy'!$B:$B,'Budget (from Controlling)_copy'!D:D,0) -> -14940672 | V4: =_xlfn.XLOOKUP(TRIM($A4),'Budget (from Controlling)_copy'!$B:$B,'Budget (from Controlling)_copy'!E:E,0) -> -20325399 | W4: =_xlfn.XLOOKUP(TRIM($A4),'Budget (from Controlling)_copy'!$B:$B,'Budget (from Controlling)_copy'!F:F,0) -> -18975129 | X4: =_xlfn.XLOOKUP(TRIM($A4),'Budget (from Controlling)_copy'!$B:$B,'Budget (from Controlling)_copy'!G:G,0) -> -17054296 | Y4: =_xlfn.XLOOKUP(TRIM($A4),'Budget (from Controlling)_copy'!$B:$B,'Budget (from Controlling)_copy'!H:H,0) -> -13728918
A5: GROSS PROFIT | B5: =_xlfn.XLOOKUP($A5,'P&L ACTUALS'!$A:$A,'P&L ACTUALS'!B:B,0) -> 6903611.9 | C5: =_xlfn.XLOOKUP($A5,'P&L ACTUALS'!$A:$A,'P&L ACTUALS'!C:C,0) -> 9144707 | D5: =_xlfn.XLOOKUP($A5,'P&L ACTUALS'!$A:$A,'P&L ACTUALS'!D:D,0) -> 12441609 | E5: =_xlfn.XLOOKUP($A5,'P&L ACTUALS'!$A:$A,'P&L ACTUALS'!E:E,0) -> 11724256 | F5: =_xlfn.XLOOKUP($A5,'P&L ACTUALS'!$A:$A,'P&L ACTUALS'!F:F,0) -> 10545181 | G5: =_xlfn.XLOOKUP($A5,'P&L ACTUALS'!$A:$A,'P&L ACTUALS'!G:G,0) -> 8394281.6 | H5: =_xlfn.XLOOKUP($A5,'P&L ACTUALS'!$A:$A,'P&L ACTUALS'!H:H,0) -> 6282143.3 | I5: =_xlfn.XLOOKUP($A5,'P&L ACTUALS'!$A:$A,'P&L ACTUALS'!I:I,0) -> 7568586.8 | J5: =_xlfn.XLOOKUP($A5,'P&L ACTUALS'!$A:$A,'P&L ACTUALS'!J:J,0) -> 13160576 | K5: =_xlfn.XLOOKUP($A5,'P&L ACTUALS'!$A:$A,'P&L ACTUALS'!K:K,0) -> 12088775 | L5: =_xlfn.XLOOKUP($A5,'P&L ACTUALS'!$A:$A,'P&L ACTUALS'!L:L,0) -> 13055205 | M5: =_xlfn.XLOOKUP($A5,'P&L ACTUALS'!$A:$A,'P&L ACTUALS'!M:M,0) -> 12207006 | N5: =_xlfn.XLOOKUP($A5,'P&L ACTUALS'!$A:$A,'P&L ACTUALS'!N:N,0) -> 7089689.1 | O5: =_xlfn.XLOOKUP($A5,'P&L ACTUALS'!$A:$A,'P&L ACTUALS'!O:O,0) -> 9381707.1 | P5: =_xlfn.XLOOKUP($A5,'P&L ACTUALS'!$A:$A,'P&L ACTUALS'!P:P,0) -> 11441565 | Q5: =_xlfn.XLOOKUP($A5,'P&L ACTUALS'!$A:$A,'P&L ACTUALS'!Q:Q,0) -> 8705533.2 | R5: =_xlfn.XLOOKUP($A5,'P&L ACTUALS'!$A:$A,'P&L ACTUALS'!R:R,0) -> 9312671.2 | S5: =_xlfn.XLOOKUP($A5,'P&L ACTUALS'!$A:$A,'P&L ACTUALS'!S:S,0) -> 8293850.2 | T5: =_xlfn.XLOOKUP(TRIM($A5),'Budget (from Controlling)_copy'!$B:$B,'Budget (from Controlling)_copy'!C:C,0) -> 7548874.2 | U5: =_xlfn.XLOOKUP(TRIM($A5),'Budget (from Controlling)_copy'!$B:$B,'Budget (from Controlling)_copy'!D:D,0) -> 9979469.8 | V5: =_xlfn.XLOOKUP(TRIM($A5),'Budget (from Controlling)_copy'!$B:$B,'Budget (from Controlling)_copy'!E:E,0) -> 13516066 | W5: =_xlfn.XLOOKUP(TRIM($A5),'Budget (from Controlling)_copy'!$B:$B,'Budget (from Controlling)_copy'!F:F,0) -> 12653096 | X5: =_xlfn.XLOOKUP(TRIM($A5),'Budget (from Controlling)_copy'!$B:$B,'Budget (from Controlling)_copy'!G:G,0) -> 11342312 | Y5: =_xlfn.XLOOKUP(TRIM($A5),'Budget (from Controlling)_copy'!$B:$B,'Budget (from Controlling)_copy'!H:H,0) -> 9124628
A6: PAYMENT | B6: =_xlfn.XLOOKUP($A6,'P&L ACTUALS'!$A:$A,'P&L ACTUALS'!B:B,0) -> -384934.32 | C6: =_xlfn.XLOOKUP($A6,'P&L ACTUALS'!$A:$A,'P&L ACTUALS'!C:C,0) -> -496888 | D6: =_xlfn.XLOOKUP($A6,'P&L ACTUALS'!$A:$A,'P&L ACTUALS'!D:D,0) -> -692136.98 | E6: =_xlfn.XLOOKUP($A6,'P&L ACTUALS'!$A:$A,'P&L ACTUALS'!E:E,0) -> -629389.18 | F6: =_xlfn.XLOOKUP($A6,'P&L ACTUALS'!$A:$A,'P&L ACTUALS'!F:F,0) -> -579036.72 | G6: =_xlfn.XLOOKUP($A6,'P&L ACTUALS'!$A:$A,'P&L ACTUALS'!G:G,0) -> -471001.98 | H6: =_xlfn.XLOOKUP($A6,'P&L ACTUALS'!$A:$A,'P&L ACTUALS'!H:H,0) -> -350680.6 | I6: =_xlfn.XLOOKUP($A6,'P&L ACTUALS'!$A:$A,'P&L ACTUALS'!I:I,0) -> -417497.95 | J6: =_xlfn.XLOOKUP($A6,'P&L ACTUALS'!$A:$A,'P&L ACTUALS'!J:J,0) -> -709864.75 | K6: =_xlfn.XLOOKUP($A6,'P&L ACTUALS'!$A:$A,'P&L ACTUALS'!K:K,0) -> -666382.09 | L6: =_xlfn.XLOOKUP($A6,'P&L ACTUALS'!$A:$A,'P&L ACTUALS'!L:L,0) -> -710725.17 | M6: =_xlfn.XLOOKUP($A6,'P&L ACTUALS'!$A:$A,'P&L ACTUALS'!M:M,0) -> -672713.93 | N6: =_xlfn.XLOOKUP($A6,'P&L ACTUALS'!$A:$A,'P&L ACTUALS'!N:N,0) -> -404217.34 | O6: =_xlfn.XLOOKUP($A6,'P&L ACTUALS'!$A:$A,'P&L ACTUALS'!O:O,0) -> -535002.49 | P6: =_xlfn.XLOOKUP($A6,'P&L ACTUALS'!$A:$A,'P&L ACTUALS'!P:P,0) -> -651196.97 | Q6: =_xlfn.XLOOKUP($A6,'P&L ACTUALS'!$A:$A,'P&L ACTUALS'!Q:Q,0) -> -492802.62 | R6: =_xlfn.XLOOKUP($A6,'P&L ACTUALS'!$A:$A,'P&L ACTUALS'!R:R,0) -> -524343.77 | S6: =_xlfn.XLOOKUP($A6,'P&L ACTUALS'!$A:$A,'P&L ACTUALS'!S:S,0) -> -471907.49 | T6: =_xlfn.XLOOKUP(TRIM($A6),'Budget (from Controlling)_copy'!$B:$B,'Budget (from Controlling)_copy'!C:C,0) -> -425933.52 | U6: =_xlfn.XLOOKUP(TRIM($A6),'Budget (from Controlling)_copy'!$B:$B,'Budget (from Controlling)_copy'!D:D,0) -> -560769.66 | V6: =_xlfn.XLOOKUP(TRIM($A6),'Budget (from Controlling)_copy'!$B:$B,'Budget (from Controlling)_copy'!E:E,0) -> -761523.23 | W6: =_xlfn.XLOOKUP(TRIM($A6),'Budget (from Controlling)_copy'!$B:$B,'Budget (from Controlling)_copy'!F:F,0) -> -711719.41 | X6: =_xlfn.XLOOKUP(TRIM($A6),'Budget (from Controlling)_copy'!$B:$B,'Budget (from Controlling)_copy'!G:G,0) -> -638999.42 | Y6: =_xlfn.XLOOKUP(TRIM($A6),'Budget (from Controlling)_copy'!$B:$B,'Budget (from Controlling)_copy'!H:H,0) -> -514265.74
A7: WAREHOUSE | B7: =_xlfn.XLOOKUP($A7,'P&L ACTUALS'!$A:$A,'P&L ACTUALS'!B:B,0) -> -1470207.6 | C7: =_xlfn.XLOOKUP($A7,'P&L ACTUALS'!$A:$A,'P&L ACTUALS'!C:C,0) -> -1932725.4 | D7: =_xlfn.XLOOKUP($A7,'P&L ACTUALS'!$A:$A,'P&L ACTUALS'!D:D,0) -> -2446516.2 | E7: =_xlfn.XLOOKUP($A7,'P&L ACTUALS'!$A:$A,'P&L ACTUALS'!E:E,0) -> -2307060.7 | F7: =_xlfn.XLOOKUP($A7,'P&L ACTUALS'!$A:$A,'P&L ACTUALS'!F:F,0) -> -2092614.8 | G7: =_xlfn.XLOOKUP($A7,'P&L ACTUALS'!$A:$A,'P&L ACTUALS'!G:G,0) -> -1618297.1 | H7: =_xlfn.XLOOKUP($A7,'P&L ACTUALS'!$A:$A,'P&L ACTUALS'!H:H,0) -> -1227654.4 | I7: =_xlfn.XLOOKUP($A7,'P&L ACTUALS'!$A:$A,'P&L ACTUALS'!I:I,0) -> -1435279 | J7: =_xlfn.XLOOKUP($A7,'P&L ACTUALS'!$A:$A,'P&L ACTUALS'!J:J,0) -> -2829668 | K7: =_xlfn.XLOOKUP($A7,'P&L ACTUALS'!$A:$A,'P&L ACTUALS'!K:K,0) -> -2625300.9 | L7: =_xlfn.XLOOKUP($A7,'P&L ACTUALS'!$A:$A,'P&L ACTUALS'!L:L,0) -> -2833430 | M7: =_xlfn.XLOOKUP($A7,'P&L ACTUALS'!$A:$A,'P&L ACTUALS'!M:M,0) -> -2614443.6 | N7: =_xlfn.XLOOKUP($A7,'P&L ACTUALS'!$A:$A,'P&L ACTUALS'!N:N,0) -> -1830023.9 | O7: =_xlfn.XLOOKUP($A7,'P&L ACTUALS'!$A:$A,'P&L ACTUALS'!O:O,0) -> -2405737.7 | P7: =_xlfn.XLOOKUP($A7,'P&L ACTUALS'!$A:$A,'P&L ACTUALS'!P:P,0) -> -2768479.8 | Q7: =_xlfn.XLOOKUP($A7,'P&L ACTUALS'!$A:$A,'P&L ACTUALS'!Q:Q,0) -> -2084666.6 | R7: =_xlfn.XLOOKUP($A7,'P&L ACTUALS'!$A:$A,'P&L ACTUALS'!R:R,0) -> -2202174.6 | S7: =_xlfn.XLOOKUP($A7,'P&L ACTUALS'!$A:$A,'P&L ACTUALS'!S:S,0) -> -1982751.8 | T7: =_xlfn.XLOOKUP(TRIM($A7),'Budget (from Controlling)_copy'!$B:$B,'Budget (from Controlling)_copy'!C:C,0) -> -1666186.2 | U7: =_xlfn.XLOOKUP(TRIM($A7),'Budget (from Controlling)_copy'!$B:$B,'Budget (from Controlling)_copy'!D:D,0) -> -2162748 | V7: =_xlfn.XLOOKUP(TRIM($A7),'Budget (from Controlling)_copy'!$B:$B,'Budget (from Controlling)_copy'!E:E,0) -> -2853089.8 | W7: =_xlfn.XLOOKUP(TRIM($A7),'Budget (from Controlling)_copy'!$B:$B,'Budget (from Controlling)_copy'!F:F,0) -> -2627283.8 | X7: =_xlfn.XLOOKUP(TRIM($A7),'Budget (from Controlling)_copy'!$B:$B,'Budget (from Controlling)_copy'!G:G,0) -> -2288427.7 | Y7: =_xlfn.XLOOKUP(TRIM($A7),'Budget (from Controlling)_copy'!$B:$B,'Budget (from Controlling)_copy'!H:H,0) -> -1841723
A8: DISTRIBUTION | B8: =_xlfn.XLOOKUP($A8,'P&L ACTUALS'!$A:$A,'P&L ACTUALS'!B:B,0) -> -2697687 | C8: =_xlfn.XLOOKUP($A8,'P&L ACTUALS'!$A:$A,'P&L ACTUALS'!C:C,0) -> -3505939.2 | D8: =_xlfn.XLOOKUP($A8,'P&L ACTUALS'!$A:$A,'P&L ACTUALS'!D:D,0) -> -4722572.6 | E8: =_xlfn.XLOOKUP($A8,'P&L ACTUALS'!$A:$A,'P&L ACTUALS'!E:E,0) -> -4336663.6 | F8: =_xlfn.XLOOKUP($A8,'P&L ACTUALS'!$A:$A,'P&L ACTUALS'!F:F,0) -> -3914189.3 | G8: =_xlfn.XLOOKUP($A8,'P&L ACTUALS'!$A:$A,'P&L ACTUALS'!G:G,0) -> -3097761.2 | H8: =_xlfn.XLOOKUP($A8,'P&L ACTUALS'!$A:$A,'P&L ACTUALS'!H:H,0) -> -2288515.4 | I8: =_xlfn.XLOOKUP($A8,'P&L ACTUALS'!$A:$A,'P&L ACTUALS'!I:I,0) -> -2714440.5 | J8: =_xlfn.XLOOKUP($A8,'P&L ACTUALS'!$A:$A,'P&L ACTUALS'!J:J,0) -> -5130950.6 | K8: =_xlfn.XLOOKUP($A8,'P&L ACTUALS'!$A:$A,'P&L ACTUALS'!K:K,0) -> -4803835.9 | L8: =_xlfn.XLOOKUP($A8,'P&L ACTUALS'!$A:$A,'P&L ACTUALS'!L:L,0) -> -5156302.7 | M8: =_xlfn.XLOOKUP($A8,'P&L ACTUALS'!$A:$A,'P&L ACTUALS'!M:M,0) -> -4771220.7 | N8: =_xlfn.XLOOKUP($A8,'P&L ACTUALS'!$A:$A,'P&L ACTUALS'!N:N,0) -> -2934147.4 | O8: =_xlfn.XLOOKUP($A8,'P&L ACTUALS'!$A:$A,'P&L ACTUALS'!O:O,0) -> -3818240.3 | P8: =_xlfn.XLOOKUP($A8,'P&L ACTUALS'!$A:$A,'P&L ACTUALS'!P:P,0) -> -4464968.2 | Q8: =_xlfn.XLOOKUP($A8,'P&L ACTUALS'!$A:$A,'P&L ACTUALS'!Q:Q,0) -> -3341724.1 | R8: =_xlfn.XLOOKUP($A8,'P&L ACTUALS'!$A:$A,'P&L ACTUALS'!R:R,0) -> -3570895.9 | S8: =_xlfn.XLOOKUP($A8,'P&L ACTUALS'!$A:$A,'P&L ACTUALS'!S:S,0) -> -3199221.3 | T8: =_xlfn.XLOOKUP(TRIM($A8),'Budget (from Controlling)_copy'!$B:$B,'Budget (from Controlling)_copy'!C:C,0) -> -2929859.4 | U8: =_xlfn.XLOOKUP(TRIM($A8),'Budget (from Controlling)_copy'!$B:$B,'Budget (from Controlling)_copy'!D:D,0) -> -3825209.2 | V8: =_xlfn.XLOOKUP(TRIM($A8),'Budget (from Controlling)_copy'!$B:$B,'Budget (from Controlling)_copy'!E:E,0) -> -5107316.1 | W8: =_xlfn.XLOOKUP(TRIM($A8),'Budget (from Controlling)_copy'!$B:$B,'Budget (from Controlling)_copy'!F:F,0) -> -4732498.8 | X8: =_xlfn.XLOOKUP(TRIM($A8),'Budget (from Controlling)_copy'!$B:$B,'Budget (from Controlling)_copy'!G:G,0) -> -4248955.4 | Y8: =_xlfn.XLOOKUP(TRIM($A8),'Budget (from Controlling)_copy'!$B:$B,'Budget (from Controlling)_copy'!H:H,0) -> -3331116
A9: VARIABLE COSTS | B9: =_xlfn.XLOOKUP($A9,'P&L ACTUALS'!$A:$A,'P&L ACTUALS'!B:B,0) -> -4552828.9 | C9: =_xlfn.XLOOKUP($A9,'P&L ACTUALS'!$A:$A,'P&L ACTUALS'!C:C,0) -> -5935552.6 | D9: =_xlfn.XLOOKUP($A9,'P&L ACTUALS'!$A:$A,'P&L ACTUALS'!D:D,0) -> -7861225.8 | E9: =_xlfn.XLOOKUP($A9,'P&L ACTUALS'!$A:$A,'P&L ACTUALS'!E:E,0) -> -7273113.5 | F9: =_xlfn.XLOOKUP($A9,'P&L ACTUALS'!$A:$A,'P&L ACTUALS'!F:F,0) -> -6585840.8 | G9: =_xlfn.XLOOKUP($A9,'P&L ACTUALS'!$A:$A,'P&L ACTUALS'!G:G,0) -> -5187060.3 | H9: =_xlfn.XLOOKUP($A9,'P&L ACTUALS'!$A:$A,'P&L ACTUALS'!H:H,0) -> -3866850.4 | I9: =_xlfn.XLOOKUP($A9,'P&L ACTUALS'!$A:$A,'P&L ACTUALS'!I:I,0) -> -4567217.4 | J9: =_xlfn.XLOOKUP($A9,'P&L ACTUALS'!$A:$A,'P&L ACTUALS'!J:J,0) -> -8670483.4 | K9: =_xlfn.XLOOKUP($A9,'P&L ACTUALS'!$A:$A,'P&L ACTUALS'!K:K,0) -> -8095518.9 | L9: =_xlfn.XLOOKUP($A9,'P&L ACTUALS'!$A:$A,'P&L ACTUALS'!L:L,0) -> -8700457.8 | M9: =_xlfn.XLOOKUP($A9,'P&L ACTUALS'!$A:$A,'P&L ACTUALS'!M:M,0) -> -8058378.2 | N9: =_xlfn.XLOOKUP($A9,'P&L ACTUALS'!$A:$A,'P&L ACTUALS'!N:N,0) -> -5168388.6 | O9: =_xlfn.XLOOKUP($A9,'P&L ACTUALS'!$A:$A,'P&L ACTUALS'!O:O,0) -> -6758980.5 | P9: =_xlfn.XLOOKUP($A9,'P&L ACTUALS'!$A:$A,'P&L ACTUALS'!P:P,0) -> -7884645 | Q9: =_xlfn.XLOOKUP($A9,'P&L ACTUALS'!$A:$A,'P&L ACTUALS'!Q:Q,0) -> -5919193.3 | R9: =_xlfn.XLOOKUP($A9,'P&L ACTUALS'!$A:$A,'P&L ACTUALS'!R:R,0) -> -6297414.3 | S9: =_xlfn.XLOOKUP($A9,'P&L ACTUALS'!$A:$A,'P&L ACTUALS'!S:S,0) -> -5653880.6 | T9: =_xlfn.XLOOKUP(TRIM($A9),'Budget (from Controlling)_copy'!$B:$B,'Budget (from Controlling)_copy'!C:C,0) -> -5021979.2 | U9: =_xlfn.XLOOKUP(TRIM($A9),'Budget (from Controlling)_copy'!$B:$B,'Budget (from Controlling)_copy'!D:D,0) -> -6548726.8 | V9: =_xlfn.XLOOKUP(TRIM($A9),'Budget (from Controlling)_copy'!$B:$B,'Budget (from Controlling)_copy'!E:E,0) -> -8721929.1 | W9: =_xlfn.XLOOKUP(TRIM($A9),'Budget (from Controlling)_copy'!$B:$B,'Budget (from Controlling)_copy'!F:F,0) -> -8071502 | X9: =_xlfn.XLOOKUP(TRIM($A9),'Budget (from Controlling)_copy'!$B:$B,'Budget (from Controlling)_copy'!G:G,0) -> -7176382.5 | Y9: =_xlfn.XLOOKUP(TRIM($A9),'Budget (from Controlling)_copy'!$B:$B,'Budget (from Controlling)_copy'!H:H,0) -> -5687104.7
A10: CONTRIBUTION PROFIT | B10: =_xlfn.XLOOKUP($A10,'P&L ACTUALS'!$A:$A,'P&L ACTUALS'!B:B,0) -> 2350783 | C10: =_xlfn.XLOOKUP($A10,'P&L ACTUALS'!$A:$A,'P&L ACTUALS'!C:C,0) -> 3209154.4 | D10: =_xlfn.XLOOKUP($A10,'P&L ACTUALS'!$A:$A,'P&L ACTUALS'!D:D,0) -> 4580383.3 | E10: =_xlfn.XLOOKUP($A10,'P&L ACTUALS'!$A:$A,'P&L ACTUALS'!E:E,0) -> 4451142.2 | F10: =_xlfn.XLOOKUP($A10,'P&L ACTUALS'!$A:$A,'P&L ACTUALS'!F:F,0) -> 3959340.7 | G10: =_xlfn.XLOOKUP($A10,'P&L ACTUALS'!$A:$A,'P&L ACTUALS'!G:G,0) -> 3207221.3 | H10: =_xlfn.XLOOKUP($A10,'P&L ACTUALS'!$A:$A,'P&L ACTUALS'!H:H,0) -> 2415292.9 | I10: =_xlfn.XLOOKUP($A10,'P&L ACTUALS'!$A:$A,'P&L ACTUALS'!I:I,0) -> 3001369.4 | J10: =_xlfn.XLOOKUP($A10,'P&L ACTUALS'!$A:$A,'P&L ACTUALS'!J:J,0) -> 4490092.1 | K10: =_xlfn.XLOOKUP($A10,'P&L ACTUALS'!$A:$A,'P&L ACTUALS'!K:K,0) -> 3993256.1 | L10: =_xlfn.XLOOKUP($A10,'P&L ACTUALS'!$A:$A,'P&L ACTUALS'!L:L,0) -> 4354747 | M10: =_xlfn.XLOOKUP($A10,'P&L ACTUALS'!$A:$A,'P&L ACTUALS'!M:M,0) -> 4148627.5 | N10: =_xlfn.XLOOKUP($A10,'P&L ACTUALS'!$A:$A,'P&L ACTUALS'!N:N,0) -> 1921300.4 | O10: =_xlfn.XLOOKUP($A10,'P&L ACTUALS'!$A:$A,'P&L ACTUALS'!O:O,0) -> 2622726.6 | P10: =_xlfn.XLOOKUP($A10,'P&L ACTUALS'!$A:$A,'P&L ACTUALS'!P:P,0) -> 3556920.2 | Q10: =_xlfn.XLOOKUP($A10,'P&L ACTUALS'!$A:$A,'P&L ACTUALS'!Q:Q,0) -> 2786339.9 | R10: =_xlfn.XLOOKUP($A10,'P&L ACTUALS'!$A:$A,'P&L ACTUALS'!R:R,0) -> 3015256.9 | S10: =_xlfn.XLOOKUP($A10,'P&L ACTUALS'!$A:$A,'P&L ACTUALS'!S:S,0) -> 2639969.6 | T10: =_xlfn.XLOOKUP(TRIM($A10),'Budget (from Controlling)_copy'!$B:$B,'Budget (from Controlling)_copy'!C:C,0) -> 2526895 | U10: =_xlfn.XLOOKUP(TRIM($A10),'Budget (from Controlling)_copy'!$B:$B,'Budget (from Controlling)_copy'!D:D,0) -> 3430743 | V10: =_xlfn.XLOOKUP(TRIM($A10),'Budget (from Controlling)_copy'!$B:$B,'Budget (from Controlling)_copy'!E:E,0) -> 4794137 | W10: =_xlfn.XLOOKUP(TRIM($A10),'Budget (from Controlling)_copy'!$B:$B,'Budget (from Controlling)_copy'!F:F,0) -> 4581593.7 | X10: =_xlfn.XLOOKUP(TRIM($A10),'Budget (from Controlling)_copy'!$B:$B,'Budget (from Controlling)_copy'!G:G,0) -> 4165929.9 | Y10: =_xlfn.XLOOKUP(TRIM($A10),'Budget (from Controlling)_copy'!$B:$B,'Budget (from Controlling)_copy'!H:H,0) -> 3437523.3
A11: LABOUR | B11: =_xlfn.XLOOKUP($A11,'P&L ACTUALS'!$A:$A,'P&L ACTUALS'!B:B,0) -> -1555136.1 | C11: =_xlfn.XLOOKUP($A11,'P&L ACTUALS'!$A:$A,'P&L ACTUALS'!C:C,0) -> -1562598.6 | D11: =_xlfn.XLOOKUP($A11,'P&L ACTUALS'!$A:$A,'P&L ACTUALS'!D:D,0) -> -1567812 | E11: =_xlfn.XLOOKUP($A11,'P&L ACTUALS'!$A:$A,'P&L ACTUALS'!E:E,0) -> -1544263.2 | F11: =_xlfn.XLOOKUP($A11,'P&L ACTUALS'!$A:$A,'P&L ACTUALS'!F:F,0) -> -1539991.1 | G11: =_xlfn.XLOOKUP($A11,'P&L ACTUALS'!$A:$A,'P&L ACTUALS'!G:G,0) -> -1548088.8 | H11: =_xlfn.XLOOKUP($A11,'P&L ACTUALS'!$A:$A,'P&L ACTUALS'!H:H,0) -> -1538853.5 | I11: =_xlfn.XLOOKUP($A11,'P&L ACTUALS'!$A:$A,'P&L ACTUALS'!I:I,0) -> -1543126.5 | J11: =_xlfn.XLOOKUP($A11,'P&L ACTUALS'!$A:$A,'P&L ACTUALS'!J:J,0) -> -1598615.1 | K11: =_xlfn.XLOOKUP($A11,'P&L ACTUALS'!$A:$A,'P&L ACTUALS'!K:K,0) -> -1579763.5 | L11: =_xlfn.XLOOKUP($A11,'P&L ACTUALS'!$A:$A,'P&L ACTUALS'!L:L,0) -> -1580422.9 | M11: =_xlfn.XLOOKUP($A11,'P&L ACTUALS'!$A:$A,'P&L ACTUALS'!M:M,0) -> -1671264.7 | N11: =_xlfn.XLOOKUP($A11,'P&L ACTUALS'!$A:$A,'P&L ACTUALS'!N:N,0) -> -1573719.8 | O11: =_xlfn.XLOOKUP($A11,'P&L ACTUALS'!$A:$A,'P&L ACTUALS'!O:O,0) -> -1593334 | P11: =_xlfn.XLOOKUP($A11,'P&L ACTUALS'!$A:$A,'P&L ACTUALS'!P:P,0) -> -1595185.7 | Q11: =_xlfn.XLOOKUP($A11,'P&L ACTUALS'!$A:$A,'P&L ACTUALS'!Q:Q,0) -> -1591764.3 | R11: =_xlfn.XLOOKUP($A11,'P&L ACTUALS'!$A:$A,'P&L ACTUALS'!R:R,0) -> -1581072.6 | S11: =_xlfn.XLOOKUP($A11,'P&L ACTUALS'!$A:$A,'P&L ACTUALS'!S:S,0) -> -1592239.5 | T11: =_xlfn.XLOOKUP(TRIM($A11),'Budget (from Controlling)_copy'!$B:$B,'Budget (from Controlling)_copy'!C:C,0) -> -1539741.9 | U11: =_xlfn.XLOOKUP(TRIM($A11),'Budget (from Controlling)_copy'!$B:$B,'Budget (from Controlling)_copy'!D:D,0) -> -1539741.9 | V11: =_xlfn.XLOOKUP(TRIM($A11),'Budget (from Controlling)_copy'!$B:$B,'Budget (from Controlling)_copy'!E:E,0) -> -1539741.9 | W11: =_xlfn.XLOOKUP(TRIM($A11),'Budget (from Controlling)_copy'!$B:$B,'Budget (from Controlling)_copy'!F:F,0) -> -1539741.9 | X11: =_xlfn.XLOOKUP(TRIM($A11),'Budget (from Controlling)_copy'!$B:$B,'Budget (from Controlling)_copy'!G:G,0) -> -1539741.9 | Y11: =_xlfn.XLOOKUP(TRIM($A11),'Budget (from Controlling)_copy'!$B:$B,'Budget (from Controlling)_copy'!H:H,0) -> -1539741.9
A12: MARKETING | B12: =_xlfn.XLOOKUP($A12,'P&L ACTUALS'!$A:$A,'P&L ACTUALS'!B:B,0) -> -555504.44 | C12: =_xlfn.XLOOKUP($A12,'P&L ACTUALS'!$A:$A,'P&L ACTUALS'!C:C,0) -> -611920.61 | D12: =_xlfn.XLOOKUP($A12,'P&L ACTUALS'!$A:$A,'P&L ACTUALS'!D:D,0) -> -712614.07 | E12: =_xlfn.XLOOKUP($A12,'P&L ACTUALS'!$A:$A,'P&L ACTUALS'!E:E,0) -> -746636.61 | F12: =_xlfn.XLOOKUP($A12,'P&L ACTUALS'!$A:$A,'P&L ACTUALS'!F:F,0) -> -671683.76 | G12: =_xlfn.XLOOKUP($A12,'P&L ACTUALS'!$A:$A,'P&L ACTUALS'!G:G,0) -> -634858.82 | H12: =_xlfn.XLOOKUP($A12,'P&L ACTUALS'!$A:$A,'P&L ACTUALS'!H:H,0) -> -514634.99 | I12: =_xlfn.XLOOKUP($A12,'P&L ACTUALS'!$A:$A,'P&L ACTUALS'!I:I,0) -> -467551.58 | J12: =_xlfn.XLOOKUP($A12,'P&L ACTUALS'!$A:$A,'P&L ACTUALS'!J:J,0) -> -744992.51 | K12: =_xlfn.XLOOKUP($A12,'P&L ACTUALS'!$A:$A,'P&L ACTUALS'!K:K,0) -> -974337.13 | L12: =_xlfn.XLOOKUP($A12,'P&L ACTUALS'!$A:$A,'P&L ACTUALS'!L:L,0) -> -870296.33 | M12: =_xlfn.XLOOKUP($A12,'P&L ACTUALS'!$A:$A,'P&L ACTUALS'!M:M,0) -> -645070.51 | N12: =_xlfn.XLOOKUP($A12,'P&L ACTUALS'!$A:$A,'P&L ACTUALS'!N:N,0) -> -573154.51 | O12: =_xlfn.XLOOKUP($A12,'P&L ACTUALS'!$A:$A,'P&L ACTUALS'!O:O,0) -> -605023.02 | P12: =_xlfn.XLOOKUP($A12,'P&L ACTUALS'!$A:$A,'P&L ACTUALS'!P:P,0) -> -684557.04 | Q12: =_xlfn.XLOOKUP($A12,'P&L ACTUALS'!$A:$A,'P&L ACTUALS'!Q:Q,0) -> -651867.47 | R12: =_xlfn.XLOOKUP($A12,'P&L ACTUALS'!$A:$A,'P&L ACTUALS'!R:R,0) -> -566308.5 | S12: =_xlfn.XLOOKUP($A12,'P&L ACTUALS'!$A:$A,'P&L ACTUALS'!S:S,0) -> -555936.72 | T12: =_xlfn.XLOOKUP(TRIM($A12),'Budget (from Controlling)_copy'!$B:$B,'Budget (from Controlling)_copy'!C:C,0) -> -594389.75 | U12: =_xlfn.XLOOKUP(TRIM($A12),'Budget (from Controlling)_copy'!$B:$B,'Budget (from Controlling)_copy'!D:D,0) -> -654755.05 | V12: =_xlfn.XLOOKUP(TRIM($A12),'Budget (from Controlling)_copy'!$B:$B,'Budget (from Controlling)_copy'!E:E,0) -> -762497.05 | W12: =_xlfn.XLOOKUP(TRIM($A12),'Budget (from Controlling)_copy'!$B:$B,'Budget (from Controlling)_copy'!F:F,0) -> -798901.17 | X12: =_xlfn.XLOOKUP(TRIM($A12),'Budget (from Controlling)_copy'!$B:$B,'Budget (from Controlling)_copy'!G:G,0) -> -718701.62 | Y12: =_xlfn.XLOOKUP(TRIM($A12),'Budget (from Controlling)_copy'!$B:$B,'Budget (from Controlling)_copy'!H:H,0) -> -679298.94
A13: RENT | B13: =_xlfn.XLOOKUP($A13,'P&L ACTUALS'!$A:$A,'P&L ACTUALS'!B:B,0) -> -97865.596 | C13: =_xlfn.XLOOKUP($A13,'P&L ACTUALS'!$A:$A,'P&L ACTUALS'!C:C,0) -> -97865.596 | D13: =_xlfn.XLOOKUP($A13,'P&L ACTUALS'!$A:$A,'P&L ACTUALS'!D:D,0) -> -97605.447 | E13: =_xlfn.XLOOKUP($A13,'P&L ACTUALS'!$A:$A,'P&L ACTUALS'!E:E,0) -> -97605.447 | F13: =_xlfn.XLOOKUP($A13,'P&L ACTUALS'!$A:$A,'P&L ACTUALS'!F:F,0) -> -97605.447 | G13: =_xlfn.XLOOKUP($A13,'P&L ACTUALS'!$A:$A,'P&L ACTUALS'!G:G,0) -> -97610.712 | H13: =_xlfn.XLOOKUP($A13,'P&L ACTUALS'!$A:$A,'P&L ACTUALS'!H:H,0) -> -97793.229 | I13: =_xlfn.XLOOKUP($A13,'P&L ACTUALS'!$A:$A,'P&L ACTUALS'!I:I,0) -> -97961.043 | J13: =_xlfn.XLOOKUP($A13,'P&L ACTUALS'!$A:$A,'P&L ACTUALS'!J:J,0) -> -97755.343 | K13: =_xlfn.XLOOKUP($A13,'P&L ACTUALS'!$A:$A,'P&L ACTUALS'!K:K,0) -> -97755.343 | L13: =_xlfn.XLOOKUP($A13,'P&L ACTUALS'!$A:$A,'P&L ACTUALS'!L:L,0) -> -97755.343 | M13: =_xlfn.XLOOKUP($A13,'P&L ACTUALS'!$A:$A,'P&L ACTUALS'!M:M,0) -> -97755.343 | N13: =_xlfn.XLOOKUP($A13,'P&L ACTUALS'!$A:$A,'P&L ACTUALS'!N:N,0) -> -96777.79 | O13: =_xlfn.XLOOKUP($A13,'P&L ACTUALS'!$A:$A,'P&L ACTUALS'!O:O,0) -> -96777.79 | P13: =_xlfn.XLOOKUP($A13,'P&L ACTUALS'!$A:$A,'P&L ACTUALS'!P:P,0) -> -96777.79 | Q13: =_xlfn.XLOOKUP($A13,'P&L ACTUALS'!$A:$A,'P&L ACTUALS'!Q:Q,0) -> -96777.79 | R13: =_xlfn.XLOOKUP($A13,'P&L ACTUALS'!$A:$A,'P&L ACTUALS'!R:R,0) -> -96777.79 | S13: =_xlfn.XLOOKUP($A13,'P&L ACTUALS'!$A:$A,'P&L ACTUALS'!S:S,0) -> -96777.79 | T13: =_xlfn.XLOOKUP(TRIM($A13),'Budget (from Controlling)_copy'!$B:$B,'Budget (from Controlling)_copy'!C:C,0) -> -98844.252 | U13: =_xlfn.XLOOKUP(TRIM($A13),'Budget (from Controlling)_copy'!$B:$B,'Budget (from Controlling)_copy'!D:D,0) -> -98844.252 | V13: =_xlfn.XLOOKUP(TRIM($A13),'Budget (from Controlling)_copy'!$B:$B,'Budget (from Controlling)_copy'!E:E,0) -> -98581.501 | W13: =_xlfn.XLOOKUP(TRIM($A13),'Budget (from Controlling)_copy'!$B:$B,'Budget (from Controlling)_copy'!F:F,0) -> -98581.501 | X13: =_xlfn.XLOOKUP(TRIM($A13),'Budget (from Controlling)_copy'!$B:$B,'Budget (from Controlling)_copy'!G:G,0) -> -98581.501 | Y13: =_xlfn.XLOOKUP(TRIM($A13),'Budget (from Controlling)_copy'!$B:$B,'Budget (from Controlling)_copy'!H:H,0) -> -98586.819
A14: TRAVEL | B14: =_xlfn.XLOOKUP($A14,'P&L ACTUALS'!$A:$A,'P&L ACTUALS'!B:B,0) -> -12827.643 | C14: =_xlfn.XLOOKUP($A14,'P&L ACTUALS'!$A:$A,'P&L ACTUALS'!C:C,0) -> -8990.7803 | D14: =_xlfn.XLOOKUP($A14,'P&L ACTUALS'!$A:$A,'P&L ACTUALS'!D:D,0) -> 0 | E14: =_xlfn.XLOOKUP($A14,'P&L ACTUALS'!$A:$A,'P&L ACTUALS'!E:E,0) -> -3847.8 | F14: =_xlfn.XLOOKUP($A14,'P&L ACTUALS'!$A:$A,'P&L ACTUALS'!F:F,0) -> -7295.2231 | G14: =_xlfn.XLOOKUP($A14,'P&L ACTUALS'!$A:$A,'P&L ACTUALS'!G:G,0) -> -7630.381 | H14: =_xlfn.XLOOKUP($A14,'P&L ACTUALS'!$A:$A,'P&L ACTUALS'!H:H,0) -> -10130.798 | I14: =_xlfn.XLOOKUP($A14,'P&L ACTUALS'!$A:$A,'P&L ACTUALS'!I:I,0) -> -1985.7673 | J14: =_xlfn.XLOOKUP($A14,'P&L ACTUALS'!$A:$A,'P&L ACTUALS'!J:J,0) -> 0 | K14: =_xlfn.XLOOKUP($A14,'P&L ACTUALS'!$A:$A,'P&L ACTUALS'!K:K,0) -> -10368.163 | L14: =_xlfn.XLOOKUP($A14,'P&L ACTUALS'!$A:$A,'P&L ACTUALS'!L:L,0) -> -5253.4328 | M14: =_xlfn.XLOOKUP($A14,'P&L ACTUALS'!$A:$A,'P&L ACTUALS'!M:M,0) -> -6869.533 | N14: =_xlfn.XLOOKUP($A14,'P&L ACTUALS'!$A:$A,'P&L ACTUALS'!N:N,0) -> -12843.86 | O14: =_xlfn.XLOOKUP($A14,'P&L ACTUALS'!$A:$A,'P&L ACTUALS'!O:O,0) -> -9002.1466 | P14: =_xlfn.XLOOKUP($A14,'P&L ACTUALS'!$A:$A,'P&L ACTUALS'!P:P,0) -> -674.07031 | Q14: =_xlfn.XLOOKUP($A14,'P&L ACTUALS'!$A:$A,'P&L ACTUALS'!Q:Q,0) -> -782.94744 | R14: =_xlfn.XLOOKUP($A14,'P&L ACTUALS'!$A:$A,'P&L ACTUALS'!R:R,0) -> -1103.4935 | S14: =_xlfn.XLOOKUP($A14,'P&L ACTUALS'!$A:$A,'P&L ACTUALS'!S:S,0) -> -4852.5611 | T14: =_xlfn.XLOOKUP(TRIM($A14),'Budget (from Controlling)_copy'!$B:$B,'Budget (from Controlling)_copy'!C:C,0) -> -14849.6 | U14: =_xlfn.XLOOKUP(TRIM($A14),'Budget (from Controlling)_copy'!$B:$B,'Budget (from Controlling)_copy'!D:D,0) -> -10407.952 | V14: =_xlfn.XLOOKUP(TRIM($A14),'Budget (from Controlling)_copy'!$B:$B,'Budget (from Controlling)_copy'!E:E,0) -> 0 | W14: =_xlfn.XLOOKUP(TRIM($A14),'Budget (from Controlling)_copy'!$B:$B,'Budget (from Controlling)_copy'!F:F,0) -> -4454.3095 | X14: =_xlfn.XLOOKUP(TRIM($A14),'Budget (from Controlling)_copy'!$B:$B,'Budget (from Controlling)_copy'!G:G,0) -> -8445.1326 | Y14: =_xlfn.XLOOKUP(TRIM($A14),'Budget (from Controlling)_copy'!$B:$B,'Budget (from Controlling)_copy'!H:H,0) -> -8833.1198
... A18: EBITDA | B18: =_xlfn.XLOOKUP($A18,'P&L ACTUALS'!$A:$A,'P&L ACTUALS'!B:B,0) -> 13028.88 | C18: =_xlfn.XLOOKUP($A18,'P&L ACTUALS'!$A:$A,'P&L ACTUALS'!C:C,0) -> 873043.63 | D18: =_xlfn.XLOOKUP($A18,'P&L ACTUALS'!$A:$A,'P&L ACTUALS'!D:D,0) -> 2110234.7 | E18: =_xlfn.XLOOKUP($A18,'P&L ACTUALS'!$A:$A,'P&L ACTUALS'!E:E,0) -> 2009576 | F18: =_xlfn.XLOOKUP($A18,'P&L ACTUALS'!$A:$A,'P&L ACTUALS'!F:F,0) -> 1600280.8 | G18: =_xlfn.XLOOKUP($A18,'P&L ACTUALS'!$A:$A,'P&L ACTUALS'!G:G,0) -> 839256.71 | H18: =_xlfn.XLOOKUP($A18,'P&L ACTUALS'!$A:$A,'P&L ACTUALS'!H:H,0) -> 198708.63 | I18: =_xlfn.XLOOKUP($A18,'P&L ACTUALS'!$A:$A,'P&L ACTUALS'!I:I,0) -> 839962.82 | J18: =_xlfn.XLOOKUP($A18,'P&L ACTUALS'!$A:$A,'P&L ACTUALS'!J:J,0) -> 1998289 | K18: =_xlfn.XLOOKUP($A18,'P&L ACTUALS'!$A:$A,'P&L ACTUALS'!K:K,0) -> 1276259.2 | L18: =_xlfn.XLOOKUP($A18,'P&L ACTUALS'!$A:$A,'P&L ACTUALS'!L:L,0) -> 1748192.1 | M18: =_xlfn.XLOOKUP($A18,'P&L ACTUALS'!$A:$A,'P&L ACTUALS'!M:M,0) -> 1655883 | N18: =_xlfn.XLOOKUP($A18,'P&L ACTUALS'!$A:$A,'P&L ACTUALS'!N:N,0) -> -451763.03 | O18: =_xlfn.XLOOKUP($A18,'P&L ACTUALS'!$A:$A,'P&L ACTUALS'!O:O,0) -> 265949.31 | P18: =_xlfn.XLOOKUP($A18,'P&L ACTUALS'!$A:$A,'P&L ACTUALS'!P:P,0) -> 1094397.7 | Q18: =_xlfn.XLOOKUP($A18,'P&L ACTUALS'!$A:$A,'P&L ACTUALS'!Q:Q,0) -> 393835.88 | R18: =_xlfn.XLOOKUP($A18,'P&L ACTUALS'!$A:$A,'P&L ACTUALS'!R:R,0) -> 720552.52 | S18: =_xlfn.XLOOKUP($A18,'P&L ACTUALS'!$A:$A,'P&L ACTUALS'!S:S,0) -> 330700.68 | T18: =_xlfn.XLOOKUP(TRIM($A18),'Budget (from Controlling)_copy'!$B:$B,'Budget (from Controlling)_copy'!C:C,0) -> 157711.02 | U18: =_xlfn.XLOOKUP(TRIM($A18),'Budget (from Controlling)_copy'!$B:$B,'Budget (from Controlling)_copy'!D:D,0) -> 1070145.6 | V18: =_xlfn.XLOOKUP(TRIM($A18),'Budget (from Controlling)_copy'!$B:$B,'Budget (from Controlling)_copy'!E:E,0) -> 2310084.2 | W18: =_xlfn.XLOOKUP(TRIM($A18),'Budget (from Controlling)_copy'!$B:$B,'Budget (from Controlling)_copy'!F:F,0) -> 2099136.6 | X18: =_xlfn.XLOOKUP(TRIM($A18),'Budget (from Controlling)_copy'!$B:$B,'Budget (from Controlling)_copy'!G:G,0) -> 1756669.3 | Y18: =_xlfn.XLOOKUP(TRIM($A18),'Budget (from Controlling)_copy'!$B:$B,'Budget (from Controlling)_copy'!H:H,0) -> 1027297.8

Sheet P&L MONTHLY
A1: MANAGEMENT P&L REPORT - ACTUALS VS BUDGET VS PRIOR YEAR - JAN 2025 - JUNE 2025
A3: supp values | B3: 2025.01_act | C3: 2024.01_act | D3: 2025.01_est | G3: 2025.02_act | H3: 2024.02_act | I3: 2025.02_est | L3: 2025.03_act | M3: 2024.03_act | N3: 2025.03_est | Q3: 2025.04_act | R3: 2024.04_act | S3: 2025.04_est | V3: 2025.05_act | W3: 2024.05_act | X3: 2025.05_est | AA3: 2025.06_act | AB3: 2024.06_act | AC3: 2025.06_est
A4: CATEGORY | B4: JANUARY | G4: FEBRUARY | L4: MARCH | Q4: APRIL | V4: MAY | AA4: JUNE | AF4: YTD JAN – JUN
B5: Act 2025 | C5: PY 2024 | D5: Budget | E5: ∆ vs Budget | F5: % vs Budget | G5: Act 2025 | H5: PY 2024 | I5: Budget | J5: ∆ vs Budget | K5: % vs Budget | L5: Act 2025 | M5: PY 2024 | N5: Budget | O5: ∆ vs Budget | P5: % vs Budget | Q5: Act 2025 | R5: PY 2024 | S5: Budget | T5: ∆ vs Budget | U5: % vs Budget | V5: Act 2025 | W5: PY 2024 | X5: Budget | Y5: ∆ vs Budget | Z5: % vs Budget | AA5: Act 2025 | AB5: PY 2024 | AC5: Budget | AD5: ∆ vs Budget | AE5: % vs Budget | AF5: Act 2025 | AG5: PY 2024 | AH5: Budget | AI5: ∆ vs Budget | AJ5: % vs Budget
A6: REVENUE | B6: =_xlfn.IFNA(INDEX('P&L ACTUALS+EST'!$B$3:$Y$18,MATCH('P&L MONTHLY'!$A6,'P&L ACTUALS+EST'!$A$3:$A$18,0),MATCH('P&L MONTHLY'!B$3,'P&L ACTUALS+EST'!$B$2:$Y$2,0)),0) -> 18270177 | C6: =_xlfn.IFNA(INDEX('P&L ACTUALS+EST'!$B$3:$Y$18,MATCH('P&L MONTHLY'!$A6,'P&L ACTUALS+EST'!$A$3:$A$18,0),MATCH('P&L MONTHLY'!C$3,'P&L ACTUALS+EST'!$B$2:$Y$2,0)),0) -> 17902923 | D6: =_xlfn.IFNA(INDEX('P&L ACTUALS+EST'!$B$3:$Y$18,MATCH('P&L MONTHLY'!$A6,'P&L ACTUALS+EST'!$A$3:$A$18,0),MATCH('P&L MONTHLY'!D$3,'P&L ACTUALS+EST'!$B$2:$Y$2,0)),0) -> 18928135 | E6: =B6-D6 -> -657958.07 | F6: =(B6-D6)/D6 -> -0.03476085 | G6: =_xlfn.IFNA(INDEX('P&L ACTUALS+EST'!$B$3:$Y$18,MATCH('P&L MONTHLY'!$A6,'P&L ACTUALS+EST'!$A$3:$A$18,0),MATCH('P&L MONTHLY'!G$3,'P&L ACTUALS+EST'!$B$2:$Y$2,0)),0) -> 24091845 | H6: =_xlfn.IFNA(INDEX('P&L ACTUALS+EST'!$B$3:$Y$18,MATCH('P&L MONTHLY'!$A6,'P&L ACTUALS+EST'!$A$3:$A$18,0),MATCH('P&L MONTHLY'!H$3,'P&L ACTUALS+EST'!$B$2:$Y$2,0)),0) -> 23598619 | I6: =_xlfn.IFNA(INDEX('P&L ACTUALS+EST'!$B$3:$Y$18,MATCH('P&L MONTHLY'!$A6,'P&L ACTUALS+EST'!$A$3:$A$18,0),MATCH('P&L MONTHLY'!I$3,'P&L ACTUALS+EST'!$B$2:$Y$2,0)),0) -> 24920142 | J6: =G6-I6 -> -828297.59 | K6: =J6/I6 -> -0.033238077 | L6: =_xlfn.IFNA(INDEX('P&L ACTUALS+EST'!$B$3:$Y$18,MATCH('P&L MONTHLY'!$A6,'P&L ACTUALS+EST'!$A$3:$A$18,0),MATCH('P&L MONTHLY'!L$3,'P&L ACTUALS+EST'!$B$2:$Y$2,0)),0) -> 29060428 | M6: =_xlfn.IFNA(INDEX('P&L ACTUALS+EST'!$B$3:$Y$18,MATCH('P&L MONTHLY'!$A6,'P&L ACTUALS+EST'!$A$3:$A$18,0),MATCH('P&L MONTHLY'!M$3,'P&L ACTUALS+EST'!$B$2:$Y$2,0)),0) -> 32077218 | N6: =_xlfn.IFNA(INDEX('P&L ACTUALS+EST'!$B$3:$Y$18,MATCH('P&L MONTHLY'!$A6,'P&L ACTUALS+EST'!$A$3:$A$18,0),MATCH('P&L MONTHLY'!N$3,'P&L ACTUALS+EST'!$B$2:$Y$2,0)),0) -> 33841465 | O6: =L6-N6 -> -4781037.5 | P6: =O6/N6 -> -0.1412775 | Q6: =_xlfn.IFNA(INDEX('P&L ACTUALS+EST'!$B$3:$Y$18,MATCH('P&L MONTHLY'!$A6,'P&L ACTUALS+EST'!$A$3:$A$18,0),MATCH('P&L MONTHLY'!Q$3,'P&L ACTUALS+EST'!$B$2:$Y$2,0)),0) -> 21989689 | R6: =_xlfn.IFNA(INDEX('P&L ACTUALS+EST'!$B$3:$Y$18,MATCH('P&L MONTHLY'!$A6,'P&L ACTUALS+EST'!$A$3:$A$18,0),MATCH('P&L MONTHLY'!R$3,'P&L ACTUALS+EST'!$B$2:$Y$2,0)),0) -> 30007803 | S6: =_xlfn.IFNA(INDEX('P&L ACTUALS+EST'!$B$3:$Y$18,MATCH('P&L MONTHLY'!$A6,'P&L ACTUALS+EST'!$A$3:$A$18,0),MATCH('P&L MONTHLY'!S$3,'P&L ACTUALS+EST'!$B$2:$Y$2,0)),0) -> 31628225 | T6: =Q6-S6 -> -9638535.9 | U6: =T6/S6 -> -0.30474477 | V6: =_xlfn.IFNA(INDEX('P&L ACTUALS+EST'!$B$3:$Y$18,MATCH('P&L MONTHLY'!$A6,'P&L ACTUALS+EST'!$A$3:$A$18,0),MATCH('P&L MONTHLY'!V$3,'P&L ACTUALS+EST'!$B$2:$Y$2,0)),0) -> 23404056 | W6: =_xlfn.IFNA(INDEX('P&L ACTUALS+EST'!$B$3:$Y$18,MATCH('P&L MONTHLY'!$A6,'P&L ACTUALS+EST'!$A$3:$A$18,0),MATCH('P&L MONTHLY'!W$3,'P&L ACTUALS+EST'!$B$2:$Y$2,0)),0) -> 26992974 | X6: =_xlfn.IFNA(INDEX('P&L ACTUALS+EST'!$B$3:$Y$18,MATCH('P&L MONTHLY'!$A6,'P&L ACTUALS+EST'!$A$3:$A$18,0),MATCH('P&L MONTHLY'!X$3,'P&L ACTUALS+EST'!$B$2:$Y$2,0)),0) -> 28396608 | Y6: =V6-X6 -> -4992552 | Z6: =Y6/X6 -> -0.17581508 | AA6: =_xlfn.IFNA(INDEX('P&L ACTUALS+EST'!$B$3:$Y$18,MATCH('P&L MONTHLY'!$A6,'P&L ACTUALS+EST'!$A$3:$A$18,0),MATCH('P&L MONTHLY'!AA$3,'P&L ACTUALS+EST'!$B$2:$Y$2,0)),0) -> 21139929 | AB6: =_xlfn.IFNA(INDEX('P&L ACTUALS+EST'!$B$3:$Y$18,MATCH('P&L MONTHLY'!$A6,'P&L ACTUALS+EST'!$A$3:$A$18,0),MATCH('P&L MONTHLY'!AB$3,'P&L ACTUALS+EST'!$B$2:$Y$2,0)),0) -> 21786031 | AC6: =_xlfn.IFNA(INDEX('P&L ACTUALS+EST'!$B$3:$Y$18,MATCH('P&L MONTHLY'!$A6,'P&L ACTUALS+EST'!$A$3:$A$18,0),MATCH('P&L MONTHLY'!AC$3,'P&L ACTUALS+EST'!$B$2:$Y$2,0)),0) -> 22853546 | AD6: =AA6-AC6 -> -1713616.6 | AE6: =AD6/AC6 -> -0.074982525 | AF6: =SUMIF($B$5:$AE$5,AF$5,$B6:$AE6) -> 1.3795612e+08 | AG6: =SUMIF($B$5:$AE$5,AG$5,$B6:$AE6) -> 1.5236557e+08 | AH6: =SUMIF($B$5:$AE$5,AH$5,$B6:$AE6) -> 1.6056812e+08 | AI6: =AF6-AG6 -> -14409445 | AJ6: =(AF6-AH6)/AH6 -> -0.14082495
A7: COGS | B7: =_xlfn.IFNA(INDEX('P&L ACTUALS+EST'!$B$3:$Y$18,MATCH('P&L MONTHLY'!$A7,'P&L ACTUALS+EST'!$A$3:$A$18,0),MATCH('P&L MONTHLY'!B$3,'P&L ACTUALS+EST'!$B$2:$Y$2,0)),0) -> -11180488 | C7: =_xlfn.IFNA(INDEX('P&L ACTUALS+EST'!$B$3:$Y$18,MATCH('P&L MONTHLY'!$A7,'P&L ACTUALS+EST'!$A$3:$A$18,0),MATCH('P&L MONTHLY'!C$3,'P&L ACTUALS+EST'!$B$2:$Y$2,0)),0) -> -10999312 | D7: =_xlfn.IFNA(INDEX('P&L ACTUALS+EST'!$B$3:$Y$18,MATCH('P&L MONTHLY'!$A7,'P&L ACTUALS+EST'!$A$3:$A$18,0),MATCH('P&L MONTHLY'!D$3,'P&L ACTUALS+EST'!$B$2:$Y$2,0)),0) -> -11379261 | E7: =B7-D7 -> 198772.97 | F7: =(B7-D7)/D7 -> -0.017468004 | G7: =_xlfn.IFNA(INDEX('P&L ACTUALS+EST'!$B$3:$Y$18,MATCH('P&L MONTHLY'!$A7,'P&L ACTUALS+EST'!$A$3:$A$18,0),MATCH('P&L MONTHLY'!G$3,'P&L ACTUALS+EST'!$B$2:$Y$2,0)),0) -> -14710137 | H7: =_xlfn.IFNA(INDEX('P&L ACTUALS+EST'!$B$3:$Y$18,MATCH('P&L MONTHLY'!$A7,'P&L ACTUALS+EST'!$A$3:$A$18,0),MATCH('P&L MONTHLY'!H$3,'P&L ACTUALS+EST'!$B$2:$Y$2,0)),0) -> -14453912 | I7: =_xlfn.IFNA(INDEX('P&L ACTUALS+EST'!$B$3:$Y$18,MATCH('P&L MONTHLY'!$A7,'P&L ACTUALS+EST'!$A$3:$A$18,0),MATCH('P&L MONTHLY'!I$3,'P&L ACTUALS+EST'!$B$2:$Y$2,0)),0) -> -14940672 | J7: =G7-I7 -> 230534.87 | K7: =J7/I7 -> -0.01543002 | L7: =_xlfn.IFNA(INDEX('P&L ACTUALS+EST'!$B$3:$Y$18,MATCH('P&L MONTHLY'!$A7,'P&L ACTUALS+EST'!$A$3:$A$18,0),MATCH('P&L MONTHLY'!L$3,'P&L ACTUALS+EST'!$B$2:$Y$2,0)),0) -> -17618863 | M7: =_xlfn.IFNA(INDEX('P&L ACTUALS+EST'!$B$3:$Y$18,MATCH('P&L MONTHLY'!$A7,'P&L ACTUALS+EST'!$A$3:$A$18,0),MATCH('P&L MONTHLY'!M$3,'P&L ACTUALS+EST'!$B$2:$Y$2,0)),0) -> -19635609 | N7: =_xlfn.IFNA(INDEX('P&L ACTUALS+EST'!$B$3:$Y$18,MATCH('P&L MONTHLY'!$A7,'P&L ACTUALS+EST'!$A$3:$A$18,0),MATCH('P&L MONTHLY'!N$3,'P&L ACTUALS+EST'!$B$2:$Y$2,0)),0) -> -20325399 | O7: =L7-N7 -> 2706536.6 | P7: =O7/N7 -> -0.13316032 | Q7: =_xlfn.IFNA(INDEX('P&L ACTUALS+EST'!$B$3:$Y$18,MATCH('P&L MONTHLY'!$A7,'P&L ACTUALS+EST'!$A$3:$A$18,0),MATCH('P&L MONTHLY'!Q$3,'P&L ACTUALS+EST'!$B$2:$Y$2,0)),0) -> -13284156 | R7: =_xlfn.IFNA(INDEX('P&L ACTUALS+EST'!$B$3:$Y$18,MATCH('P&L MONTHLY'!$A7,'P&L ACTUALS+EST'!$A$3:$A$18,0),MATCH('P&L MONTHLY'!R$3,'P&L ACTUALS+EST'!$B$2:$Y$2,0)),0) -> -18283548 | S7: =_xlfn.IFNA(INDEX('P&L ACTUALS+EST'!$B$3:$Y$18,MATCH('P&L MONTHLY'!$A7,'P&L ACTUALS+EST'!$A$3:$A$18,0),MATCH('P&L MONTHLY'!S$3,'P&L ACTUALS+EST'!$B$2:$Y$2,0)),0) -> -18975129 | T7: =Q7-S7 -> 5690973.4 | U7: =T7/S7 -> -0.29991751 | V7: =_xlfn.IFNA(INDEX('P&L ACTUALS+EST'!$B$3:$Y$18,MATCH('P&L MONTHLY'!$A7,'P&L ACTUALS+EST'!$A$3:$A$18,0),MATCH('P&L MONTHLY'!V$3,'P&L ACTUALS+EST'!$B$2:$Y$2,0)),0) -> -14091385 | W7: =_xlfn.IFNA(INDEX('P&L ACTUALS+EST'!$B$3:$Y$18,MATCH('P&L MONTHLY'!$A7,'P&L ACTUALS+EST'!$A$3:$A$18,0),MATCH('P&L MONTHLY'!W$3,'P&L ACTUALS+EST'!$B$2:$Y$2,0)),0) -> -16447792 | X7: =_xlfn.IFNA(INDEX('P&L ACTUALS+EST'!$B$3:$Y$18,MATCH('P&L MONTHLY'!$A7,'P&L ACTUALS+EST'!$A$3:$A$18,0),MATCH('P&L MONTHLY'!X$3,'P&L ACTUALS+EST'!$B$2:$Y$2,0)),0) -> -17054296 | Y7: =V7-X7 -> 2962910.9 | Z7: =Y7/X7 -> -0.17373399 | AA7: =_xlfn.IFNA(INDEX('P&L ACTUALS+EST'!$B$3:$Y$18,MATCH('P&L MONTHLY'!$A7,'P&L ACTUALS+EST'!$A$3:$A$18,0),MATCH('P&L MONTHLY'!AA$3,'P&L ACTUALS+EST'!$B$2:$Y$2,0)),0) -> -12846079 | AB7: =_xlfn.IFNA(INDEX('P&L ACTUALS+EST'!$B$3:$Y$18,MATCH('P&L MONTHLY'!$A7,'P&L ACTUALS+EST'!$A$3:$A$18,0),MATCH('P&L MONTHLY'!AB$3,'P&L ACTUALS+EST'!$B$2:$Y$2,0)),0) -> -13391749 | AC7: =_xlfn.IFNA(INDEX('P&L ACTUALS+EST'!$B$3:$Y$18,MATCH('P&L MONTHLY'!$A7,'P&L ACTUALS+EST'!$A$3:$A$18,0),MATCH('P&L MONTHLY'!AC$3,'P&L ACTUALS+EST'!$B$2:$Y$2,0)),0) -> -13728918 | AD7: =AA7-AC7 -> 882838.76 | AE7: =AD7/AC7 -> -0.06430505 | AF7: =SUMIF($B$5:$AE$5,AF$5,$B7:$AE7) -> -83731108 | AG7: =SUMIF($B$5:$AE$5,AG$5,$B7:$AE7) -> -93211922 | AH7: =SUMIF($B$5:$AE$5,AH$5,$B7:$AE7) -> -96403675 | AI7: =AF7-AG7 -> 9480814 | AJ7: =(AF7-AH7)/AH7 -> -0.13145316
A8: GROSS PROFIT | B8: =_xlfn.IFNA(INDEX('P&L ACTUALS+EST'!$B$3:$Y$18,MATCH('P&L MONTHLY'!$A8,'P&L ACTUALS+EST'!$A$3:$A$18,0),MATCH('P&L MONTHLY'!B$3,'P&L ACTUALS+EST'!$B$2:$Y$2,0)),0) -> 7089689.1 | C8: =_xlfn.IFNA(INDEX('P&L ACTUALS+EST'!$B$3:$Y$18,MATCH('P&L MONTHLY'!$A8,'P&L ACTUALS+EST'!$A$3:$A$18,0),MATCH('P&L MONTHLY'!C$3,'P&L ACTUALS+EST'!$B$2:$Y$2,0)),0) -> 6903611.9 | D8: =_xlfn.IFNA(INDEX('P&L ACTUALS+EST'!$B$3:$Y$18,MATCH('P&L MONTHLY'!$A8,'P&L ACTUALS+EST'!$A$3:$A$18,0),MATCH('P&L MONTHLY'!D$3,'P&L ACTUALS+EST'!$B$2:$Y$2,0)),0) -> 7548874.2 | E8: =B8-D8 -> -459185.1 | F8: =(B8-D8)/D8 -> -0.060828289 | G8: =_xlfn.IFNA(INDEX('P&L ACTUALS+EST'!$B$3:$Y$18,MATCH('P&L MONTHLY'!$A8,'P&L ACTUALS+EST'!$A$3:$A$18,0),MATCH('P&L MONTHLY'!G$3,'P&L ACTUALS+EST'!$B$2:$Y$2,0)),0) -> 9381707.1 | H8: =_xlfn.IFNA(INDEX('P&L ACTUALS+EST'!$B$3:$Y$18,MATCH('P&L MONTHLY'!$A8,'P&L ACTUALS+EST'!$A$3:$A$18,0),MATCH('P&L MONTHLY'!H$3,'P&L ACTUALS+EST'!$B$2:$Y$2,0)),0) -> 9144707 | I8: =_xlfn.IFNA(INDEX('P&L ACTUALS+EST'!$B$3:$Y$18,MATCH('P&L MONTHLY'!$A8,'P&L ACTUALS+EST'!$A$3:$A$18,0),MATCH('P&L MONTHLY'!I$3,'P&L ACTUALS+EST'!$B$2:$Y$2,0)),0) -> 9979469.8 | J8: =G8-I8 -> -597762.73 | K8: =J8/I8 -> -0.059899247 | L8: =_xlfn.IFNA(INDEX('P&L ACTUALS+EST'!$B$3:$Y$18,MATCH('P&L MONTHLY'!$A8,'P&L ACTUALS+EST'!$A$3:$A$18,0),MATCH('P&L MONTHLY'!L$3,'P&L ACTUALS+EST'!$B$2:$Y$2,0)),0) -> 11441565 | M8: =_xlfn.IFNA(INDEX('P&L ACTUALS+EST'!$B$3:$Y$18,MATCH('P&L MONTHLY'!$A8,'P&L ACTUALS+EST'!$A$3:$A$18,0),MATCH('P&L MONTHLY'!M$3,'P&L ACTUALS+EST'!$B$2:$Y$2,0)),0) -> 12441609 | N8: =_xlfn.IFNA(INDEX('P&L ACTUALS+EST'!$B$3:$Y$18,MATCH('P&L MONTHLY'!$A8,'P&L ACTUALS+EST'!$A$3:$A$18,0),MATCH('P&L MONTHLY'!N$3,'P&L ACTUALS+EST'!$B$2:$Y$2,0)),0) -> 13516066 | O8: =L8-N8 -> -2074500.9 | P8: =O8/N8 -> -0.15348408 | Q8: =_xlfn.IFNA(INDEX('P&L ACTUALS+EST'!$B$3:$Y$18,MATCH('P&L MONTHLY'!$A8,'P&L ACTUALS+EST'!$A$3:$A$18,0),MATCH('P&L MONTHLY'!Q$3,'P&L ACTUALS+EST'!$B$2:$Y$2,0)),0) -> 8705533.2 | R8: =_xlfn.IFNA(INDEX('P&L ACTUALS+EST'!$B$3:$Y$18,MATCH('P&L MONTHLY'!$A8,'P&L ACTUALS+EST'!$A$3:$A$18,0),MATCH('P&L MONTHLY'!R$3,'P&L ACTUALS+EST'!$B$2:$Y$2,0)),0) -> 11724256 | S8: =_xlfn.IFNA(INDEX('P&L ACTUALS+EST'!$B$3:$Y$18,MATCH('P&L MONTHLY'!$A8,'P&L ACTUALS+EST'!$A$3:$A$18,0),MATCH('P&L MONTHLY'!S$3,'P&L ACTUALS+EST'!$B$2:$Y$2,0)),0) -> 12653096 | T8: =Q8-S8 -> -3947562.5 | U8: =T8/S8 -> -0.31198393 | V8: =_xlfn.IFNA(INDEX('P&L ACTUALS+EST'!$B$3:$Y$18,MATCH('P&L MONTHLY'!$A8,'P&L ACTUALS+EST'!$A$3:$A$18,0),MATCH('P&L MONTHLY'!V$3,'P&L ACTUALS+EST'!$B$2:$Y$2,0)),0) -> 9312671.2 | W8: =_xlfn.IFNA(INDEX('P&L ACTUALS+EST'!$B$3:$Y$18,MATCH('P&L MONTHLY'!$A8,'P&L ACTUALS+EST'!$A$3:$A$18,0),MATCH('P&L MONTHLY'!W$3,'P&L ACTUALS+EST'!$B$2:$Y$2,0)),0) -> 10545181 | X8: =_xlfn.IFNA(INDEX('P&L ACTUALS+EST'!$B$3:$Y$18,MATCH('P&L MONTHLY'!$A8,'P&L ACTUALS+EST'!$A$3:$A$18,0),MATCH('P&L MONTHLY'!X$3,'P&L ACTUALS+EST'!$B$2:$Y$2,0)),0) -> 11342312 | Y8: =V8-X8 -> -2029641.2 | Z8: =Y8/X8 -> -0.17894421 | AA8: =_xlfn.IFNA(INDEX('P&L ACTUALS+EST'!$B$3:$Y$18,MATCH('P&L MONTHLY'!$A8,'P&L ACTUALS+EST'!$A$3:$A$18,0),MATCH('P&L MONTHLY'!AA$3,'P&L ACTUALS+EST'!$B$2:$Y$2,0)),0) -> 8293850.2 | AB8: =_xlfn.IFNA(INDEX('P&L ACTUALS+EST'!$B$3:$Y$18,MATCH('P&L MONTHLY'!$A8,'P&L ACTUALS+EST'!$A$3:$A$18,0),MATCH('P&L MONTHLY'!AB$3,'P&L ACTUALS+EST'!$B$2:$Y$2,0)),0) -> 8394281.6 | AC8: =_xlfn.IFNA(INDEX('P&L ACTUALS+EST'!$B$3:$Y$18,MATCH('P&L MONTHLY'!$A8,'P&L ACTUALS+EST'!$A$3:$A$18,0),MATCH('P&L MONTHLY'!AC$3,'P&L ACTUALS+EST'!$B$2:$Y$2,0)),0) -> 9124628 | AD8: =AA8-AC8 -> -830777.82 | AE8: =AD8/AC8 -> -0.091047856 | AF8: =SUMIF($B$5:$AE$5,AF$5,$B8:$AE8) -> 54225016 | AG8: =SUMIF($B$5:$AE$5,AG$5,$B8:$AE8) -> 59153647 | AH8: =SUMIF($B$5:$AE$5,AH$5,$B8:$AE8) -> 64164446 | AI8: =AF8-AG8 -> -4928630.8 | AJ8: =(AF8-AH8)/AH8 -> -0.15490557
A9: Gross profit % | B9: =B8/B6 -> 0.38804709 | C9: =C8/C6 -> 0.38561367 | D9: =D8/D6 -> 0.39881764 | E9: =B9-D9 -> -0.010770548 | F9: =E9/D9 -> -0.027006197 | G9: =G8/G6 -> 0.38941423 | H9: =H8/H6 -> 0.38751025 | I9: =I8/I6 -> 0.40045798 | J9: =G9-I9 -> -0.011043752 | K9: =J9/I9 -> -0.027577803 | L9: =L8/L6 -> 0.39371634 | M9: =M8/M6 -> 0.38786434 | N9: =N8/N6 -> 0.39939364 | O9: =L9-N9 -> -0.0056773058 | P9: =O9/N9 -> -0.014214813 | Q9: =Q8/Q6 -> 0.39589161 | R9: =R8/R6 -> 0.3907069 | S9: =S8/S6 -> 0.4000571 | T9: =Q9-S9 -> -0.0041654904 | U9: =T9/S9 -> -0.01041224 | V9: =V8/V6 -> 0.39790843 | W9: =W8/W6 -> 0.39066394 | X9: =X8/X6 -> 0.3994249 | Y9: =V9-X9 -> -0.001516471 | Z9: =Y9/X9 -> -0.003796636 | AA9: =AA8/AA6 -> 0.39233102 | AB9: =AB8/AB6 -> 0.38530569 | AC9: =AC8/AC6 -> 0.3992653 | AD9: =AA9-AC9 -> -0.0069342792 | AE9: =AD9/AC9 -> -0.017367598 | AF9: =AF8/AF6 -> 0.39305987 | AG9: =AG8/AG6 -> 0.388235 | AH9: =AH8/AH6 -> 0.39960887 | AI9: =AF9-AH9 -> -0.0065490049 | AJ9: =AI9/AH9 -> -0.016388537
A10: PAYMENT | B10: =_xlfn.IFNA(INDEX('P&L ACTUALS+EST'!$B$3:$Y$18,MATCH('P&L MONTHLY'!$A10,'P&L ACTUALS+EST'!$A$3:$A$18,0),MATCH('P&L MONTHLY'!B$3,'P&L ACTUALS+EST'!$B$2:$Y$2,0)),0) -> -404217.34 | C10: =_xlfn.IFNA(INDEX('P&L ACTUALS+EST'!$B$3:$Y$18,MATCH('P&L MONTHLY'!$A10,'P&L ACTUALS+EST'!$A$3:$A$18,0),MATCH('P&L MONTHLY'!C$3,'P&L ACTUALS+EST'!$B$2:$Y$2,0)),0) -> -384934.32 | D10: =_xlfn.IFNA(INDEX('P&L ACTUALS+EST'!$B$3:$Y$18,MATCH('P&L MONTHLY'!$A10,'P&L ACTUALS+EST'!$A$3:$A$18,0),MATCH('P&L MONTHLY'!D$3,'P&L ACTUALS+EST'!$B$2:$Y$2,0)),0) -> -425933.52 | E10: =B10-D10 -> 21716.184 | F10: =(B10-D10)/D10 -> -0.050984914 | G10: =_xlfn.IFNA(INDEX('P&L ACTUALS+EST'!$B$3:$Y$18,MATCH('P&L MONTHLY'!$A10,'P&L ACTUALS+EST'!$A$3:$A$18,0),MATCH('P&L MONTHLY'!G$3,'P&L ACTUALS+EST'!$B$2:$Y$2,0)),0) -> -535002.49 | H10: =_xlfn.IFNA(INDEX('P&L ACTUALS+EST'!$B$3:$Y$18,MATCH('P&L MONTHLY'!$A10,'P&L ACTUALS+EST'!$A$3:$A$18,0),MATCH('P&L MONTHLY'!H$3,'P&L ACTUALS+EST'!$B$2:$Y$2,0)),0) -> -496888 | I10: =_xlfn.IFNA(INDEX('P&L ACTUALS+EST'!$B$3:$Y$18,MATCH('P&L MONTHLY'!$A10,'P&L ACTUALS+EST'!$A$3:$A$18,0),MATCH('P&L MONTHLY'!I$3,'P&L ACTUALS+EST'!$B$2:$Y$2,0)),0) -> -560769.66 | J10: =G10-I10 -> 25767.175 | K10: =J10/I10 -> -0.04594966 | L10: =_xlfn.IFNA(INDEX('P&L ACTUALS+EST'!$B$3:$Y$18,MATCH('P&L MONTHLY'!$A10,'P&L ACTUALS+EST'!$A$3:$A$18,0),MATCH('P&L MONTHLY'!L$3,'P&L ACTUALS+EST'!$B$2:$Y$2,0)),0) -> -651196.97 | M10: =_xlfn.IFNA(INDEX('P&L ACTUALS+EST'!$B$3:$Y$18,MATCH('P&L MONTHLY'!$A10,'P&L ACTUALS+EST'!$A$3:$A$18,0),MATCH('P&L MONTHLY'!M$3,'P&L ACTUALS+EST'!$B$2:$Y$2,0)),0) -> -692136.98 | N10: =_xlfn.IFNA(INDEX('P&L ACTUALS+EST'!$B$3:$Y$18,MATCH('P&L MONTHLY'!$A10,'P&L ACTUALS+EST'!$A$3:$A$18,0),MATCH('P&L MONTHLY'!N$3,'P&L ACTUALS+EST'!$B$2:$Y$2,0)),0) -> -761523.23 | O10: =L10-N10 -> 110326.26 | P10: =O10/N10 -> -0.14487576 | Q10: =_xlfn.IFNA(INDEX('P&L ACTUALS+EST'!$B$3:$Y$18,MATCH('P&L MONTHLY'!$A10,'P&L ACTUALS+EST'!$A$3:$A$18,0),MATCH('P&L MONTHLY'!Q$3,'P&L ACTUALS+EST'!$B$2:$Y$2,0)),0) -> -492802.62 | R10: =_xlfn.IFNA(INDEX('P&L ACTUALS+EST'!$B$3:$Y$18,MATCH('P&L MONTHLY'!$A10,'P&L ACTUALS+EST'!$A$3:$A$18,0),MATCH('P&L MONTHLY'!R$3,'P&L ACTUALS+EST'!$B$2:$Y$2,0)),0) -> -629389.18 | S10: =_xlfn.IFNA(INDEX('P&L ACTUALS+EST'!$B$3:$Y$18,MATCH('P&L MONTHLY'!$A10,'P&L ACTUALS+EST'!$A$3:$A$18,0),MATCH('P&L MONTHLY'!S$3,'P&L ACTUALS+EST'!$B$2:$Y$2,0)),0) -> -711719.41 | T10: =Q10-S10 -> 218916.79 | U10: =T10/S10 -> -0.30758861 | V10: =_xlfn.IFNA(INDEX('P&L ACTUALS+EST'!$B$3:$Y$18,MATCH('P&L MONTHLY'!$A10,'P&L ACTUALS+EST'!$A$3:$A$18,0),MATCH('P&L MONTHLY'!V$3,'P&L ACTUALS+EST'!$B$2:$Y$2,0)),0) -> -524343.77 | W10: =_xlfn.IFNA(INDEX('P&L ACTUALS+EST'!$B$3:$Y$18,MATCH('P&L MONTHLY'!$A10,'P&L ACTUALS+EST'!$A$3:$A$18,0),MATCH('P&L MONTHLY'!W$3,'P&L ACTUALS+EST'!$B$2:$Y$2,0)),0) -> -579036.72 | X10: =_xlfn.IFNA(INDEX('P&L ACTUALS+EST'!$B$3:$Y$18,MATCH('P&L MONTHLY'!$A10,'P&L ACTUALS+EST'!$A$3:$A$18,0),MATCH('P&L MONTHLY'!X$3,'P&L ACTUALS+EST'!$B$2:$Y$2,0)),0) -> -638999.42 | Y10: =V10-X10 -> 114655.65 | Z10: =Y10/X10 -> -0.17942998 | AA10: =_xlfn.IFNA(INDEX('P&L ACTUALS+EST'!$B$3:$Y$18,MATCH('P&L MONTHLY'!$A10,'P&L ACTUALS+EST'!$A$3:$A$18,0),MATCH('P&L MONTHLY'!AA$3,'P&L ACTUALS+EST'!$B$2:$Y$2,0)),0) -> -471907.49 | AB10: =_xlfn.IFNA(INDEX('P&L ACTUALS+EST'!$B$3:$Y$18,MATCH('P&L MONTHLY'!$A10,'P&L ACTUALS+EST'!$A$3:$A$18,0),MATCH('P&L MONTHLY'!AB$3,'P&L ACTUALS+EST'!$B$2:$Y$2,0)),0) -> -471001.98 | AC10: =_xlfn.IFNA(INDEX('P&L ACTUALS+EST'!$B$3:$Y$18,MATCH('P&L MONTHLY'!$A10,'P&L ACTUALS+EST'!$A$3:$A$18,0),MATCH('P&L MONTHLY'!AC$3,'P&L ACTUALS+EST'!$B$2:$Y$2,0)),0) -> -514265.74 | AD10: =AA10-AC10 -> 42358.252 | AE10: =AD10/AC10 -> -0.082366467 | AF10: =SUMIF($B$5:$AE$5,AF$5,$B10:$AE10) -> -3079470.7 | AG10: =SUMIF($B$5:$AE$5,AG$5,$B10:$AE10) -> -3253387.2 | AH10: =SUMIF($B$5:$AE$5,AH$5,$B10:$AE10) -> -3613211 | AI10: =AF10-AG10 -> 173916.5 | AJ10: =(AF10-AH10)/AH10 -> -0.14771911
A11: WAREHOUSE | B11: =_xlfn.IFNA(INDEX('P&L ACTUALS+EST'!$B$3:$Y$18,MATCH('P&L MONTHLY'!$A11,'P&L ACTUALS+EST'!$A$3:$A$18,0),MATCH('P&L MONTHLY'!B$3,'P&L ACTUALS+EST'!$B$2:$Y$2,0)),0) -> -1830023.9 | C11: =_xlfn.IFNA(INDEX('P&L ACTUALS+EST'!$B$3:$Y$18,MATCH('P&L MONTHLY'!$A11,'P&L ACTUALS+EST'!$A$3:$A$18,0),MATCH('P&L MONTHLY'!C$3,'P&L ACTUALS+EST'!$B$2:$Y$2,0)),0) -> -1470207.6 | D11: =_xlfn.IFNA(INDEX('P&L ACTUALS+EST'!$B$3:$Y$18,MATCH('P&L MONTHLY'!$A11,'P&L ACTUALS+EST'!$A$3:$A$18,0),MATCH('P&L MONTHLY'!D$3,'P&L ACTUALS+EST'!$B$2:$Y$2,0)),0) -> -1666186.2 | E11: =B11-D11 -> -163837.67 | F11: =(B11-D11)/D11 -> 0.09833095 | G11: =_xlfn.IFNA(INDEX('P&L ACTUALS+EST'!$B$3:$Y$18,MATCH('P&L MONTHLY'!$A11,'P&L ACTUALS+EST'!$A$3:$A$18,0),MATCH('P&L MONTHLY'!G$3,'P&L ACTUALS+EST'!$B$2:$Y$2,0)),0) -> -2405737.7 | H11: =_xlfn.IFNA(INDEX('P&L ACTUALS+EST'!$B$3:$Y$18,MATCH('P&L MONTHLY'!$A11,'P&L ACTUALS+EST'!$A$3:$A$18,0),MATCH('P&L MONTHLY'!H$3,'P&L ACTUALS+EST'!$B$2:$Y$2,0)),0) -> -1932725.4 | I11: =_xlfn.IFNA(INDEX('P&L ACTUALS+EST'!$B$3:$Y$18,MATCH('P&L MONTHLY'!$A11,'P&L ACTUALS+EST'!$A$3:$A$18,0),MATCH('P&L MONTHLY'!I$3,'P&L ACTUALS+EST'!$B$2:$Y$2,0)),0) -> -2162748 | J11: =G11-I11 -> -242989.66 | K11: =J11/I11 -> 0.11235228 | L11: =_xlfn.IFNA(INDEX('P&L ACTUALS+EST'!$B$3:$Y$18,MATCH('P&L MONTHLY'!$A11,'P&L ACTUALS+EST'!$A$3:$A$18,0),MATCH('P&L MONTHLY'!L$3,'P&L ACTUALS+EST'!$B$2:$Y$2,0)),0) -> -2768479.8 | M11: =_xlfn.IFNA(INDEX('P&L ACTUALS+EST'!$B$3:$Y$18,MATCH('P&L MONTHLY'!$A11,'P&L ACTUALS+EST'!$A$3:$A$18,0),MATCH('P&L MONTHLY'!M$3,'P&L ACTUALS+EST'!$B$2:$Y$2,0)),0) -> -2446516.2 | N11: =_xlfn.IFNA(INDEX('P&L ACTUALS+EST'!$B$3:$Y$18,MATCH('P&L MONTHLY'!$A11,'P&L ACTUALS+EST'!$A$3:$A$18,0),MATCH('P&L MONTHLY'!N$3,'P&L ACTUALS+EST'!$B$2:$Y$2,0)),0) -> -2853089.8 | O11: =L11-N11 -> 84609.975 | P11: =O11/N11 -> -0.02965556 | Q11: =_xlfn.IFNA(INDEX('P&L ACTUALS+EST'!$B$3:$Y$18,MATCH('P&L MONTHLY'!$A11,'P&L ACTUALS+EST'!$A$3:$A$18,0),MATCH('P&L MONTHLY'!Q$3,'P&L ACTUALS+EST'!$B$2:$Y$2,0)),0) -> -2084666.6 | R11: =_xlfn.IFNA(INDEX('P&L ACTUALS+EST'!$B$3:$Y$18,MATCH('P&L MONTHLY'!$A11,'P&L ACTUALS+EST'!$A$3:$A$18,0),MATCH('P&L MONTHLY'!R$3,'P&L ACTUALS+EST'!$B$2:$Y$2,0)),0) -> -2307060.7 | S11: =_xlfn.IFNA(INDEX('P&L ACTUALS+EST'!$B$3:$Y$18,MATCH('P&L MONTHLY'!$A11,'P&L ACTUALS+EST'!$A$3:$A$18,0),MATCH('P&L MONTHLY'!S$3,'P&L ACTUALS+EST'!$B$2:$Y$2,0)),0) -> -2627283.8 | T11: =Q11-S11 -> 542617.2 | U11: =T11/S11 -> -0.20653163 | V11: =_xlfn.IFNA(INDEX('P&L ACTUALS+EST'!$B$3:$Y$18,MATCH('P&L MONTHLY'!$A11,'P&L ACTUALS+EST'!$A$3:$A$18,0),MATCH('P&L MONTHLY'!V$3,'P&L ACTUALS+EST'!$B$2:$Y$2,0)),0) -> -2202174.6 | W11: =_xlfn.IFNA(INDEX('P&L ACTUALS+EST'!$B$3:$Y$18,MATCH('P&L MONTHLY'!$A11,'P&L ACTUALS+EST'!$A$3:$A$18,0),MATCH('P&L MONTHLY'!W$3,'P&L ACTUALS+EST'!$B$2:$Y$2,0)),0) -> -2092614.8 | X11: =_xlfn.IFNA(INDEX('P&L ACTUALS+EST'!$B$3:$Y$18,MATCH('P&L MONTHLY'!$A11,'P&L ACTUALS+EST'!$A$3:$A$18,0),MATCH('P&L MONTHLY'!X$3,'P&L ACTUALS+EST'!$B$2:$Y$2,0)),0) -> -2288427.7 | Y11: =V11-X11 -> 86253.061 | Z11: =Y11/X11 -> -0.037690971 | AA11: =_xlfn.IFNA(INDEX('P&L ACTUALS+EST'!$B$3:$Y$18,MATCH('P&L MONTHLY'!$A11,'P&L ACTUALS+EST'!$A$3:$A$18,0),MATCH('P&L MONTHLY'!AA$3,'P&L ACTUALS+EST'!$B$2:$Y$2,0)),0) -> -1982751.8 | AB11: =_xlfn.IFNA(INDEX('P&L ACTUALS+EST'!$B$3:$Y$18,MATCH('P&L MONTHLY'!$A11,'P&L ACTUALS+EST'!$A$3:$A$18,0),MATCH('P&L MONTHLY'!AB$3,'P&L ACTUALS+EST'!$B$2:$Y$2,0)),0) -> -1618297.1 | AC11: =_xlfn.IFNA(INDEX('P&L ACTUALS+EST'!$B$3:$Y$18,MATCH('P&L MONTHLY'!$A11,'P&L ACTUALS+EST'!$A$3:$A$18,0),MATCH('P&L MONTHLY'!AC$3,'P&L ACTUALS+EST'!$B$2:$Y$2,0)),0) -> -1841723 | AD11: =AA11-AC11 -> -141028.78 | AE11: =AD11/AC11 -> 0.076574369 | AF11: =SUMIF($B$5:$AE$5,AF$5,$B11:$AE11) -> -13273834 | AG11: =SUMIF($B$5:$AE$5,AG$5,$B11:$AE11) -> -11867422 | AH11: =SUMIF($B$5:$AE$5,AH$5,$B11:$AE11) -> -13439459 | AI11: =AF11-AG11 -> -1406412.7 | AJ11: =(AF11-AH11)/AH11 -> -0.01232372
A12: DISTRIBUTION | B12: =_xlfn.IFNA(INDEX('P&L ACTUALS+EST'!$B$3:$Y$18,MATCH('P&L MONTHLY'!$A12,'P&L ACTUALS+EST'!$A$3:$A$18,0),MATCH('P&L MONTHLY'!B$3,'P&L ACTUALS+EST'!$B$2:$Y$2,0)),0) -> -2934147.4 | C12: =_xlfn.IFNA(INDEX('P&L ACTUALS+EST'!$B$3:$Y$18,MATCH('P&L MONTHLY'!$A12,'P&L ACTUALS+EST'!$A$3:$A$18,0),MATCH('P&L MONTHLY'!C$3,'P&L ACTUALS+EST'!$B$2:$Y$2,0)),0) -> -2697687 | D12: =_xlfn.IFNA(INDEX('P&L ACTUALS+EST'!$B$3:$Y$18,MATCH('P&L MONTHLY'!$A12,'P&L ACTUALS+EST'!$A$3:$A$18,0),MATCH('P&L MONTHLY'!D$3,'P&L ACTUALS+EST'!$B$2:$Y$2,0)),0) -> -2929859.4 | E12: =B12-D12 -> -4287.9564 | F12: =(B12-D12)/D12 -> 0.0014635366 | G12: =_xlfn.IFNA(INDEX('P&L ACTUALS+EST'!$B$3:$Y$18,MATCH('P&L MONTHLY'!$A12,'P&L ACTUALS+EST'!$A$3:$A$18,0),MATCH('P&L MONTHLY'!G$3,'P&L ACTUALS+EST'!$B$2:$Y$2,0)),0) -> -3818240.3 | H12: =_xlfn.IFNA(INDEX('P&L ACTUALS+EST'!$B$3:$Y$18,MATCH('P&L MONTHLY'!$A12,'P&L ACTUALS+EST'!$A$3:$A$18,0),MATCH('P&L MONTHLY'!H$3,'P&L ACTUALS+EST'!$B$2:$Y$2,0)),0) -> -3505939.2 | I12: =_xlfn.IFNA(INDEX('P&L ACTUALS+EST'!$B$3:$Y$18,MATCH('P&L MONTHLY'!$A12,'P&L ACTUALS+EST'!$A$3:$A$18,0),MATCH('P&L MONTHLY'!I$3,'P&L ACTUALS+EST'!$B$2:$Y$2,0)),0) -> -3825209.2 | J12: =G12-I12 -> 6968.8573 | K12: =J12/I12 -> -0.0018218239 | L12: =_xlfn.IFNA(INDEX('P&L ACTUALS+EST'!$B$3:$Y$18,MATCH('P&L MONTHLY'!$A12,'P&L ACTUALS+EST'!$A$3:$A$18,0),MATCH('P&L MONTHLY'!L$3,'P&L ACTUALS+EST'!$B$2:$Y$2,0)),0) -> -4464968.2 | M12: =_xlfn.IFNA(INDEX('P&L ACTUALS+EST'!$B$3:$Y$18,MATCH('P&L MONTHLY'!$A12,'P&L ACTUALS+EST'!$A$3:$A$18,0),MATCH('P&L MONTHLY'!M$3,'P&L ACTUALS+EST'!$B$2:$Y$2,0)),0) -> -4722572.6 | N12: =_xlfn.IFNA(INDEX('P&L ACTUALS+EST'!$B$3:$Y$18,MATCH('P&L MONTHLY'!$A12,'P&L ACTUALS+EST'!$A$3:$A$18,0),MATCH('P&L MONTHLY'!N$3,'P&L ACTUALS+EST'!$B$2:$Y$2,0)),0) -> -5107316.1 | O12: =L12-N12 -> 642347.83 | P12: =O12/N12 -> -0.12577013 | Q12: =_xlfn.IFNA(INDEX('P&L ACTUALS+EST'!$B$3:$Y$18,MATCH('P&L MONTHLY'!$A12,'P&L ACTUALS+EST'!$A$3:$A$18,0),MATCH('P&L MONTHLY'!Q$3,'P&L ACTUALS+EST'!$B$2:$Y$2,0)),0) -> -3341724.1 | R12: =_xlfn.IFNA(INDEX('P&L ACTUALS+EST'!$B$3:$Y$18,MATCH('P&L MONTHLY'!$A12,'P&L ACTUALS+EST'!$A$3:$A$18,0),MATCH('P&L MONTHLY'!R$3,'P&L ACTUALS+EST'!$B$2:$Y$2,0)),0) -> -4336663.6 | S12: =_xlfn.IFNA(INDEX('P&L ACTUALS+EST'!$B$3:$Y$18,MATCH('P&L MONTHLY'!$A12,'P&L ACTUALS+EST'!$A$3:$A$18,0),MATCH('P&L MONTHLY'!S$3,'P&L ACTUALS+EST'!$B$2:$Y$2,0)),0) -> -4732498.8 | T12: =Q12-S12 -> 1390774.7 | U12: =T12/S12 -> -0.29387746 | V12: =_xlfn.IFNA(INDEX('P&L ACTUALS+EST'!$B$3:$Y$18,MATCH('P&L MONTHLY'!$A12,'P&L ACTUALS+EST'!$A$3:$A$18,0),MATCH('P&L MONTHLY'!V$3,'P&L ACTUALS+EST'!$B$2:$Y$2,0)),0) -> -3570895.9 | W12: =_xlfn.IFNA(INDEX('P&L ACTUALS+EST'!$B$3:$Y$18,MATCH('P&L MONTHLY'!$A12,'P&L ACTUALS+EST'!$A$3:$A$18,0),MATCH('P&L MONTHLY'!W$3,'P&L ACTUALS+EST'!$B$2:$Y$2,0)),0) -> -3914189.3 | X12: =_xlfn.IFNA(INDEX('P&L ACTUALS+EST'!$B$3:$Y$18,MATCH('P&L MONTHLY'!$A12,'P&L ACTUALS+EST'!$A$3:$A$18,0),MATCH('P&L MONTHLY'!X$3,'P&L ACTUALS+EST'!$B$2:$Y$2,0)),0) -> -4248955.4 | Y12: =V12-X12 -> 678059.49 | Z12: =Y12/X12 -> -0.15958263 | AA12: =_xlfn.IFNA(INDEX('P&L ACTUALS+EST'!$B$3:$Y$18,MATCH('P&L MONTHLY'!$A12,'P&L ACTUALS+EST'!$A$3:$A$18,0),MATCH('P&L MONTHLY'!AA$3,'P&L ACTUALS+EST'!$B$2:$Y$2,0)),0) -> -3199221.3 | AB12: =_xlfn.IFNA(INDEX('P&L ACTUALS+EST'!$B$3:$Y$18,MATCH('P&L MONTHLY'!$A12,'P&L ACTUALS+EST'!$A$3:$A$18,0),MATCH('P&L MONTHLY'!AB$3,'P&L ACTUALS+EST'!$B$2:$Y$2,0)),0) -> -3097761.2 | AC12: =_xlfn.IFNA(INDEX('P&L ACTUALS+EST'!$B$3:$Y$18,MATCH('P&L MONTHLY'!$A12,'P&L ACTUALS+EST'!$A$3:$A$18,0),MATCH('P&L MONTHLY'!AC$3,'P&L ACTUALS+EST'!$B$2:$Y$2,0)),0) -> -3331116 | AD12: =AA12-AC12 -> 131894.7 | AE12: =AD12/AC12 -> -0.039594748 | AF12: =SUMIF($B$5:$AE$5,AF$5,$B12:$AE12) -> -21329197 | AG12: =SUMIF($B$5:$AE$5,AG$5,$B12:$AE12) -> -22274813 | AH12: =SUMIF($B$5:$AE$5,AH$5,$B12:$AE12) -> -24174955 | AI12: =AF12-AG12 -> 945615.72 | AJ12: =(AF12-AH12)/AH12 -> -0.11771512
A13: VARIABLE COSTS | B13: =_xlfn.IFNA(INDEX('P&L ACTUALS+EST'!$B$3:$Y$18,MATCH('P&L MONTHLY'!$A13,'P&L ACTUALS+EST'!$A$3:$A$18,0),MATCH('P&L MONTHLY'!B$3,'P&L ACTUALS+EST'!$B$2:$Y$2,0)),0) -> -5168388.6 | C13: =_xlfn.IFNA(INDEX('P&L ACTUALS+EST'!$B$3:$Y$18,MATCH('P&L MONTHLY'!$A13,'P&L ACTUALS+EST'!$A$3:$A$18,0),MATCH('P&L MONTHLY'!C$3,'P&L ACTUALS+EST'!$B$2:$Y$2,0)),0) -> -4552828.9 | D13: =_xlfn.IFNA(INDEX('P&L ACTUALS+EST'!$B$3:$Y$18,MATCH('P&L MONTHLY'!$A13,'P&L ACTUALS+EST'!$A$3:$A$18,0),MATCH('P&L MONTHLY'!D$3,'P&L ACTUALS+EST'!$B$2:$Y$2,0)),0) -> -5021979.2 | E13: =B13-D13 -> -146409.45 | F13: =(B13-D13)/D13 -> 0.029153734 | G13: =_xlfn.IFNA(INDEX('P&L ACTUALS+EST'!$B$3:$Y$18,MATCH('P&L MONTHLY'!$A13,'P&L ACTUALS+EST'!$A$3:$A$18,0),MATCH('P&L MONTHLY'!G$3,'P&L ACTUALS+EST'!$B$2:$Y$2,0)),0) -> -6758980.5 | H13: =_xlfn.IFNA(INDEX('P&L ACTUALS+EST'!$B$3:$Y$18,MATCH('P&L MONTHLY'!$A13,'P&L ACTUALS+EST'!$A$3:$A$18,0),MATCH('P&L MONTHLY'!H$3,'P&L ACTUALS+EST'!$B$2:$Y$2,0)),0) -> -5935552.6 | I13: =_xlfn.IFNA(INDEX('P&L ACTUALS+EST'!$B$3:$Y$18,MATCH('P&L MONTHLY'!$A13,'P&L ACTUALS+EST'!$A$3:$A$18,0),MATCH('P&L MONTHLY'!I$3,'P&L ACTUALS+EST'!$B$2:$Y$2,0)),0) -> -6548726.8 | J13: =G13-I13 -> -210253.63 | K13: =J13/I13 -> 0.032106031 | L13: =_xlfn.IFNA(INDEX('P&L ACTUALS+EST'!$B$3:$Y$18,MATCH('P&L MONTHLY'!$A13,'P&L ACTUALS+EST'!$A$3:$A$18,0),MATCH('P&L MONTHLY'!L$3,'P&L ACTUALS+EST'!$B$2:$Y$2,0)),0) -> -7884645 | M13: =_xlfn.IFNA(INDEX('P&L ACTUALS+EST'!$B$3:$Y$18,MATCH('P&L MONTHLY'!$A13,'P&L ACTUALS+EST'!$A$3:$A$18,0),MATCH('P&L MONTHLY'!M$3,'P&L ACTUALS+EST'!$B$2:$Y$2,0)),0) -> -7861225.8 | N13: =_xlfn.IFNA(INDEX('P&L ACTUALS+EST'!$B$3:$Y$18,MATCH('P&L MONTHLY'!$A13,'P&L ACTUALS+EST'!$A$3:$A$18,0),MATCH('P&L MONTHLY'!N$3,'P&L ACTUALS+EST'!$B$2:$Y$2,0)),0) -> -8721929.1 | O13: =L13-N13 -> 837284.06 | P13: =O13/N13 -> -0.095997577 | Q13: =_xlfn.IFNA(INDEX('P&L ACTUALS+EST'!$B$3:$Y$18,MATCH('P&L MONTHLY'!$A13,'P&L ACTUALS+EST'!$A$3:$A$18,0),MATCH('P&L MONTHLY'!Q$3,'P&L ACTUALS+EST'!$B$2:$Y$2,0)),0) -> -5919193.3 | R13: =_xlfn.IFNA(INDEX('P&L ACTUALS+EST'!$B$3:$Y$18,MATCH('P&L MONTHLY'!$A13,'P&L ACTUALS+EST'!$A$3:$A$18,0),MATCH('P&L MONTHLY'!R$3,'P&L ACTUALS+EST'!$B$2:$Y$2,0)),0) -> -7273113.5 | S13: =_xlfn.IFNA(INDEX('P&L ACTUALS+EST'!$B$3:$Y$18,MATCH('P&L MONTHLY'!$A13,'P&L ACTUALS+EST'!$A$3:$A$18,0),MATCH('P&L MONTHLY'!S$3,'P&L ACTUALS+EST'!$B$2:$Y$2,0)),0) -> -8071502 | T13: =Q13-S13 -> 2152308.7 | U13: =T13/S13 -> -0.26665529 | V13: =_xlfn.IFNA(INDEX('P&L ACTUALS+EST'!$B$3:$Y$18,MATCH('P&L MONTHLY'!$A13,'P&L ACTUALS+EST'!$A$3:$A$18,0),MATCH('P&L MONTHLY'!V$3,'P&L ACTUALS+EST'!$B$2:$Y$2,0)),0) -> -6297414.3 | W13: =_xlfn.IFNA(INDEX('P&L ACTUALS+EST'!$B$3:$Y$18,MATCH('P&L MONTHLY'!$A13,'P&L ACTUALS+EST'!$A$3:$A$18,0),MATCH('P&L MONTHLY'!W$3,'P&L ACTUALS+EST'!$B$2:$Y$2,0)),0) -> -6585840.8 | X13: =_xlfn.IFNA(INDEX('P&L ACTUALS+EST'!$B$3:$Y$18,MATCH('P&L MONTHLY'!$A13,'P&L ACTUALS+EST'!$A$3:$A$18,0),MATCH('P&L MONTHLY'!X$3,'P&L ACTUALS+EST'!$B$2:$Y$2,0)),0) -> -7176382.5 | Y13: =V13-X13 -> 878968.2 | Z13: =Y13/X13 -> -0.12248068 | AA13: =_xlfn.IFNA(INDEX('P&L ACTUALS+EST'!$B$3:$Y$18,MATCH('P&L MONTHLY'!$A13,'P&L ACTUALS+EST'!$A$3:$A$18,0),MATCH('P&L MONTHLY'!AA$3,'P&L ACTUALS+EST'!$B$2:$Y$2,0)),0) -> -5653880.6 | AB13: =_xlfn.IFNA(INDEX('P&L ACTUALS+EST'!$B$3:$Y$18,MATCH('P&L MONTHLY'!$A13,'P&L ACTUALS+EST'!$A$3:$A$18,0),MATCH('P&L MONTHLY'!AB$3,'P&L ACTUALS+EST'!$B$2:$Y$2,0)),0) -> -5187060.3 | AC13: =_xlfn.IFNA(INDEX('P&L ACTUALS+EST'!$B$3:$Y$18,MATCH('P&L MONTHLY'!$A13,'P&L ACTUALS+EST'!$A$3:$A$18,0),MATCH('P&L MONTHLY'!AC$3,'P&L ACTUALS+EST'!$B$2:$Y$2,0)),0) -> -5687104.7 | AD13: =AA13-AC13 -> 33224.172 | AE13: =AD13/AC13 -> -0.0058420186 | AF13: =SUMIF($B$5:$AE$5,AF$5,$B13:$AE13) -> -37682502 | AG13: =SUMIF($B$5:$AE$5,AG$5,$B13:$AE13) -> -37395622 | AH13: =SUMIF($B$5:$AE$5,AH$5,$B13:$AE13) -> -41227624 | AI13: =AF13-AG13 -> -286880.46 | AJ13: =(AF13-AH13)/AH13 -> -0.085988997
A14: CONTRIBUTION PROFIT | B14: =_xlfn.IFNA(INDEX('P&L ACTUALS+EST'!$B$3:$Y$18,MATCH('P&L MONTHLY'!$A14,'P&L ACTUALS+EST'!$A$3:$A$18,0),MATCH('P&L MONTHLY'!B$3,'P&L ACTUALS+EST'!$B$2:$Y$2,0)),0) -> 1921300.4 | C14: =_xlfn.IFNA(INDEX('P&L ACTUALS+EST'!$B$3:$Y$18,MATCH('P&L MONTHLY'!$A14,'P&L ACTUALS+EST'!$A$3:$A$18,0),MATCH('P&L MONTHLY'!C$3,'P&L ACTUALS+EST'!$B$2:$Y$2,0)),0) -> 2350783 | D14: =_xlfn.IFNA(INDEX('P&L ACTUALS+EST'!$B$3:$Y$18,MATCH('P&L MONTHLY'!$A14,'P&L ACTUALS+EST'!$A$3:$A$18,0),MATCH('P&L MONTHLY'!D$3,'P&L ACTUALS+EST'!$B$2:$Y$2,0)),0) -> 2526895 | E14: =B14-D14 -> -605594.55 | F14: =(B14-D14)/D14 -> -0.23965956 | G14: =_xlfn.IFNA(INDEX('P&L ACTUALS+EST'!$B$3:$Y$18,MATCH('P&L MONTHLY'!$A14,'P&L ACTUALS+EST'!$A$3:$A$18,0),MATCH('P&L MONTHLY'!G$3,'P&L ACTUALS+EST'!$B$2:$Y$2,0)),0) -> 2622726.6 | H14: =_xlfn.IFNA(INDEX('P&L ACTUALS+EST'!$B$3:$Y$18,MATCH('P&L MONTHLY'!$A14,'P&L ACTUALS+EST'!$A$3:$A$18,0),MATCH('P&L MONTHLY'!H$3,'P&L ACTUALS+EST'!$B$2:$Y$2,0)),0) -> 3209154.4 | I14: =_xlfn.IFNA(INDEX('P&L ACTUALS+EST'!$B$3:$Y$18,MATCH('P&L MONTHLY'!$A14,'P&L ACTUALS+EST'!$A$3:$A$18,0),MATCH('P&L MONTHLY'!I$3,'P&L ACTUALS+EST'!$B$2:$Y$2,0)),0) -> 3430743 | J14: =G14-I14 -> -808016.36 | K14: =J14/I14 -> -0.23552226 | L14: =_xlfn.IFNA(INDEX('P&L ACTUALS+EST'!$B$3:$Y$18,MATCH('P&L MONTHLY'!$A14,'P&L ACTUALS+EST'!$A$3:$A$18,0),MATCH('P&L MONTHLY'!L$3,'P&L ACTUALS+EST'!$B$2:$Y$2,0)),0) -> 3556920.2 | M14: =_xlfn.IFNA(INDEX('P&L ACTUALS+EST'!$B$3:$Y$18,MATCH('P&L MONTHLY'!$A14,'P&L ACTUALS+EST'!$A$3:$A$18,0),MATCH('P&L MONTHLY'!M$3,'P&L ACTUALS+EST'!$B$2:$Y$2,0)),0) -> 4580383.3 | N14: =_xlfn.IFNA(INDEX('P&L ACTUALS+EST'!$B$3:$Y$18,MATCH('P&L MONTHLY'!$A14,'P&L ACTUALS+EST'!$A$3:$A$18,0),MATCH('P&L MONTHLY'!N$3,'P&L ACTUALS+EST'!$B$2:$Y$2,0)),0) -> 4794137 | O14: =L14-N14 -> -1237216.8 | P14: =O14/N14 -> -0.25806873 | Q14: =_xlfn.IFNA(INDEX('P&L ACTUALS+EST'!$B$3:$Y$18,MATCH('P&L MONTHLY'!$A14,'P&L ACTUALS+EST'!$A$3:$A$18,0),MATCH('P&L MONTHLY'!Q$3,'P&L ACTUALS+EST'!$B$2:$Y$2,0)),0) -> 2786339.9 | R14: =_xlfn.IFNA(INDEX('P&L ACTUALS+EST'!$B$3:$Y$18,MATCH('P&L MONTHLY'!$A14,'P&L ACTUALS+EST'!$A$3:$A$18,0),MATCH('P&L MONTHLY'!R$3,'P&L ACTUALS+EST'!$B$2:$Y$2,0)),0) -> 4451142.2 | S14: =_xlfn.IFNA(INDEX('P&L ACTUALS+EST'!$B$3:$Y$18,MATCH('P&L MONTHLY'!$A14,'P&L ACTUALS+EST'!$A$3:$A$18,0),MATCH('P&L MONTHLY'!S$3,'P&L ACTUALS+EST'!$B$2:$Y$2,0)),0) -> 4581593.7 | T14: =Q14-S14 -> -1795253.8 | U14: =T14/S14 -> -0.39184047 | V14: =_xlfn.IFNA(INDEX('P&L ACTUALS+EST'!$B$3:$Y$18,MATCH('P&L MONTHLY'!$A14,'P&L ACTUALS+EST'!$A$3:$A$18,0),MATCH('P&L MONTHLY'!V$3,'P&L ACTUALS+EST'!$B$2:$Y$2,0)),0) -> 3015256.9 | W14: =_xlfn.IFNA(INDEX('P&L ACTUALS+EST'!$B$3:$Y$18,MATCH('P&L MONTHLY'!$A14,'P&L ACTUALS+EST'!$A$3:$A$18,0),MATCH('P&L MONTHLY'!W$3,'P&L ACTUALS+EST'!$B$2:$Y$2,0)),0) -> 3959340.7 | X14: =_xlfn.IFNA(INDEX('P&L ACTUALS+EST'!$B$3:$Y$18,MATCH('P&L MONTHLY'!$A14,'P&L ACTUALS+EST'!$A$3:$A$18,0),MATCH('P&L MONTHLY'!X$3,'P&L ACTUALS+EST'!$B$2:$Y$2,0)),0) -> 4165929.9 | Y14: =V14-X14 -> -1150673 | Z14: =Y14/X14 -> -0.27621035 | AA14: =_xlfn.IFNA(INDEX('P&L ACTUALS+EST'!$B$3:$Y$18,MATCH('P&L MONTHLY'!$A14,'P&L ACTUALS+EST'!$A$3:$A$18,0),MATCH('P&L MONTHLY'!AA$3,'P&L ACTUALS+EST'!$B$2:$Y$2,0)),0) -> 2639969.6 | AB14: =_xlfn.IFNA(INDEX('P&L ACTUALS+EST'!$B$3:$Y$18,MATCH('P&L MONTHLY'!$A14,'P&L ACTUALS+EST'!$A$3:$A$18,0),MATCH('P&L MONTHLY'!AB$3,'P&L ACTUALS+EST'!$B$2:$Y$2,0)),0) -> 3207221.3 | AC14: =_xlfn.IFNA(INDEX('P&L ACTUALS+EST'!$B$3:$Y$18,MATCH('P&L MONTHLY'!$A14,'P&L ACTUALS+EST'!$A$3:$A$18,0),MATCH('P&L MONTHLY'!AC$3,'P&L ACTUALS+EST'!$B$2:$Y$2,0)),0) -> 3437523.3 | AD14: =AA14-AC14 -> -797553.65 | AE14: =AD14/AC14 -> -0.23201404 | AF14: =SUMIF($B$5:$AE$5,AF$5,$B14:$AE14) -> 16542514 | AG14: =SUMIF($B$5:$AE$5,AG$5,$B14:$AE14) -> 21758025 | AH14: =SUMIF($B$5:$AE$5,AH$5,$B14:$AE14) -> 22936822 | AI14: =AF14-AG14 -> -5215511.2 | AJ14: =(AF14-AH14)/AH14 -> -0.27877917
A15: Contribution profit % | B15: =B14/B6 -> 0.10516047 | C15: =C14/C6 -> 0.13130721 | D15: =D14/D6 -> 0.13349942 | E15: =B15-D15 -> -0.028338944 | F15: =E15/D15 -> -0.21227766 | G15: =G14/G6 -> 0.10886367 | H15: =H14/H6 -> 0.13598907 | I15: =I14/I6 -> 0.13766948 | J15: =G15-I15 -> -0.028805808 | K15: =J15/I15 -> -0.20923889 | L15: =L14/L6 -> 0.12239738 | M15: =M14/M6 -> 0.14279241 | N15: =N14/N6 -> 0.14166458 | O15: =L15-N15 -> -0.019267203 | P15: =O15/N15 -> -0.13600579 | Q15: =Q14/Q6 -> 0.1267112 | R15: =R14/R6 -> 0.14833282 | S15: =S14/S6 -> 0.14485776 | T15: =Q15-S15 -> -0.018146556 | U15: =T15/S15 -> -0.12527155 | V15: =V14/V6 -> 0.1288348 | W15: =W14/W6 -> 0.14668042 | X15: =X14/X6 -> 0.14670519 | Y15: =V15-X15 -> -0.017870392 | Z15: =Y15/X15 -> -0.12181158 | AA15: =AA14/AA6 -> 0.12488072 | AB15: =AB14/AB6 -> 0.14721458 | AC15: =AC14/AC6 -> 0.15041531 | AD15: =AA15-AC15 -> -0.025534592 | AE15: =AD15/AC15 -> -0.16976059 | AF15: =AF14/AF6 -> 0.11991141 | AG15: =AG14/AG6 -> 0.14280146 | AH15: =AH14/AH6 -> 0.14284792 | AI15: =AF15-AH15 -> -0.022936505 | AJ15: =AI15/AH15 -> -0.16056591
A16: LABOUR | B16: =_xlfn.IFNA(INDEX('P&L ACTUALS+EST'!$B$3:$Y$18,MATCH('P&L MONTHLY'!$A16,'P&L ACTUALS+EST'!$A$3:$A$18,0),MATCH('P&L MONTHLY'!B$3,'P&L ACTUALS+EST'!$B$2:$Y$2,0)),0) -> -1573719.8 | C16: =_xlfn.IFNA(INDEX('P&L ACTUALS+EST'!$B$3:$Y$18,MATCH('P&L MONTHLY'!$A16,'P&L ACTUALS+EST'!$A$3:$A$18,0),MATCH('P&L MONTHLY'!C$3,'P&L ACTUALS+EST'!$B$2:$Y$2,0)),0) -> -1555136.1 | D16: =_xlfn.IFNA(INDEX('P&L ACTUALS+EST'!$B$3:$Y$18,MATCH('P&L MONTHLY'!$A16,'P&L ACTUALS+EST'!$A$3:$A$18,0),MATCH('P&L MONTHLY'!D$3,'P&L ACTUALS+EST'!$B$2:$Y$2,0)),0) -> -1539741.9 | E16: =B16-D16 -> -33977.86 | F16: =(B16-D16)/D16 -> 0.022067244 | G16: =_xlfn.IFNA(INDEX('P&L ACTUALS+EST'!$B$3:$Y$18,MATCH('P&L MONTHLY'!$A16,'P&L ACTUALS+EST'!$A$3:$A$18,0),MATCH('P&L MONTHLY'!G$3,'P&L ACTUALS+EST'!$B$2:$Y$2,0)),0) -> -1593334 | H16: =_xlfn.IFNA(INDEX('P&L ACTUALS+EST'!$B$3:$Y$18,MATCH('P&L MONTHLY'!$A16,'P&L ACTUALS+EST'!$A$3:$A$18,0),MATCH('P&L MONTHLY'!H$3,'P&L ACTUALS+EST'!$B$2:$Y$2,0)),0) -> -1562598.6 | I16: =_xlfn.IFNA(INDEX('P&L ACTUALS+EST'!$B$3:$Y$18,MATCH('P&L MONTHLY'!$A16,'P&L ACTUALS+EST'!$A$3:$A$18,0),MATCH('P&L MONTHLY'!I$3,'P&L ACTUALS+EST'!$B$2:$Y$2,0)),0) -> -1539741.9 | J16: =G16-I16 -> -53592.141 | K16: =J16/I16 -> 0.034805925 | L16: =_xlfn.IFNA(INDEX('P&L ACTUALS+EST'!$B$3:$Y$18,MATCH('P&L MONTHLY'!$A16,'P&L ACTUALS+EST'!$A$3:$A$18,0),MATCH('P&L MONTHLY'!L$3,'P&L ACTUALS+EST'!$B$2:$Y$2,0)),0) -> -1595185.7 | M16: =_xlfn.IFNA(INDEX('P&L ACTUALS+EST'!$B$3:$Y$18,MATCH('P&L MONTHLY'!$A16,'P&L ACTUALS+EST'!$A$3:$A$18,0),MATCH('P&L MONTHLY'!M$3,'P&L ACTUALS+EST'!$B$2:$Y$2,0)),0) -> -1567812 | N16: =_xlfn.IFNA(INDEX('P&L ACTUALS+EST'!$B$3:$Y$18,MATCH('P&L MONTHLY'!$A16,'P&L ACTUALS+EST'!$A$3:$A$18,0),MATCH('P&L MONTHLY'!N$3,'P&L ACTUALS+EST'!$B$2:$Y$2,0)),0) -> -1539741.9 | O16: =L16-N16 -> -55443.787 | P16: =O16/N16 -> 0.036008494 | Q16: =_xlfn.IFNA(INDEX('P&L ACTUALS+EST'!$B$3:$Y$18,MATCH('P&L MONTHLY'!$A16,'P&L ACTUALS+EST'!$A$3:$A$18,0),MATCH('P&L MONTHLY'!Q$3,'P&L ACTUALS+EST'!$B$2:$Y$2,0)),0) -> -1591764.3 | R16: =_xlfn.IFNA(INDEX('P&L ACTUALS+EST'!$B$3:$Y$18,MATCH('P&L MONTHLY'!$A16,'P&L ACTUALS+EST'!$A$3:$A$18,0),MATCH('P&L MONTHLY'!R$3,'P&L ACTUALS+EST'!$B$2:$Y$2,0)),0) -> -1544263.2 | S16: =_xlfn.IFNA(INDEX('P&L ACTUALS+EST'!$B$3:$Y$18,MATCH('P&L MONTHLY'!$A16,'P&L ACTUALS+EST'!$A$3:$A$18,0),MATCH('P&L MONTHLY'!S$3,'P&L ACTUALS+EST'!$B$2:$Y$2,0)),0) -> -1539741.9 | T16: =Q16-S16 -> -52022.387 | U16: =T16/S16 -> 0.033786434 | V16: =_xlfn.IFNA(INDEX('P&L ACTUALS+EST'!$B$3:$Y$18,MATCH('P&L MONTHLY'!$A16,'P&L ACTUALS+EST'!$A$3:$A$18,0),MATCH('P&L MONTHLY'!V$3,'P&L ACTUALS+EST'!$B$2:$Y$2,0)),0) -> -1581072.6 | W16: =_xlfn.IFNA(INDEX('P&L ACTUALS+EST'!$B$3:$Y$18,MATCH('P&L MONTHLY'!$A16,'P&L ACTUALS+EST'!$A$3:$A$18,0),MATCH('P&L MONTHLY'!W$3,'P&L ACTUALS+EST'!$B$2:$Y$2,0)),0) -> -1539991.1 | X16: =_xlfn.IFNA(INDEX('P&L ACTUALS+EST'!$B$3:$Y$18,MATCH('P&L MONTHLY'!$A16,'P&L ACTUALS+EST'!$A$3:$A$18,0),MATCH('P&L MONTHLY'!X$3,'P&L ACTUALS+EST'!$B$2:$Y$2,0)),0) -> -1539741.9 | Y16: =V16-X16 -> -41330.695 | Z16: =Y16/X16 -> 0.026842612 | AA16: =_xlfn.IFNA(INDEX('P&L ACTUALS+EST'!$B$3:$Y$18,MATCH('P&L MONTHLY'!$A16,'P&L ACTUALS+EST'!$A$3:$A$18,0),MATCH('P&L MONTHLY'!AA$3,'P&L ACTUALS+EST'!$B$2:$Y$2,0)),0) -> -1592239.5 | AB16: =_xlfn.IFNA(INDEX('P&L ACTUALS+EST'!$B$3:$Y$18,MATCH('P&L MONTHLY'!$A16,'P&L ACTUALS+EST'!$A$3:$A$18,0),MATCH('P&L MONTHLY'!AB$3,'P&L ACTUALS+EST'!$B$2:$Y$2,0)),0) -> -1548088.8 | AC16: =_xlfn.IFNA(INDEX('P&L ACTUALS+EST'!$B$3:$Y$18,MATCH('P&L MONTHLY'!$A16,'P&L ACTUALS+EST'!$A$3:$A$18,0),MATCH('P&L MONTHLY'!AC$3,'P&L ACTUALS+EST'!$B$2:$Y$2,0)),0) -> -1539741.9 | AD16: =AA16-AC16 -> -52497.613 | AE16: =AD16/AC16 -> 0.034095073 | AF16: =SUMIF($B$5:$AE$5,AF$5,$B16:$AE16) -> -9527315.9 | AG16: =SUMIF($B$5:$AE$5,AG$5,$B16:$AE16) -> -9317889.7 | AH16: =SUMIF($B$5:$AE$5,AH$5,$B16:$AE16) -> -9238451.4 | AI16: =AF16-AG16 -> -209426.16 | AJ16: =(AF16-AH16)/AH16 -> 0.03126763
A17: MARKETING | B17: =_xlfn.IFNA(INDEX('P&L ACTUALS+EST'!$B$3:$Y$18,MATCH('P&L MONTHLY'!$A17,'P&L ACTUALS+EST'!$A$3:$A$18,0),MATCH('P&L MONTHLY'!B$3,'P&L ACTUALS+EST'!$B$2:$Y$2,0)),0) -> -573154.51 | C17: =_xlfn.IFNA(INDEX('P&L ACTUALS+EST'!$B$3:$Y$18,MATCH('P&L MONTHLY'!$A17,'P&L ACTUALS+EST'!$A$3:$A$18,0),MATCH('P&L MONTHLY'!C$3,'P&L ACTUALS+EST'!$B$2:$Y$2,0)),0) -> -555504.44 | D17: =_xlfn.IFNA(INDEX('P&L ACTUALS+EST'!$B$3:$Y$18,MATCH('P&L MONTHLY'!$A17,'P&L ACTUALS+EST'!$A$3:$A$18,0),MATCH('P&L MONTHLY'!D$3,'P&L ACTUALS+EST'!$B$2:$Y$2,0)),0) -> -594389.75 | E17: =B17-D17 -> 21235.243 | F17: =(B17-D17)/D17 -> -0.035726126 | G17: =_xlfn.IFNA(INDEX('P&L ACTUALS+EST'!$B$3:$Y$18,MATCH('P&L MONTHLY'!$A17,'P&L ACTUALS+EST'!$A$3:$A$18,0),MATCH('P&L MONTHLY'!G$3,'P&L ACTUALS+EST'!$B$2:$Y$2,0)),0) -> -605023.02 | H17: =_xlfn.IFNA(INDEX('P&L ACTUALS+EST'!$B$3:$Y$18,MATCH('P&L MONTHLY'!$A17,'P&L ACTUALS+EST'!$A$3:$A$18,0),MATCH('P&L MONTHLY'!H$3,'P&L ACTUALS+EST'!$B$2:$Y$2,0)),0) -> -611920.61 | I17: =_xlfn.IFNA(INDEX('P&L ACTUALS+EST'!$B$3:$Y$18,MATCH('P&L MONTHLY'!$A17,'P&L ACTUALS+EST'!$A$3:$A$18,0),MATCH('P&L MONTHLY'!I$3,'P&L ACTUALS+EST'!$B$2:$Y$2,0)),0) -> -654755.05 | J17: =G17-I17 -> 49732.031 | K17: =J17/I17 -> -0.07595517 | L17: =_xlfn.IFNA(INDEX('P&L ACTUALS+EST'!$B$3:$Y$18,MATCH('P&L MONTHLY'!$A17,'P&L ACTUALS+EST'!$A$3:$A$18,0),MATCH('P&L MONTHLY'!L$3,'P&L ACTUALS+EST'!$B$2:$Y$2,0)),0) -> -684557.04 | M17: =_xlfn.IFNA(INDEX('P&L ACTUALS+EST'!$B$3:$Y$18,MATCH('P&L MONTHLY'!$A17,'P&L ACTUALS+EST'!$A$3:$A$18,0),MATCH('P&L MONTHLY'!M$3,'P&L ACTUALS+EST'!$B$2:$Y$2,0)),0) -> -712614.07 | N17: =_xlfn.IFNA(INDEX('P&L ACTUALS+EST'!$B$3:$Y$18,MATCH('P&L MONTHLY'!$A17,'P&L ACTUALS+EST'!$A$3:$A$18,0),MATCH('P&L MONTHLY'!N$3,'P&L ACTUALS+EST'!$B$2:$Y$2,0)),0) -> -762497.05 | O17: =L17-N17 -> 77940.012 | P17: =O17/N17 -> -0.10221681 | Q17: =_xlfn.IFNA(INDEX('P&L ACTUALS+EST'!$B$3:$Y$18,MATCH('P&L MONTHLY'!$A17,'P&L ACTUALS+EST'!$A$3:$A$18,0),MATCH('P&L MONTHLY'!Q$3,'P&L ACTUALS+EST'!$B$2:$Y$2,0)),0) -> -651867.47 | R17: =_xlfn.IFNA(INDEX('P&L ACTUALS+EST'!$B$3:$Y$18,MATCH('P&L MONTHLY'!$A17,'P&L ACTUALS+EST'!$A$3:$A$18,0),MATCH('P&L MONTHLY'!R$3,'P&L ACTUALS+EST'!$B$2:$Y$2,0)),0) -> -746636.61 | S17: =_xlfn.IFNA(INDEX('P&L ACTUALS+EST'!$B$3:$Y$18,MATCH('P&L MONTHLY'!$A17,'P&L ACTUALS+EST'!$A$3:$A$18,0),MATCH('P&L MONTHLY'!S$3,'P&L ACTUALS+EST'!$B$2:$Y$2,0)),0) -> -798901.17 | T17: =Q17-S17 -> 147033.7 | U17: =T17/S17 -> -0.18404492 | V17: =_xlfn.IFNA(INDEX('P&L ACTUALS+EST'!$B$3:$Y$18,MATCH('P&L MONTHLY'!$A17,'P&L ACTUALS+EST'!$A$3:$A$18,0),MATCH('P&L MONTHLY'!V$3,'P&L ACTUALS+EST'!$B$2:$Y$2,0)),0) -> -566308.5 | W17: =_xlfn.IFNA(INDEX('P&L ACTUALS+EST'!$B$3:$Y$18,MATCH('P&L MONTHLY'!$A17,'P&L ACTUALS+EST'!$A$3:$A$18,0),MATCH('P&L MONTHLY'!W$3,'P&L ACTUALS+EST'!$B$2:$Y$2,0)),0) -> -671683.76 | X17: =_xlfn.IFNA(INDEX('P&L ACTUALS+EST'!$B$3:$Y$18,MATCH('P&L MONTHLY'!$A17,'P&L ACTUALS+EST'!$A$3:$A$18,0),MATCH('P&L MONTHLY'!X$3,'P&L ACTUALS+EST'!$B$2:$Y$2,0)),0) -> -718701.62 | Y17: =V17-X17 -> 152393.12 | Z17: =Y17/X17 -> -0.21203949 | AA17: =_xlfn.IFNA(INDEX('P&L ACTUALS+EST'!$B$3:$Y$18,MATCH('P&L MONTHLY'!$A17,'P&L ACTUALS+EST'!$A$3:$A$18,0),MATCH('P&L MONTHLY'!AA$3,'P&L ACTUALS+EST'!$B$2:$Y$2,0)),0) -> -555936.72 | AB17: =_xlfn.IFNA(INDEX('P&L ACTUALS+EST'!$B$3:$Y$18,MATCH('P&L MONTHLY'!$A17,'P&L ACTUALS+EST'!$A$3:$A$18,0),MATCH('P&L MONTHLY'!AB$3,'P&L ACTUALS+EST'!$B$2:$Y$2,0)),0) -> -634858.82 | AC17: =_xlfn.IFNA(INDEX('P&L ACTUALS+EST'!$B$3:$Y$18,MATCH('P&L MONTHLY'!$A17,'P&L ACTUALS+EST'!$A$3:$A$18,0),MATCH('P&L MONTHLY'!AC$3,'P&L ACTUALS+EST'!$B$2:$Y$2,0)),0) -> -679298.94 | AD17: =AA17-AC17 -> 123362.22 | AE17: =AD17/AC17 -> -0.18160225 | AF17: =SUMIF($B$5:$AE$5,AF$5,$B17:$AE17) -> -3636847.3 | AG17: =SUMIF($B$5:$AE$5,AG$5,$B17:$AE17) -> -3933218.3 | AH17: =SUMIF($B$5:$AE$5,AH$5,$B17:$AE17) -> -4208543.6 | AI17: =AF17-AG17 -> 296371.05 | AJ17: =(AF17-AH17)/AH17 -> -0.13584185
A18: RENT | B18: =_xlfn.IFNA(INDEX('P&L ACTUALS+EST'!$B$3:$Y$18,MATCH('P&L MONTHLY'!$A18,'P&L ACTUALS+EST'!$A$3:$A$18,0),MATCH('P&L MONTHLY'!B$3,'P&L ACTUALS+EST'!$B$2:$Y$2,0)),0) -> -96777.79 | C18: =_xlfn.IFNA(INDEX('P&L ACTUALS+EST'!$B$3:$Y$18,MATCH('P&L MONTHLY'!$A18,'P&L ACTUALS+EST'!$A$3:$A$18,0),MATCH('P&L MONTHLY'!C$3,'P&L ACTUALS+EST'!$B$2:$Y$2,0)),0) -> -97865.596 | D18: =_xlfn.IFNA(INDEX('P&L ACTUALS+EST'!$B$3:$Y$18,MATCH('P&L MONTHLY'!$A18,'P&L ACTUALS+EST'!$A$3:$A$18,0),MATCH('P&L MONTHLY'!D$3,'P&L ACTUALS+EST'!$B$2:$Y$2,0)),0) -> -98844.252 | E18: =B18-D18 -> 2066.4618 | F18: =(B18-D18)/D18 -> -0.020906241 | G18: =_xlfn.IFNA(INDEX('P&L ACTUALS+EST'!$B$3:$Y$18,MATCH('P&L MONTHLY'!$A18,'P&L ACTUALS+EST'!$A$3:$A$18,0),MATCH('P&L MONTHLY'!G$3,'P&L ACTUALS+EST'!$B$2:$Y$2,0)),0) -> -96777.79 | H18: =_xlfn.IFNA(INDEX('P&L ACTUALS+EST'!$B$3:$Y$18,MATCH('P&L MONTHLY'!$A18,'P&L ACTUALS+EST'!$A$3:$A$18,0),MATCH('P&L MONTHLY'!H$3,'P&L ACTUALS+EST'!$B$2:$Y$2,0)),0) -> -97865.596 | I18: =_xlfn.IFNA(INDEX('P&L ACTUALS+EST'!$B$3:$Y$18,MATCH('P&L MONTHLY'!$A18,'P&L ACTUALS+EST'!$A$3:$A$18,0),MATCH('P&L MONTHLY'!I$3,'P&L ACTUALS+EST'!$B$2:$Y$2,0)),0) -> -98844.252 | J18: =G18-I18 -> 2066.4618 | K18: =J18/I18 -> -0.020906241 | L18: =_xlfn.IFNA(INDEX('P&L ACTUALS+EST'!$B$3:$Y$18,MATCH('P&L MONTHLY'!$A18,'P&L ACTUALS+EST'!$A$3:$A$18,0),MATCH('P&L MONTHLY'!L$3,'P&L ACTUALS+EST'!$B$2:$Y$2,0)),0) -> -96777.79 | M18: =_xlfn.IFNA(INDEX('P&L ACTUALS+EST'!$B$3:$Y$18,MATCH('P&L MONTHLY'!$A18,'P&L ACTUALS+EST'!$A$3:$A$18,0),MATCH('P&L MONTHLY'!M$3,'P&L ACTUALS+EST'!$B$2:$Y$2,0)),0) -> -97605.447 | N18: =_xlfn.IFNA(INDEX('P&L ACTUALS+EST'!$B$3:$Y$18,MATCH('P&L MONTHLY'!$A18,'P&L ACTUALS+EST'!$A$3:$A$18,0),MATCH('P&L MONTHLY'!N$3,'P&L ACTUALS+EST'!$B$2:$Y$2,0)),0) -> -98581.501 | O18: =L18-N18 -> 1803.7111 | P18: =O18/N18 -> -0.018296648 | Q18: =_xlfn.IFNA(INDEX('P&L ACTUALS+EST'!$B$3:$Y$18,MATCH('P&L MONTHLY'!$A18,'P&L ACTUALS+EST'!$A$3:$A$18,0),MATCH('P&L MONTHLY'!Q$3,'P&L ACTUALS+EST'!$B$2:$Y$2,0)),0) -> -96777.79 | R18: =_xlfn.IFNA(INDEX('P&L ACTUALS+EST'!$B$3:$Y$18,MATCH('P&L MONTHLY'!$A18,'P&L ACTUALS+EST'!$A$3:$A$18,0),MATCH('P&L MONTHLY'!R$3,'P&L ACTUALS+EST'!$B$2:$Y$2,0)),0) -> -97605.447 | S18: =_xlfn.IFNA(INDEX('P&L ACTUALS+EST'!$B$3:$Y$18,MATCH('P&L MONTHLY'!$A18,'P&L ACTUALS+EST'!$A$3:$A$18,0),MATCH('P&L MONTHLY'!S$3,'P&L ACTUALS+EST'!$B$2:$Y$2,0)),0) -> -98581.501 | T18: =Q18-S18 -> 1803.7111 | U18: =T18/S18 -> -0.018296648 | V18: =_xlfn.IFNA(INDEX('P&L ACTUALS+EST'!$B$3:$Y$18,MATCH('P&L MONTHLY'!$A18,'P&L ACTUALS+EST'!$A$3:$A$18,0),MATCH('P&L MONTHLY'!V$3,'P&L ACTUALS+EST'!$B$2:$Y$2,0)),0) -> -96777.79 | W18: =_xlfn.IFNA(INDEX('P&L ACTUALS+EST'!$B$3:$Y$18,MATCH('P&L MONTHLY'!$A18,'P&L ACTUALS+EST'!$A$3:$A$18,0),MATCH('P&L MONTHLY'!W$3,'P&L ACTUALS+EST'!$B$2:$Y$2,0)),0) -> -97605.447 | X18: =_xlfn.IFNA(INDEX('P&L ACTUALS+EST'!$B$3:$Y$18,MATCH('P&L MONTHLY'!$A18,'P&L ACTUALS+EST'!$A$3:$A$18,0),MATCH('P&L MONTHLY'!X$3,'P&L ACTUALS+EST'!$B$2:$Y$2,0)),0) -> -98581.501 | Y18: =V18-X18 -> 1803.7111 | Z18: =Y18/X18 -> -0.018296648 | AA18: =_xlfn.IFNA(INDEX('P&L ACTUALS+EST'!$B$3:$Y$18,MATCH('P&L MONTHLY'!$A18,'P&L ACTUALS+EST'!$A$3:$A$18,0),MATCH('P&L MONTHLY'!AA$3,'P&L ACTUALS+EST'!$B$2:$Y$2,0)),0) -> -96777.79 | AB18: =_xlfn.IFNA(INDEX('P&L ACTUALS+EST'!$B$3:$Y$18,MATCH('P&L MONTHLY'!$A18,'P&L ACTUALS+EST'!$A$3:$A$18,0),MATCH('P&L MONTHLY'!AB$3,'P&L ACTUALS+EST'!$B$2:$Y$2,0)),0) -> -97610.712 | AC18: =_xlfn.IFNA(INDEX('P&L ACTUALS+EST'!$B$3:$Y$18,MATCH('P&L MONTHLY'!$A18,'P&L ACTUALS+EST'!$A$3:$A$18,0),MATCH('P&L MONTHLY'!AC$3,'P&L ACTUALS+EST'!$B$2:$Y$2,0)),0) -> -98586.819 | AD18: =AA18-AC18 -> 1809.0293 | AE18: =AD18/AC18 -> -0.018349606 | AF18: =SUMIF($B$5:$AE$5,AF$5,$B18:$AE18) -> -580666.74 | AG18: =SUMIF($B$5:$AE$5,AG$5,$B18:$AE18) -> -586158.24 | AH18: =SUMIF($B$5:$AE$5,AH$5,$B18:$AE18) -> -592019.83 | AI18: =AF18-AG18 -> 5491.5036 | AJ18: =(AF18-AH18)/AH18 -> -0.019176868
A19: TRAVEL | B19: =_xlfn.IFNA(INDEX('P&L ACTUALS+EST'!$B$3:$Y$18,MATCH('P&L MONTHLY'!$A19,'P&L ACTUALS+EST'!$A$3:$A$18,0),MATCH('P&L MONTHLY'!B$3,'P&L ACTUALS+EST'!$B$2:$Y$2,0)),0) -> -12843.86 | C19: =_xlfn.IFNA(INDEX('P&L ACTUALS+EST'!$B$3:$Y$18,MATCH('P&L MONTHLY'!$A19,'P&L ACTUALS+EST'!$A$3:$A$18,0),MATCH('P&L MONTHLY'!C$3,'P&L ACTUALS+EST'!$B$2:$Y$2,0)),0) -> -12827.643 | D19: =_xlfn.IFNA(INDEX('P&L ACTUALS+EST'!$B$3:$Y$18,MATCH('P&L MONTHLY'!$A19,'P&L ACTUALS+EST'!$A$3:$A$18,0),MATCH('P&L MONTHLY'!D$3,'P&L ACTUALS+EST'!$B$2:$Y$2,0)),0) -> -14849.6 | E19: =B19-D19 -> 2005.7402 | F19: =(B19-D19)/D19 -> -0.13507032 | G19: =_xlfn.IFNA(INDEX('P&L ACTUALS+EST'!$B$3:$Y$18,MATCH('P&L MONTHLY'!$A19,'P&L ACTUALS+EST'!$A$3:$A$18,0),MATCH('P&L MONTHLY'!G$3,'P&L ACTUALS+EST'!$B$2:$Y$2,0)),0) -> -9002.1466 | H19: =_xlfn.IFNA(INDEX('P&L ACTUALS+EST'!$B$3:$Y$18,MATCH('P&L MONTHLY'!$A19,'P&L ACTUALS+EST'!$A$3:$A$18,0),MATCH('P&L MONTHLY'!H$3,'P&L ACTUALS+EST'!$B$2:$Y$2,0)),0) -> -8990.7803 | I19: =_xlfn.IFNA(INDEX('P&L ACTUALS+EST'!$B$3:$Y$18,MATCH('P&L MONTHLY'!$A19,'P&L ACTUALS+EST'!$A$3:$A$18,0),MATCH('P&L MONTHLY'!I$3,'P&L ACTUALS+EST'!$B$2:$Y$2,0)),0) -> -10407.952 | J19: =G19-I19 -> 1405.8054 | K19: =J19/I19 -> -0.13507032 | L19: =_xlfn.IFNA(INDEX('P&L ACTUALS+EST'!$B$3:$Y$18,MATCH('P&L MONTHLY'!$A19,'P&L ACTUALS+EST'!$A$3:$A$18,0),MATCH('P&L MONTHLY'!L$3,'P&L ACTUALS+EST'!$B$2:$Y$2,0)),0) -> -674.07031 | M19: =_xlfn.IFNA(INDEX('P&L ACTUALS+EST'!$B$3:$Y$18,MATCH('P&L MONTHLY'!$A19,'P&L ACTUALS+EST'!$A$3:$A$18,0),MATCH('P&L MONTHLY'!M$3,'P&L ACTUALS+EST'!$B$2:$Y$2,0)),0) -> 0 | N19: =_xlfn.IFNA(INDEX('P&L ACTUALS+EST'!$B$3:$Y$18,MATCH('P&L MONTHLY'!$A19,'P&L ACTUALS+EST'!$A$3:$A$18,0),MATCH('P&L MONTHLY'!N$3,'P&L ACTUALS+EST'!$B$2:$Y$2,0)),0) -> 0 | O19: =L19-N19 -> -674.07031 | P19: =IFERROR(O19/N19,) -> 0 | Q19: =_xlfn.IFNA(INDEX('P&L ACTUALS+EST'!$B$3:$Y$18,MATCH('P&L MONTHLY'!$A19,'P&L ACTUALS+EST'!$A$3:$A$18,0),MATCH('P&L MONTHLY'!Q$3,'P&L ACTUALS+EST'!$B$2:$Y$2,0)),0) -> -782.94744 | R19: =_xlfn.IFNA(INDEX('P&L ACTUALS+EST'!$B$3:$Y$18,MATCH('P&L MONTHLY'!$A19,'P&L ACTUALS+EST'!$A$3:$A$18,0),MATCH('P&L MONTHLY'!R$3,'P&L ACTUALS+EST'!$B$2:$Y$2,0)),0) -> -3847.8 | S19: =_xlfn.IFNA(INDEX('P&L ACTUALS+EST'!$B$3:$Y$18,MATCH('P&L MONTHLY'!$A19,'P&L ACTUALS+EST'!$A$3:$A$18,0),MATCH('P&L MONTHLY'!S$3,'P&L ACTUALS+EST'!$B$2:$Y$2,0)),0) -> -4454.3095 | T19: =Q19-S19 -> 3671.362 | U19: =T19/S19 -> -0.82422698 | V19: =_xlfn.IFNA(INDEX('P&L ACTUALS+EST'!$B$3:$Y$18,MATCH('P&L MONTHLY'!$A19,'P&L ACTUALS+EST'!$A$3:$A$18,0),MATCH('P&L MONTHLY'!V$3,'P&L ACTUALS+EST'!$B$2:$Y$2,0)),0) -> -1103.4935 | W19: =_xlfn.IFNA(INDEX('P&L ACTUALS+EST'!$B$3:$Y$18,MATCH('P&L MONTHLY'!$A19,'P&L ACTUALS+EST'!$A$3:$A$18,0),MATCH('P&L MONTHLY'!W$3,'P&L ACTUALS+EST'!$B$2:$Y$2,0)),0) -> -7295.2231 | X19: =_xlfn.IFNA(INDEX('P&L ACTUALS+EST'!$B$3:$Y$18,MATCH('P&L MONTHLY'!$A19,'P&L ACTUALS+EST'!$A$3:$A$18,0),MATCH('P&L MONTHLY'!X$3,'P&L ACTUALS+EST'!$B$2:$Y$2,0)),0) -> -8445.1326 | Y19: =V19-X19 -> 7341.6391 | Z19: =Y19/X19 -> -0.86933379 | AA19: =_xlfn.IFNA(INDEX('P&L ACTUALS+EST'!$B$3:$Y$18,MATCH('P&L MONTHLY'!$A19,'P&L ACTUALS+EST'!$A$3:$A$18,0),MATCH('P&L MONTHLY'!AA$3,'P&L ACTUALS+EST'!$B$2:$Y$2,0)),0) -> -4852.5611 | AB19: =_xlfn.IFNA(INDEX('P&L ACTUALS+EST'!$B$3:$Y$18,MATCH('P&L MONTHLY'!$A19,'P&L ACTUALS+EST'!$A$3:$A$18,0),MATCH('P&L MONTHLY'!AB$3,'P&L ACTUALS+EST'!$B$2:$Y$2,0)),0) -> -7630.381 | AC19: =_xlfn.IFNA(INDEX('P&L ACTUALS+EST'!$B$3:$Y$18,MATCH('P&L MONTHLY'!$A19,'P&L ACTUALS+EST'!$A$3:$A$18,0),MATCH('P&L MONTHLY'!AC$3,'P&L ACTUALS+EST'!$B$2:$Y$2,0)),0) -> -8833.1198 | AD19: =AA19-AC19 -> 3980.5587 | AE19: =AD19/AC19 -> -0.45064018 | AF19: =SUMIF($B$5:$AE$5,AF$5,$B19:$AE19) -> -29259.079 | AG19: =SUMIF($B$5:$AE$5,AG$5,$B19:$AE19) -> -40591.827 | AH19: =SUMIF($B$5:$AE$5,AH$5,$B19:$AE19) -> -46990.114 | AI19: =AF19-AG19 -> 11332.748 | AJ19: =(AF19-AH19)/AH19 -> -0.37733544
A20: CONSULTING | B20: =_xlfn.IFNA(INDEX('P&L ACTUALS+EST'!$B$3:$Y$18,MATCH('P&L MONTHLY'!$A20,'P&L ACTUALS+EST'!$A$3:$A$18,0),MATCH('P&L MONTHLY'!B$3,'P&L ACTUALS+EST'!$B$2:$Y$2,0)),0) -> -17680.633 | C20: =_xlfn.IFNA(INDEX('P&L ACTUALS+EST'!$B$3:$Y$18,MATCH('P&L MONTHLY'!$A20,'P&L ACTUALS+EST'!$A$3:$A$18,0),MATCH('P&L MONTHLY'!C$3,'P&L ACTUALS+EST'!$B$2:$Y$2,0)),0) -> -17658.309 | D20: =_xlfn.IFNA(INDEX('P&L ACTUALS+EST'!$B$3:$Y$18,MATCH('P&L MONTHLY'!$A20,'P&L ACTUALS+EST'!$A$3:$A$18,0),MATCH('P&L MONTHLY'!D$3,'P&L ACTUALS+EST'!$B$2:$Y$2,0)),0) -> -17658.309 | E20: =B20-D20 -> -22.324031 | F20: =(B20-D20)/D20 -> 0.0012642225 | G20: =_xlfn.IFNA(INDEX('P&L ACTUALS+EST'!$B$3:$Y$18,MATCH('P&L MONTHLY'!$A20,'P&L ACTUALS+EST'!$A$3:$A$18,0),MATCH('P&L MONTHLY'!G$3,'P&L ACTUALS+EST'!$B$2:$Y$2,0)),0) -> -10325.982 | H20: =_xlfn.IFNA(INDEX('P&L ACTUALS+EST'!$B$3:$Y$18,MATCH('P&L MONTHLY'!$A20,'P&L ACTUALS+EST'!$A$3:$A$18,0),MATCH('P&L MONTHLY'!H$3,'P&L ACTUALS+EST'!$B$2:$Y$2,0)),0) -> -12474.306 | I20: =_xlfn.IFNA(INDEX('P&L ACTUALS+EST'!$B$3:$Y$18,MATCH('P&L MONTHLY'!$A20,'P&L ACTUALS+EST'!$A$3:$A$18,0),MATCH('P&L MONTHLY'!I$3,'P&L ACTUALS+EST'!$B$2:$Y$2,0)),0) -> -12474.306 | J20: =G20-I20 -> 2148.3246 | K20: =J20/I20 -> -0.17221997 | L20: =_xlfn.IFNA(INDEX('P&L ACTUALS+EST'!$B$3:$Y$18,MATCH('P&L MONTHLY'!$A20,'P&L ACTUALS+EST'!$A$3:$A$18,0),MATCH('P&L MONTHLY'!L$3,'P&L ACTUALS+EST'!$B$2:$Y$2,0)),0) -> -9534.6132 | M20: =_xlfn.IFNA(INDEX('P&L ACTUALS+EST'!$B$3:$Y$18,MATCH('P&L MONTHLY'!$A20,'P&L ACTUALS+EST'!$A$3:$A$18,0),MATCH('P&L MONTHLY'!M$3,'P&L ACTUALS+EST'!$B$2:$Y$2,0)),0) -> -27809.406 | N20: =_xlfn.IFNA(INDEX('P&L ACTUALS+EST'!$B$3:$Y$18,MATCH('P&L MONTHLY'!$A20,'P&L ACTUALS+EST'!$A$3:$A$18,0),MATCH('P&L MONTHLY'!N$3,'P&L ACTUALS+EST'!$B$2:$Y$2,0)),0) -> -15709.406 | O20: =L20-N20 -> 6174.7926 | P20: =O20/N20 -> -0.39306341 | Q20: =_xlfn.IFNA(INDEX('P&L ACTUALS+EST'!$B$3:$Y$18,MATCH('P&L MONTHLY'!$A20,'P&L ACTUALS+EST'!$A$3:$A$18,0),MATCH('P&L MONTHLY'!Q$3,'P&L ACTUALS+EST'!$B$2:$Y$2,0)),0) -> -14689.273 | R20: =_xlfn.IFNA(INDEX('P&L ACTUALS+EST'!$B$3:$Y$18,MATCH('P&L MONTHLY'!$A20,'P&L ACTUALS+EST'!$A$3:$A$18,0),MATCH('P&L MONTHLY'!R$3,'P&L ACTUALS+EST'!$B$2:$Y$2,0)),0) -> -24312.893 | S20: =_xlfn.IFNA(INDEX('P&L ACTUALS+EST'!$B$3:$Y$18,MATCH('P&L MONTHLY'!$A20,'P&L ACTUALS+EST'!$A$3:$A$18,0),MATCH('P&L MONTHLY'!S$3,'P&L ACTUALS+EST'!$B$2:$Y$2,0)),0) -> -14632.893 | T20: =Q20-S20 -> -56.379708 | U20: =T20/S20 -> 0.0038529434 | V20: =_xlfn.IFNA(INDEX('P&L ACTUALS+EST'!$B$3:$Y$18,MATCH('P&L MONTHLY'!$A20,'P&L ACTUALS+EST'!$A$3:$A$18,0),MATCH('P&L MONTHLY'!V$3,'P&L ACTUALS+EST'!$B$2:$Y$2,0)),0) -> -14917.041 | W20: =_xlfn.IFNA(INDEX('P&L ACTUALS+EST'!$B$3:$Y$18,MATCH('P&L MONTHLY'!$A20,'P&L ACTUALS+EST'!$A$3:$A$18,0),MATCH('P&L MONTHLY'!W$3,'P&L ACTUALS+EST'!$B$2:$Y$2,0)),0) -> -16361.729 | X20: =_xlfn.IFNA(INDEX('P&L ACTUALS+EST'!$B$3:$Y$18,MATCH('P&L MONTHLY'!$A20,'P&L ACTUALS+EST'!$A$3:$A$18,0),MATCH('P&L MONTHLY'!X$3,'P&L ACTUALS+EST'!$B$2:$Y$2,0)),0) -> -16361.729 | Y20: =V20-X20 -> 1444.6875 | Z20: =Y20/X20 -> -0.08829675 | AA20: =_xlfn.IFNA(INDEX('P&L ACTUALS+EST'!$B$3:$Y$18,MATCH('P&L MONTHLY'!$A20,'P&L ACTUALS+EST'!$A$3:$A$18,0),MATCH('P&L MONTHLY'!AA$3,'P&L ACTUALS+EST'!$B$2:$Y$2,0)),0) -> -24189.207 | AB20: =_xlfn.IFNA(INDEX('P&L ACTUALS+EST'!$B$3:$Y$18,MATCH('P&L MONTHLY'!$A20,'P&L ACTUALS+EST'!$A$3:$A$18,0),MATCH('P&L MONTHLY'!AB$3,'P&L ACTUALS+EST'!$B$2:$Y$2,0)),0) -> -19434.379 | AC20: =_xlfn.IFNA(INDEX('P&L ACTUALS+EST'!$B$3:$Y$18,MATCH('P&L MONTHLY'!$A20,'P&L ACTUALS+EST'!$A$3:$A$18,0),MATCH('P&L MONTHLY'!AC$3,'P&L ACTUALS+EST'!$B$2:$Y$2,0)),0) -> -20406.098 | AD20: =AA20-AC20 -> -3783.109 | AE20: =AD20/AC20 -> 0.18539111 | AF20: =SUMIF($B$5:$AE$5,AF$5,$B20:$AE20) -> -91336.748 | AG20: =SUMIF($B$5:$AE$5,AG$5,$B20:$AE20) -> -118051.02 | AH20: =SUMIF($B$5:$AE$5,AH$5,$B20:$AE20) -> -97242.74 | AI20: =AF20-AG20 -> 26714.273 | AJ20: =(AF20-AH20)/AH20 -> -0.060734528
A21: INSURANCES | B21: =_xlfn.IFNA(INDEX('P&L ACTUALS+EST'!$B$3:$Y$18,MATCH('P&L MONTHLY'!$A21,'P&L ACTUALS+EST'!$A$3:$A$18,0),MATCH('P&L MONTHLY'!B$3,'P&L ACTUALS+EST'!$B$2:$Y$2,0)),0) -> -98886.921 | C21: =_xlfn.IFNA(INDEX('P&L ACTUALS+EST'!$B$3:$Y$18,MATCH('P&L MONTHLY'!$A21,'P&L ACTUALS+EST'!$A$3:$A$18,0),MATCH('P&L MONTHLY'!C$3,'P&L ACTUALS+EST'!$B$2:$Y$2,0)),0) -> -98762.063 | D21: =_xlfn.IFNA(INDEX('P&L ACTUALS+EST'!$B$3:$Y$18,MATCH('P&L MONTHLY'!$A21,'P&L ACTUALS+EST'!$A$3:$A$18,0),MATCH('P&L MONTHLY'!D$3,'P&L ACTUALS+EST'!$B$2:$Y$2,0)),0) -> -103700.17 | E21: =B21-D21 -> 4813.2459 | F21: =(B21-D21)/D21 -> -0.046415026 | G21: =_xlfn.IFNA(INDEX('P&L ACTUALS+EST'!$B$3:$Y$18,MATCH('P&L MONTHLY'!$A21,'P&L ACTUALS+EST'!$A$3:$A$18,0),MATCH('P&L MONTHLY'!G$3,'P&L ACTUALS+EST'!$B$2:$Y$2,0)),0) -> -42314.332 | H21: =_xlfn.IFNA(INDEX('P&L ACTUALS+EST'!$B$3:$Y$18,MATCH('P&L MONTHLY'!$A21,'P&L ACTUALS+EST'!$A$3:$A$18,0),MATCH('P&L MONTHLY'!H$3,'P&L ACTUALS+EST'!$B$2:$Y$2,0)),0) -> -42260.905 | I21: =_xlfn.IFNA(INDEX('P&L ACTUALS+EST'!$B$3:$Y$18,MATCH('P&L MONTHLY'!$A21,'P&L ACTUALS+EST'!$A$3:$A$18,0),MATCH('P&L MONTHLY'!I$3,'P&L ACTUALS+EST'!$B$2:$Y$2,0)),0) -> -44373.95 | J21: =G21-I21 -> 2059.6181 | K21: =J21/I21 -> -0.046415026 | L21: =_xlfn.IFNA(INDEX('P&L ACTUALS+EST'!$B$3:$Y$18,MATCH('P&L MONTHLY'!$A21,'P&L ACTUALS+EST'!$A$3:$A$18,0),MATCH('P&L MONTHLY'!L$3,'P&L ACTUALS+EST'!$B$2:$Y$2,0)),0) -> -75793.241 | M21: =_xlfn.IFNA(INDEX('P&L ACTUALS+EST'!$B$3:$Y$18,MATCH('P&L MONTHLY'!$A21,'P&L ACTUALS+EST'!$A$3:$A$18,0),MATCH('P&L MONTHLY'!M$3,'P&L ACTUALS+EST'!$B$2:$Y$2,0)),0) -> -64307.628 | N21: =_xlfn.IFNA(INDEX('P&L ACTUALS+EST'!$B$3:$Y$18,MATCH('P&L MONTHLY'!$A21,'P&L ACTUALS+EST'!$A$3:$A$18,0),MATCH('P&L MONTHLY'!N$3,'P&L ACTUALS+EST'!$B$2:$Y$2,0)),0) -> -67523.009 | O21: =L21-N21 -> -8270.2319 | P21: =O21/N21 -> 0.1224802 | Q21: =_xlfn.IFNA(INDEX('P&L ACTUALS+EST'!$B$3:$Y$18,MATCH('P&L MONTHLY'!$A21,'P&L ACTUALS+EST'!$A$3:$A$18,0),MATCH('P&L MONTHLY'!Q$3,'P&L ACTUALS+EST'!$B$2:$Y$2,0)),0) -> -36622.235 | R21: =_xlfn.IFNA(INDEX('P&L ACTUALS+EST'!$B$3:$Y$18,MATCH('P&L MONTHLY'!$A21,'P&L ACTUALS+EST'!$A$3:$A$18,0),MATCH('P&L MONTHLY'!R$3,'P&L ACTUALS+EST'!$B$2:$Y$2,0)),0) -> -24900.348 | S21: =_xlfn.IFNA(INDEX('P&L ACTUALS+EST'!$B$3:$Y$18,MATCH('P&L MONTHLY'!$A21,'P&L ACTUALS+EST'!$A$3:$A$18,0),MATCH('P&L MONTHLY'!S$3,'P&L ACTUALS+EST'!$B$2:$Y$2,0)),0) -> -26145.365 | T21: =Q21-S21 -> -10476.869 | U21: =T21/S21 -> 0.40071612 | V21: =_xlfn.IFNA(INDEX('P&L ACTUALS+EST'!$B$3:$Y$18,MATCH('P&L MONTHLY'!$A21,'P&L ACTUALS+EST'!$A$3:$A$18,0),MATCH('P&L MONTHLY'!V$3,'P&L ACTUALS+EST'!$B$2:$Y$2,0)),0) -> -34524.975 | W21: =_xlfn.IFNA(INDEX('P&L ACTUALS+EST'!$B$3:$Y$18,MATCH('P&L MONTHLY'!$A21,'P&L ACTUALS+EST'!$A$3:$A$18,0),MATCH('P&L MONTHLY'!W$3,'P&L ACTUALS+EST'!$B$2:$Y$2,0)),0) -> -26122.569 | X21: =_xlfn.IFNA(INDEX('P&L ACTUALS+EST'!$B$3:$Y$18,MATCH('P&L MONTHLY'!$A21,'P&L ACTUALS+EST'!$A$3:$A$18,0),MATCH('P&L MONTHLY'!X$3,'P&L ACTUALS+EST'!$B$2:$Y$2,0)),0) -> -27428.697 | Y21: =V21-X21 -> -7096.2779 | Z21: =Y21/X21 -> 0.25871728 | AA21: =_xlfn.IFNA(INDEX('P&L ACTUALS+EST'!$B$3:$Y$18,MATCH('P&L MONTHLY'!$A21,'P&L ACTUALS+EST'!$A$3:$A$18,0),MATCH('P&L MONTHLY'!AA$3,'P&L ACTUALS+EST'!$B$2:$Y$2,0)),0) -> -35273.148 | AB21: =_xlfn.IFNA(INDEX('P&L ACTUALS+EST'!$B$3:$Y$18,MATCH('P&L MONTHLY'!$A21,'P&L ACTUALS+EST'!$A$3:$A$18,0),MATCH('P&L MONTHLY'!AB$3,'P&L ACTUALS+EST'!$B$2:$Y$2,0)),0) -> -60341.551 | AC21: =_xlfn.IFNA(INDEX('P&L ACTUALS+EST'!$B$3:$Y$18,MATCH('P&L MONTHLY'!$A21,'P&L ACTUALS+EST'!$A$3:$A$18,0),MATCH('P&L MONTHLY'!AC$3,'P&L ACTUALS+EST'!$B$2:$Y$2,0)),0) -> -63358.628 | AD21: =AA21-AC21 -> 28085.48 | AE21: =AD21/AC21 -> -0.44327791 | AF21: =SUMIF($B$5:$AE$5,AF$5,$B21:$AE21) -> -323414.85 | AG21: =SUMIF($B$5:$AE$5,AG$5,$B21:$AE21) -> -316695.06 | AH21: =SUMIF($B$5:$AE$5,AH$5,$B21:$AE21) -> -332529.82 | AI21: =AF21-AG21 -> -6719.7881 | AJ21: =(AF21-AH21)/AH21 -> -0.027410971
A22: OPEX | B22: =_xlfn.IFNA(INDEX('P&L ACTUALS+EST'!$B$3:$Y$18,MATCH('P&L MONTHLY'!$A22,'P&L ACTUALS+EST'!$A$3:$A$18,0),MATCH('P&L MONTHLY'!B$3,'P&L ACTUALS+EST'!$B$2:$Y$2,0)),0) -> -2373063.5 | C22: =_xlfn.IFNA(INDEX('P&L ACTUALS+EST'!$B$3:$Y$18,MATCH('P&L MONTHLY'!$A22,'P&L ACTUALS+EST'!$A$3:$A$18,0),MATCH('P&L MONTHLY'!C$3,'P&L ACTUALS+EST'!$B$2:$Y$2,0)),0) -> -2337754.1 | D22: =_xlfn.IFNA(INDEX('P&L ACTUALS+EST'!$B$3:$Y$18,MATCH('P&L MONTHLY'!$A22,'P&L ACTUALS+EST'!$A$3:$A$18,0),MATCH('P&L MONTHLY'!D$3,'P&L ACTUALS+EST'!$B$2:$Y$2,0)),0) -> -2369184 | E22: =B22-D22 -> -3879.4925 | F22: =(B22-D22)/D22 -> 0.0016374805 | G22: =_xlfn.IFNA(INDEX('P&L ACTUALS+EST'!$B$3:$Y$18,MATCH('P&L MONTHLY'!$A22,'P&L ACTUALS+EST'!$A$3:$A$18,0),MATCH('P&L MONTHLY'!G$3,'P&L ACTUALS+EST'!$B$2:$Y$2,0)),0) -> -2356777.3 | H22: =_xlfn.IFNA(INDEX('P&L ACTUALS+EST'!$B$3:$Y$18,MATCH('P&L MONTHLY'!$A22,'P&L ACTUALS+EST'!$A$3:$A$18,0),MATCH('P&L MONTHLY'!H$3,'P&L ACTUALS+EST'!$B$2:$Y$2,0)),0) -> -2336110.8 | I22: =_xlfn.IFNA(INDEX('P&L ACTUALS+EST'!$B$3:$Y$18,MATCH('P&L MONTHLY'!$A22,'P&L ACTUALS+EST'!$A$3:$A$18,0),MATCH('P&L MONTHLY'!I$3,'P&L ACTUALS+EST'!$B$2:$Y$2,0)),0) -> -2360597.4 | J22: =G22-I22 -> 3820.1 | K22: =J22/I22 -> -0.0016182768 | L22: =_xlfn.IFNA(INDEX('P&L ACTUALS+EST'!$B$3:$Y$18,MATCH('P&L MONTHLY'!$A22,'P&L ACTUALS+EST'!$A$3:$A$18,0),MATCH('P&L MONTHLY'!L$3,'P&L ACTUALS+EST'!$B$2:$Y$2,0)),0) -> -2462522.4 | M22: =_xlfn.IFNA(INDEX('P&L ACTUALS+EST'!$B$3:$Y$18,MATCH('P&L MONTHLY'!$A22,'P&L ACTUALS+EST'!$A$3:$A$18,0),MATCH('P&L MONTHLY'!M$3,'P&L ACTUALS+EST'!$B$2:$Y$2,0)),0) -> -2470148.5 | N22: =_xlfn.IFNA(INDEX('P&L ACTUALS+EST'!$B$3:$Y$18,MATCH('P&L MONTHLY'!$A22,'P&L ACTUALS+EST'!$A$3:$A$18,0),MATCH('P&L MONTHLY'!N$3,'P&L ACTUALS+EST'!$B$2:$Y$2,0)),0) -> -2484052.9 | O22: =L22-N22 -> 21530.427 | P22: =O22/N22 -> -0.0086674592 | Q22: =_xlfn.IFNA(INDEX('P&L ACTUALS+EST'!$B$3:$Y$18,MATCH('P&L MONTHLY'!$A22,'P&L ACTUALS+EST'!$A$3:$A$18,0),MATCH('P&L MONTHLY'!Q$3,'P&L ACTUALS+EST'!$B$2:$Y$2,0)),0) -> -2392504 | R22: =_xlfn.IFNA(INDEX('P&L ACTUALS+EST'!$B$3:$Y$18,MATCH('P&L MONTHLY'!$A22,'P&L ACTUALS+EST'!$A$3:$A$18,0),MATCH('P&L MONTHLY'!R$3,'P&L ACTUALS+EST'!$B$2:$Y$2,0)),0) -> -2441566.2 | S22: =_xlfn.IFNA(INDEX('P&L ACTUALS+EST'!$B$3:$Y$18,MATCH('P&L MONTHLY'!$A22,'P&L ACTUALS+EST'!$A$3:$A$18,0),MATCH('P&L MONTHLY'!S$3,'P&L ACTUALS+EST'!$B$2:$Y$2,0)),0) -> -2482457.1 | T22: =Q22-S22 -> 89953.138 | U22: =T22/S22 -> -0.036235525 | V22: =_xlfn.IFNA(INDEX('P&L ACTUALS+EST'!$B$3:$Y$18,MATCH('P&L MONTHLY'!$A22,'P&L ACTUALS+EST'!$A$3:$A$18,0),MATCH('P&L MONTHLY'!V$3,'P&L ACTUALS+EST'!$B$2:$Y$2,0)),0) -> -2294704.4 | W22: =_xlfn.IFNA(INDEX('P&L ACTUALS+EST'!$B$3:$Y$18,MATCH('P&L MONTHLY'!$A22,'P&L ACTUALS+EST'!$A$3:$A$18,0),MATCH('P&L MONTHLY'!W$3,'P&L ACTUALS+EST'!$B$2:$Y$2,0)),0) -> -2359059.9 | X22: =_xlfn.IFNA(INDEX('P&L ACTUALS+EST'!$B$3:$Y$18,MATCH('P&L MONTHLY'!$A22,'P&L ACTUALS+EST'!$A$3:$A$18,0),MATCH('P&L MONTHLY'!X$3,'P&L ACTUALS+EST'!$B$2:$Y$2,0)),0) -> -2409260.6 | Y22: =V22-X22 -> 114556.19 | Z22: =Y22/X22 -> -0.047548277 | AA22: =_xlfn.IFNA(INDEX('P&L ACTUALS+EST'!$B$3:$Y$18,MATCH('P&L MONTHLY'!$A22,'P&L ACTUALS+EST'!$A$3:$A$18,0),MATCH('P&L MONTHLY'!AA$3,'P&L ACTUALS+EST'!$B$2:$Y$2,0)),0) -> -2309268.9 | AB22: =_xlfn.IFNA(INDEX('P&L ACTUALS+EST'!$B$3:$Y$18,MATCH('P&L MONTHLY'!$A22,'P&L ACTUALS+EST'!$A$3:$A$18,0),MATCH('P&L MONTHLY'!AB$3,'P&L ACTUALS+EST'!$B$2:$Y$2,0)),0) -> -2367964.6 | AC22: =_xlfn.IFNA(INDEX('P&L ACTUALS+EST'!$B$3:$Y$18,MATCH('P&L MONTHLY'!$A22,'P&L ACTUALS+EST'!$A$3:$A$18,0),MATCH('P&L MONTHLY'!AC$3,'P&L ACTUALS+EST'!$B$2:$Y$2,0)),0) -> -2410225.5 | AD22: =AA22-AC22 -> 100956.56 | AE22: =AD22/AC22 -> -0.041886771 | AF22: =SUMIF($B$5:$AE$5,AF$5,$B22:$AE22) -> -14188841 | AG22: =SUMIF($B$5:$AE$5,AG$5,$B22:$AE22) -> -14312604 | AH22: =SUMIF($B$5:$AE$5,AH$5,$B22:$AE22) -> -14515777 | AI22: =AF22-AG22 -> 123763.62 | AJ22: =(AF22-AH22)/AH22 -> -0.022522867
A23: EBITDA | B23: =_xlfn.IFNA(INDEX('P&L ACTUALS+EST'!$B$3:$Y$18,MATCH('P&L MONTHLY'!$A23,'P&L ACTUALS+EST'!$A$3:$A$18,0),MATCH('P&L MONTHLY'!B$3,'P&L ACTUALS+EST'!$B$2:$Y$2,0)),0) -> -451763.03 | C23: =_xlfn.IFNA(INDEX('P&L ACTUALS+EST'!$B$3:$Y$18,MATCH('P&L MONTHLY'!$A23,'P&L ACTUALS+EST'!$A$3:$A$18,0),MATCH('P&L MONTHLY'!C$3,'P&L ACTUALS+EST'!$B$2:$Y$2,0)),0) -> 13028.88 | D23: =_xlfn.IFNA(INDEX('P&L ACTUALS+EST'!$B$3:$Y$18,MATCH('P&L MONTHLY'!$A23,'P&L ACTUALS+EST'!$A$3:$A$18,0),MATCH('P&L MONTHLY'!D$3,'P&L ACTUALS+EST'!$B$2:$Y$2,0)),0) -> 157711.02 | E23: =B23-D23 -> -609474.04 | F23: =E23/D23 -> -3.8644988 | G23: =_xlfn.IFNA(INDEX('P&L ACTUALS+EST'!$B$3:$Y$18,MATCH('P&L MONTHLY'!$A23,'P&L ACTUALS+EST'!$A$3:$A$18,0),MATCH('P&L MONTHLY'!G$3,'P&L ACTUALS+EST'!$B$2:$Y$2,0)),0) -> 265949.31 | H23: =_xlfn.IFNA(INDEX('P&L ACTUALS+EST'!$B$3:$Y$18,MATCH('P&L MONTHLY'!$A23,'P&L ACTUALS+EST'!$A$3:$A$18,0),MATCH('P&L MONTHLY'!H$3,'P&L ACTUALS+EST'!$B$2:$Y$2,0)),0) -> 873043.63 | I23: =_xlfn.IFNA(INDEX('P&L ACTUALS+EST'!$B$3:$Y$18,MATCH('P&L MONTHLY'!$A23,'P&L ACTUALS+EST'!$A$3:$A$18,0),MATCH('P&L MONTHLY'!I$3,'P&L ACTUALS+EST'!$B$2:$Y$2,0)),0) -> 1070145.6 | J23: =G23-I23 -> -804196.26 | K23: =J23/I23 -> -0.75148305 | L23: =_xlfn.IFNA(INDEX('P&L ACTUALS+EST'!$B$3:$Y$18,MATCH('P&L MONTHLY'!$A23,'P&L ACTUALS+EST'!$A$3:$A$18,0),MATCH('P&L MONTHLY'!L$3,'P&L ACTUALS+EST'!$B$2:$Y$2,0)),0) -> 1094397.7 | M23: =_xlfn.IFNA(INDEX('P&L ACTUALS+EST'!$B$3:$Y$18,MATCH('P&L MONTHLY'!$A23,'P&L ACTUALS+EST'!$A$3:$A$18,0),MATCH('P&L MONTHLY'!M$3,'P&L ACTUALS+EST'!$B$2:$Y$2,0)),0) -> 2110234.7 | N23: =_xlfn.IFNA(INDEX('P&L ACTUALS+EST'!$B$3:$Y$18,MATCH('P&L MONTHLY'!$A23,'P&L ACTUALS+EST'!$A$3:$A$18,0),MATCH('P&L MONTHLY'!N$3,'P&L ACTUALS+EST'!$B$2:$Y$2,0)),0) -> 2310084.2 | O23: =L23-N23 -> -1215686.4 | P23: =O23/N23 -> -0.526252 | Q23: =_xlfn.IFNA(INDEX('P&L ACTUALS+EST'!$B$3:$Y$18,MATCH('P&L MONTHLY'!$A23,'P&L ACTUALS+EST'!$A$3:$A$18,0),MATCH('P&L MONTHLY'!Q$3,'P&L ACTUALS+EST'!$B$2:$Y$2,0)),0) -> 393835.88 | R23: =_xlfn.IFNA(INDEX('P&L ACTUALS+EST'!$B$3:$Y$18,MATCH('P&L MONTHLY'!$A23,'P&L ACTUALS+EST'!$A$3:$A$18,0),MATCH('P&L MONTHLY'!R$3,'P&L ACTUALS+EST'!$B$2:$Y$2,0)),0) -> 2009576 | S23: =_xlfn.IFNA(INDEX('P&L ACTUALS+EST'!$B$3:$Y$18,MATCH('P&L MONTHLY'!$A23,'P&L ACTUALS+EST'!$A$3:$A$18,0),MATCH('P&L MONTHLY'!S$3,'P&L ACTUALS+EST'!$B$2:$Y$2,0)),0) -> 2099136.6 | T23: =Q23-S23 -> -1705300.7 | U23: =T23/S23 -> -0.81238196 | V23: =_xlfn.IFNA(INDEX('P&L ACTUALS+EST'!$B$3:$Y$18,MATCH('P&L MONTHLY'!$A23,'P&L ACTUALS+EST'!$A$3:$A$18,0),MATCH('P&L MONTHLY'!V$3,'P&L ACTUALS+EST'!$B$2:$Y$2,0)),0) -> 720552.52 | W23: =_xlfn.IFNA(INDEX('P&L ACTUALS+EST'!$B$3:$Y$18,MATCH('P&L MONTHLY'!$A23,'P&L ACTUALS+EST'!$A$3:$A$18,0),MATCH('P&L MONTHLY'!W$3,'P&L ACTUALS+EST'!$B$2:$Y$2,0)),0) -> 1600280.8 | X23: =_xlfn.IFNA(INDEX('P&L ACTUALS+EST'!$B$3:$Y$18,MATCH('P&L MONTHLY'!$A23,'P&L ACTUALS+EST'!$A$3:$A$18,0),MATCH('P&L MONTHLY'!X$3,'P&L ACTUALS+EST'!$B$2:$Y$2,0)),0) -> 1756669.3 | Y23: =V23-X23 -> -1036116.8 | Z23: =Y23/X23 -> -0.58981891 | AA23: =_xlfn.IFNA(INDEX('P&L ACTUALS+EST'!$B$3:$Y$18,MATCH('P&L MONTHLY'!$A23,'P&L ACTUALS+EST'!$A$3:$A$18,0),MATCH('P&L MONTHLY'!AA$3,'P&L ACTUALS+EST'!$B$2:$Y$2,0)),0) -> 330700.68 | AB23: =_xlfn.IFNA(INDEX('P&L ACTUALS+EST'!$B$3:$Y$18,MATCH('P&L MONTHLY'!$A23,'P&L ACTUALS+EST'!$A$3:$A$18,0),MATCH('P&L MONTHLY'!AB$3,'P&L ACTUALS+EST'!$B$2:$Y$2,0)),0) -> 839256.71 | AC23: =_xlfn.IFNA(INDEX('P&L ACTUALS+EST'!$B$3:$Y$18,MATCH('P&L MONTHLY'!$A23,'P&L ACTUALS+EST'!$A$3:$A$18,0),MATCH('P&L MONTHLY'!AC$3,'P&L ACTUALS+EST'!$B$2:$Y$2,0)),0) -> 1027297.8 | AD23: =AA23-AC23 -> -696597.08 | AE23: =AD23/AC23 -> -0.67808683 | AF23: =SUMIF($B$5:$AE$5,AF$5,$B23:$AE23) -> 2353673.1 | AG23: =SUMIF($B$5:$AE$5,AG$5,$B23:$AE23) -> 7445420.7 | AH23: =SUMIF($B$5:$AE$5,AH$5,$B23:$AE23) -> 8421044.4 | AI23: =AF23-AG23 -> -5091747.6 | AJ23: =(AF23-AH23)/AH23 -> -0.72050104
A24: EBITDA margin % | B24: =B23/B6 -> -0.024726801 | C24: =C23/C6 -> 0.00072775153 | D24: =D23/D6 -> 0.0083320948 | E24: =B24-D24 -> -0.033058896 | F24: =E24/D24 -> -3.9676571 | G24: =G23/G6 -> 0.011038977 | H24: =H23/H6 -> 0.036995538 | I24: =I23/I6 -> 0.042942996 | J24: =G24-I24 -> -0.031904019 | K24: =J24/I24 -> -0.74293883 | L24: =L23/L6 -> 0.037659382 | M24: =M23/M6 -> 0.065786089 | N24: =N23/N6 -> 0.068261942 | O24: =L24-N24 -> -0.030602561 | P24: =O24/N24 -> -0.44831073 | Q24: =Q23/Q6 -> 0.017910025 | R24: =R23/R6 -> 0.066968447 | S24: =S23/S6 -> 0.066369092 | T24: =Q24-S24 -> -0.048459067 | U24: =T24/S24 -> -0.73014509 | V24: =V23/V6 -> 0.030787506 | W24: =W23/W6 -> 0.059285088 | X24: =X23/X6 -> 0.061861941 | Y24: =V24-X24 -> -0.031074435 | Z24: =Y24/X24 -> -0.5023191 | AA24: =AA23/AA6 -> 0.015643415 | AB24: =AB23/AB6 -> 0.0385227 | AC24: =AC23/AC6 -> 0.044951351 | AD24: =AA24-AC24 -> -0.029307936 | AE24: =AD24/AC24 -> -0.65199233 | AF24: =AF23/AF6 -> 0.017061027 | AG24: =AG23/AG6 -> 0.048865507 | AH24: =AH23/AH6 -> 0.052445307 | AI24: =AF24-AH24 -> -0.03538428 | AJ24: =AI24/AH24 -> -0.67468916

Sheet KPI TRENDS
A1: KPI Dashboard — Monthly Performance Trends |Actuals vs Budget vs PY| Jan – Jun 2025
B2: 2025.01_act | C2: 2025.02_act | D2: 2025.03_act | E2: 2025.04_act | F2: 2025.05_act | G2: 2025.06_act | I2: 2025.01_est | J2: 2025.02_est | K2: 2025.03_est | L2: 2025.04_est | M2: 2025.05_est | N2: 2025.06_est
A3: KPI / Month | B3: 2025.01_act | C3: 2025.02_act | D3: 2025.03_act | E3: 2025.04_act | F3: 2025.05_act | G3: 2025.06_act | H3: YTD Act | I3: 2025.01_bud | J3: 2025.02_bud | K3: 2025.03_bud | L3: 2025.04_bud | M3: 2025.05_bud | N3: 2025.06_bud | O3: YTD Bud | P3: YTD PY
A4: REVENUE & MARGIN
A5: REVENUE | B5: =_xlfn.IFNA(INDEX('P&L ACTUALS+EST'!$B$3:$Y$18,MATCH('KPI TRENDS'!$A5,'P&L ACTUALS+EST'!$A$3:$A$18,0),MATCH(B$2,'P&L ACTUALS+EST'!$B$2:$Y$2,0)),0) -> 18270177 | C5: =_xlfn.IFNA(INDEX('P&L ACTUALS+EST'!$B$3:$Y$18,MATCH('KPI TRENDS'!$A5,'P&L ACTUALS+EST'!$A$3:$A$18,0),MATCH(C$2,'P&L ACTUALS+EST'!$B$2:$Y$2,0)),0) -> 24091845 | D5: =_xlfn.IFNA(INDEX('P&L ACTUALS+EST'!$B$3:$Y$18,MATCH('KPI TRENDS'!$A5,'P&L ACTUALS+EST'!$A$3:$A$18,0),MATCH(D$2,'P&L ACTUALS+EST'!$B$2:$Y$2,0)),0) -> 29060428 | E5: =_xlfn.IFNA(INDEX('P&L ACTUALS+EST'!$B$3:$Y$18,MATCH('KPI TRENDS'!$A5,'P&L ACTUALS+EST'!$A$3:$A$18,0),MATCH(E$2,'P&L ACTUALS+EST'!$B$2:$Y$2,0)),0) -> 21989689 | F5: =_xlfn.IFNA(INDEX('P&L ACTUALS+EST'!$B$3:$Y$18,MATCH('KPI TRENDS'!$A5,'P&L ACTUALS+EST'!$A$3:$A$18,0),MATCH(F$2,'P&L ACTUALS+EST'!$B$2:$Y$2,0)),0) -> 23404056 | G5: =_xlfn.IFNA(INDEX('P&L ACTUALS+EST'!$B$3:$Y$18,MATCH('KPI TRENDS'!$A5,'P&L ACTUALS+EST'!$A$3:$A$18,0),MATCH(G$2,'P&L ACTUALS+EST'!$B$2:$Y$2,0)),0) -> 21139929 | H5: =SUM(B5:G5) -> 1.3795612e+08 | I5: =_xlfn.IFNA(INDEX('P&L ACTUALS+EST'!$B$3:$Y$18,MATCH('KPI TRENDS'!$A5,'P&L ACTUALS+EST'!$A$3:$A$18,0),MATCH(I$2,'P&L ACTUALS+EST'!$B$2:$Y$2,0)),0) -> 18928135 | J5: =_xlfn.IFNA(INDEX('P&L ACTUALS+EST'!$B$3:$Y$18,MATCH('KPI TRENDS'!$A5,'P&L ACTUALS+EST'!$A$3:$A$18,0),MATCH(J$2,'P&L ACTUALS+EST'!$B$2:$Y$2,0)),0) -> 24920142 | K5: =_xlfn.IFNA(INDEX('P&L ACTUALS+EST'!$B$3:$Y$18,MATCH('KPI TRENDS'!$A5,'P&L ACTUALS+EST'!$A$3:$A$18,0),MATCH(K$2,'P&L ACTUALS+EST'!$B$2:$Y$2,0)),0) -> 33841465 | L5: =_xlfn.IFNA(INDEX('P&L ACTUALS+EST'!$B$3:$Y$18,MATCH('KPI TRENDS'!$A5,'P&L ACTUALS+EST'!$A$3:$A$18,0),MATCH(L$2,'P&L ACTUALS+EST'!$B$2:$Y$2,0)),0) -> 31628225 | M5: =_xlfn.IFNA(INDEX('P&L ACTUALS+EST'!$B$3:$Y$18,MATCH('KPI TRENDS'!$A5,'P&L ACTUALS+EST'!$A$3:$A$18,0),MATCH(M$2,'P&L ACTUALS+EST'!$B$2:$Y$2,0)),0) -> 28396608 | N5: =_xlfn.IFNA(INDEX('P&L ACTUALS+EST'!$B$3:$Y$18,MATCH('KPI TRENDS'!$A5,'P&L ACTUALS+EST'!$A$3:$A$18,0),MATCH(N$2,'P&L ACTUALS+EST'!$B$2:$Y$2,0)),0) -> 22853546 | O5: =SUM(I5:N5) -> 1.6056812e+08 | P5: =SUM('P&L ACTUALS+EST'!B3:G3) -> 1.5236557e+08
A6: GROSS PROFIT | B6: =_xlfn.IFNA(INDEX('P&L ACTUALS+EST'!$B$3:$Y$18,MATCH('KPI TRENDS'!$A6,'P&L ACTUALS+EST'!$A$3:$A$18,0),MATCH(B$2,'P&L ACTUALS+EST'!$B$2:$Y$2,0)),0) -> 7089689.1 | C6: =_xlfn.IFNA(INDEX('P&L ACTUALS+EST'!$B$3:$Y$18,MATCH('KPI TRENDS'!$A6,'P&L ACTUALS+EST'!$A$3:$A$18,0),MATCH(C$2,'P&L ACTUALS+EST'!$B$2:$Y$2,0)),0) -> 9381707.1 | D6: =_xlfn.IFNA(INDEX('P&L ACTUALS+EST'!$B$3:$Y$18,MATCH('KPI TRENDS'!$A6,'P&L ACTUALS+EST'!$A$3:$A$18,0),MATCH(D$2,'P&L ACTUALS+EST'!$B$2:$Y$2,0)),0) -> 11441565 | E6: =_xlfn.IFNA(INDEX('P&L ACTUALS+EST'!$B$3:$Y$18,MATCH('KPI TRENDS'!$A6,'P&L ACTUALS+EST'!$A$3:$A$18,0),MATCH(E$2,'P&L ACTUALS+EST'!$B$2:$Y$2,0)),0) -> 8705533.2 | F6: =_xlfn.IFNA(INDEX('P&L ACTUALS+EST'!$B$3:$Y$18,MATCH('KPI TRENDS'!$A6,'P&L ACTUALS+EST'!$A$3:$A$18,0),MATCH(F$2,'P&L ACTUALS+EST'!$B$2:$Y$2,0)),0) -> 9312671.2 | G6: =_xlfn.IFNA(INDEX('P&L ACTUALS+EST'!$B$3:$Y$18,MATCH('KPI TRENDS'!$A6,'P&L ACTUALS+EST'!$A$3:$A$18,0),MATCH(G$2,'P&L ACTUALS+EST'!$B$2:$Y$2,0)),0) -> 8293850.2 | H6: =SUM(B6:G6) -> 54225016 | I6: =_xlfn.IFNA(INDEX('P&L ACTUALS+EST'!$B$3:$Y$18,MATCH('KPI TRENDS'!$A6,'P&L ACTUALS+EST'!$A$3:$A$18,0),MATCH(I$2,'P&L ACTUALS+EST'!$B$2:$Y$2,0)),0) -> 7548874.2 | J6: =_xlfn.IFNA(INDEX('P&L ACTUALS+EST'!$B$3:$Y$18,MATCH('KPI TRENDS'!$A6,'P&L ACTUALS+EST'!$A$3:$A$18,0),MATCH(J$2,'P&L ACTUALS+EST'!$B$2:$Y$2,0)),0) -> 9979469.8 | K6: =_xlfn.IFNA(INDEX('P&L ACTUALS+EST'!$B$3:$Y$18,MATCH('KPI TRENDS'!$A6,'P&L ACTUALS+EST'!$A$3:$A$18,0),MATCH(K$2,'P&L ACTUALS+EST'!$B$2:$Y$2,0)),0) -> 13516066 | L6: =_xlfn.IFNA(INDEX('P&L ACTUALS+EST'!$B$3:$Y$18,MATCH('KPI TRENDS'!$A6,'P&L ACTUALS+EST'!$A$3:$A$18,0),MATCH(L$2,'P&L ACTUALS+EST'!$B$2:$Y$2,0)),0) -> 12653096 | M6: =_xlfn.IFNA(INDEX('P&L ACTUALS+EST'!$B$3:$Y$18,MATCH('KPI TRENDS'!$A6,'P&L ACTUALS+EST'!$A$3:$A$18,0),MATCH(M$2,'P&L ACTUALS+EST'!$B$2:$Y$2,0)),0) -> 11342312 | N6: =_xlfn.IFNA(INDEX('P&L ACTUALS+EST'!$B$3:$Y$18,MATCH('KPI TRENDS'!$A6,'P&L ACTUALS+EST'!$A$3:$A$18,0),MATCH(N$2,'P&L ACTUALS+EST'!$B$2:$Y$2,0)),0) -> 9124628 | O6: =SUM(I6:N6) -> 64164446 | P6: =SUM('P&L ACTUALS+EST'!B5:G5) -> 59153647
A7: Gross profit % | B7: =B6/B5 -> 0.38804709 | C7: =C6/C5 -> 0.38941423 | D7: =D6/D5 -> 0.39371634 | E7: =E6/E5 -> 0.39589161 | F7: =F6/F5 -> 0.39790843 | G7: =G6/G5 -> 0.39233102 | H7: =H6/H5 -> 0.39305987 | I7: =I6/I5 -> 0.39881764 | ... P7: =P6/P5 -> 0.388235
A8: COGS / REVENUE | B8: ='P&L ACTUALS+EST'!N4/B5 -> -0.61195291 | C8: ='P&L ACTUALS+EST'!O4/C5 -> -0.61058577 | D8: ='P&L ACTUALS+EST'!P4/D5 -> -0.60628366 | E8: ='P&L ACTUALS+EST'!Q4/E5 -> -0.60410839 | F8: ='P&L ACTUALS+EST'!R4/F5 -> -0.60209157 | G8: ='P&L ACTUALS+EST'!S4/G5 -> -0.60766898 | H8: =SUM('P&L ACTUALS+EST'!N4:S4)/H5 -> -0.60694013 | I8: ='Budget (from Controlling)_copy'!C5/I5 -> -0.60118236 | J8: ='Budget (from Controlling)_copy'!D5/J5 -> -0.59954202 | K8: ='Budget (from Controlling)_copy'!E5/K5 -> -0.60060636 | L8: ='Budget (from Controlling)_copy'!F5/L5 -> -0.5999429 | M8: ='Budget (from Controlling)_copy'!G5/M5 -> -0.6005751 | N8: ='Budget (from Controlling)_copy'!H5/N5 -> -0.6007347 | O8: =SUM('Budget (from Controlling)_copy'!C5:H5)/'KPI TRENDS'!O5 -> -0.60039113 | P8: =SUM('P&L ACTUALS+EST'!B4:G4)/'KPI TRENDS'!P5 -> -0.611765
A9: VARIABLE COSTS
A10: VARIABLE COSTS | B10: =_xlfn.IFNA(INDEX('P&L ACTUALS+EST'!$B$3:$Y$18,MATCH('KPI TRENDS'!$A10,'P&L ACTUALS+EST'!$A$3:$A$18,0),MATCH(B$2,'P&L ACTUALS+EST'!$B$2:$Y$2,0)),0) -> -5168388.6 | C10: =_xlfn.IFNA(INDEX('P&L ACTUALS+EST'!$B$3:$Y$18,MATCH('KPI TRENDS'!$A10,'P&L ACTUALS+EST'!$A$3:$A$18,0),MATCH(C$2,'P&L ACTUALS+EST'!$B$2:$Y$2,0)),0) -> -6758980.5 | D10: =_xlfn.IFNA(INDEX('P&L ACTUALS+EST'!$B$3:$Y$18,MATCH('KPI TRENDS'!$A10,'P&L ACTUALS+EST'!$A$3:$A$18,0),MATCH(D$2,'P&L ACTUALS+EST'!$B$2:$Y$2,0)),0) -> -7884645 | E10: =_xlfn.IFNA(INDEX('P&L ACTUALS+EST'!$B$3:$Y$18,MATCH('KPI TRENDS'!$A10,'P&L ACTUALS+EST'!$A$3:$A$18,0),MATCH(E$2,'P&L ACTUALS+EST'!$B$2:$Y$2,0)),0) -> -5919193.3 | F10: =_xlfn.IFNA(INDEX('P&L ACTUALS+EST'!$B$3:$Y$18,MATCH('KPI TRENDS'!$A10,'P&L ACTUALS+EST'!$A$3:$A$18,0),MATCH(F$2,'P&L ACTUALS+EST'!$B$2:$Y$2,0)),0) -> -6297414.3 | G10: =_xlfn.IFNA(INDEX('P&L ACTUALS+EST'!$B$3:$Y$18,MATCH('KPI TRENDS'!$A10,'P&L ACTUALS+EST'!$A$3:$A$18,0),MATCH(G$2,'P&L ACTUALS+EST'!$B$2:$Y$2,0)),0) -> -5653880.6 | H10: =SUM(B10:G10) -> -37682502 | I10: =_xlfn.IFNA(INDEX('P&L ACTUALS+EST'!$B$3:$Y$18,MATCH('KPI TRENDS'!$A10,'P&L ACTUALS+EST'!$A$3:$A$18,0),MATCH(I$2,'P&L ACTUALS+EST'!$B$2:$Y$2,0)),0) -> -5021979.2 | J10: =_xlfn.IFNA(INDEX('P&L ACTUALS+EST'!$B$3:$Y$18,MATCH('KPI TRENDS'!$A10,'P&L ACTUALS+EST'!$A$3:$A$18,0),MATCH(J$2,'P&L ACTUALS+EST'!$B$2:$Y$2,0)),0) -> -6548726.8 | K10: =_xlfn.IFNA(INDEX('P&L ACTUALS+EST'!$B$3:$Y$18,MATCH('KPI TRENDS'!$A10,'P&L ACTUALS+EST'!$A$3:$A$18,0),MATCH(K$2,'P&L ACTUALS+EST'!$B$2:$Y$2,0)),0) -> -8721929.1 | L10: =_xlfn.IFNA(INDEX('P&L ACTUALS+EST'!$B$3:$Y$18,MATCH('KPI TRENDS'!$A10,'P&L ACTUALS+EST'!$A$3:$A$18,0),MATCH(L$2,'P&L ACTUALS+EST'!$B$2:$Y$2,0)),0) -> -8071502 | M10: =_xlfn.IFNA(INDEX('P&L ACTUALS+EST'!$B$3:$Y$18,MATCH('KPI TRENDS'!$A10,'P&L ACTUALS+EST'!$A$3:$A$18,0),MATCH(M$2,'P&L ACTUALS+EST'!$B$2:$Y$2,0)),0) -> -7176382.5 | N10: =_xlfn.IFNA(INDEX('P&L ACTUALS+EST'!$B$3:$Y$18,MATCH('KPI TRENDS'!$A10,'P&L ACTUALS+EST'!$A$3:$A$18,0),MATCH(N$2,'P&L ACTUALS+EST'!$B$2:$Y$2,0)),0) -> -5687104.7 | O10: =SUM(I10:N10) -> -41227624 | P10: =SUM('P&L ACTUALS+EST'!B9:G9) -> -37395622
A11: VARIABLE COSTS / REVENUE | B11: =B10/B5 -> -0.28288662 | C11: =C10/C5 -> -0.28055056 | D11: =D10/D5 -> -0.27131896 | E11: =E10/E5 -> -0.2691804 | F11: =F10/F5 -> -0.26907363 | G11: =G10/G5 -> -0.2674503 | H11: =H10/H5 -> -0.27314846 | I11: =I10/I5 -> -0.26531822 | ... P11: =P10/P5 -> -0.24543355
A12: CONTRIBUTION PROFIT | B12: =_xlfn.IFNA(INDEX('P&L ACTUALS+EST'!$B$3:$Y$18,MATCH('KPI TRENDS'!$A12,'P&L ACTUALS+EST'!$A$3:$A$18,0),MATCH(B$2,'P&L ACTUALS+EST'!$B$2:$Y$2,0)),0) -> 1921300.4 | C12: =_xlfn.IFNA(INDEX('P&L ACTUALS+EST'!$B$3:$Y$18,MATCH('KPI TRENDS'!$A12,'P&L ACTUALS+EST'!$A$3:$A$18,0),MATCH(C$2,'P&L ACTUALS+EST'!$B$2:$Y$2,0)),0) -> 2622726.6 | D12: =_xlfn.IFNA(INDEX('P&L ACTUALS+EST'!$B$3:$Y$18,MATCH('KPI TRENDS'!$A12,'P&L ACTUALS+EST'!$A$3:$A$18,0),MATCH(D$2,'P&L ACTUALS+EST'!$B$2:$Y$2,0)),0) -> 3556920.2 | E12: =_xlfn.IFNA(INDEX('P&L ACTUALS+EST'!$B$3:$Y$18,MATCH('KPI TRENDS'!$A12,'P&L ACTUALS+EST'!$A$3:$A$18,0),MATCH(E$2,'P&L ACTUALS+EST'!$B$2:$Y$2,0)),0) -> 2786339.9 | F12: =_xlfn.IFNA(INDEX('P&L ACTUALS+EST'!$B$3:$Y$18,MATCH('KPI TRENDS'!$A12,'P&L ACTUALS+EST'!$A$3:$A$18,0),MATCH(F$2,'P&L ACTUALS+EST'!$B$2:$Y$2,0)),0) -> 3015256.9 | G12: =_xlfn.IFNA(INDEX('P&L ACTUALS+EST'!$B$3:$Y$18,MATCH('KPI TRENDS'!$A12,'P&L ACTUALS+EST'!$A$3:$A$18,0),MATCH(G$2,'P&L ACTUALS+EST'!$B$2:$Y$2,0)),0) -> 2639969.6 | H12: =SUM(B12:G12) -> 16542514 | I12: =_xlfn.IFNA(INDEX('P&L ACTUALS+EST'!$B$3:$Y$18,MATCH('KPI TRENDS'!$A12,'P&L ACTUALS+EST'!$A$3:$A$18,0),MATCH(I$2,'P&L ACTUALS+EST'!$B$2:$Y$2,0)),0) -> 2526895 | J12: =_xlfn.IFNA(INDEX('P&L ACTUALS+EST'!$B$3:$Y$18,MATCH('KPI TRENDS'!$A12,'P&L ACTUALS+EST'!$A$3:$A$18,0),MATCH(J$2,'P&L ACTUALS+EST'!$B$2:$Y$2,0)),0) -> 3430743 | K12: =_xlfn.IFNA(INDEX('P&L ACTUALS+EST'!$B$3:$Y$18,MATCH('KPI TRENDS'!$A12,'P&L ACTUALS+EST'!$A$3:$A$18,0),MATCH(K$2,'P&L ACTUALS+EST'!$B$2:$Y$2,0)),0) -> 4794137 | L12: =_xlfn.IFNA(INDEX('P&L ACTUALS+EST'!$B$3:$Y$18,MATCH('KPI TRENDS'!$A12,'P&L ACTUALS+EST'!$A$3:$A$18,0),MATCH(L$2,'P&L ACTUALS+EST'!$B$2:$Y$2,0)),0) -> 4581593.7 | M12: =_xlfn.IFNA(INDEX('P&L ACTUALS+EST'!$B$3:$Y$18,MATCH('KPI TRENDS'!$A12,'P&L ACTUALS+EST'!$A$3:$A$18,0),MATCH(M$2,'P&L ACTUALS+EST'!$B$2:$Y$2,0)),0) -> 4165929.9 | N12: =_xlfn.IFNA(INDEX('P&L ACTUALS+EST'!$B$3:$Y$18,MATCH('KPI TRENDS'!$A12,'P&L ACTUALS+EST'!$A$3:$A$18,0),MATCH(N$2,'P&L ACTUALS+EST'!$B$2:$Y$2,0)),0) -> 3437523.3 | O12: =SUM(I12:N12) -> 22936822 | P12: =SUM('P&L ACTUALS+EST'!B10:G10) -> 21758025
A13: Contribution profit % | B13: =B12/B5 -> 0.10516047 | C13: =C12/C5 -> 0.10886367 | D13: =D12/D5 -> 0.12239738 | E13: =E12/E5 -> 0.1267112 | F13: =F12/F5 -> 0.1288348 | G13: =G12/G5 -> 0.12488072 | H13: =H12/H5 -> 0.11991141 | I13: =I12/I5 -> 0.13349942 | ... P13: =P12/P5 -> 0.14280146
A14: OPEX
A15: OPEX | B15: =_xlfn.IFNA(INDEX('P&L ACTUALS+EST'!$B$3:$Y$18,MATCH('KPI TRENDS'!$A15,'P&L ACTUALS+EST'!$A$3:$A$18,0),MATCH(B$2,'P&L ACTUALS+EST'!$B$2:$Y$2,0)),0) -> -2373063.5 | C15: =_xlfn.IFNA(INDEX('P&L ACTUALS+EST'!$B$3:$Y$18,MATCH('KPI TRENDS'!$A15,'P&L ACTUALS+EST'!$A$3:$A$18,0),MATCH(C$2,'P&L ACTUALS+EST'!$B$2:$Y$2,0)),0) -> -2356777.3 | D15: =_xlfn.IFNA(INDEX('P&L ACTUALS+EST'!$B$3:$Y$18,MATCH('KPI TRENDS'!$A15,'P&L ACTUALS+EST'!$A$3:$A$18,0),MATCH(D$2,'P&L ACTUALS+EST'!$B$2:$Y$2,0)),0) -> -2462522.4 | E15: =_xlfn.IFNA(INDEX('P&L ACTUALS+EST'!$B$3:$Y$18,MATCH('KPI TRENDS'!$A15,'P&L ACTUALS+EST'!$A$3:$A$18,0),MATCH(E$2,'P&L ACTUALS+EST'!$B$2:$Y$2,0)),0) -> -2392504 | F15: =_xlfn.IFNA(INDEX('P&L ACTUALS+EST'!$B$3:$Y$18,MATCH('KPI TRENDS'!$A15,'P&L ACTUALS+EST'!$A$3:$A$18,0),MATCH(F$2,'P&L ACTUALS+EST'!$B$2:$Y$2,0)),0) -> -2294704.4 | G15: =_xlfn.IFNA(INDEX('P&L ACTUALS+EST'!$B$3:$Y$18,MATCH('KPI TRENDS'!$A15,'P&L ACTUALS+EST'!$A$3:$A$18,0),MATCH(G$2,'P&L ACTUALS+EST'!$B$2:$Y$2,0)),0) -> -2309268.9 | H15: =SUM(B15:G15) -> -14188841 | I15: =_xlfn.IFNA(INDEX('P&L ACTUALS+EST'!$B$3:$Y$18,MATCH('KPI TRENDS'!$A15,'P&L ACTUALS+EST'!$A$3:$A$18,0),MATCH(I$2,'P&L ACTUALS+EST'!$B$2:$Y$2,0)),0) -> -2369184 | J15: =_xlfn.IFNA(INDEX('P&L ACTUALS+EST'!$B$3:$Y$18,MATCH('KPI TRENDS'!$A15,'P&L ACTUALS+EST'!$A$3:$A$18,0),MATCH(J$2,'P&L ACTUALS+EST'!$B$2:$Y$2,0)),0) -> -2360597.4 | K15: =_xlfn.IFNA(INDEX('P&L ACTUALS+EST'!$B$3:$Y$18,MATCH('KPI TRENDS'!$A15,'P&L ACTUALS+EST'!$A$3:$A$18,0),MATCH(K$2,'P&L ACTUALS+EST'!$B$2:$Y$2,0)),0) -> -2484052.9 | L15: =_xlfn.IFNA(INDEX('P&L ACTUALS+EST'!$B$3:$Y$18,MATCH('KPI TRENDS'!$A15,'P&L ACTUALS+EST'!$A$3:$A$18,0),MATCH(L$2,'P&L ACTUALS+EST'!$B$2:$Y$2,0)),0) -> -2482457.1 | M15: =_xlfn.IFNA(INDEX('P&L ACTUALS+EST'!$B$3:$Y$18,MATCH('KPI TRENDS'!$A15,'P&L ACTUALS+EST'!$A$3:$A$18,0),MATCH(M$2,'P&L ACTUALS+EST'!$B$2:$Y$2,0)),0) -> -2409260.6 | N15: =_xlfn.IFNA(INDEX('P&L ACTUALS+EST'!$B$3:$Y$18,MATCH('KPI TRENDS'!$A15,'P&L ACTUALS+EST'!$A$3:$A$18,0),MATCH(N$2,'P&L ACTUALS+EST'!$B$2:$Y$2,0)),0) -> -2410225.5 | O15: =SUM(I15:N15) -> -14515777 | P15: =SUM('P&L ACTUALS+EST'!B17:G17) -> -14312604
A16: OPEX / REVENUE | B16: =B15/B5 -> -0.12988727 | C16: =C15/C5 -> -0.097824694 | D16: =D15/D5 -> -0.084737996 | E16: =E15/E5 -> -0.10880118 | F16: =F15/F5 -> -0.098047295 | G16: =G15/G5 -> -0.10923731 | H16: =H15/H5 -> -0.10285039 | I16: =I15/I5 -> -0.12516732 | ... P16: =P15/P5 -> -0.093935948
A17: LABOUR / REVENUE | B17: ='P&L ACTUALS+EST'!N11/B5 -> -0.086135989 | C17: ='P&L ACTUALS+EST'!O11/C5 -> -0.066135826 | D17: ='P&L ACTUALS+EST'!P11/D5 -> -0.054892023 | E17: ='P&L ACTUALS+EST'!Q11/E5 -> -0.072386849 | F17: ='P&L ACTUALS+EST'!R11/F5 -> -0.067555495 | G17: ='P&L ACTUALS+EST'!S11/G5 -> -0.075319055 | H17: =SUM('P&L ACTUALS+EST'!N11:S11)/'KPI TRENDS'!H5 -> -0.069060478 | I17: ='P&L ACTUALS+EST'!T11/I5 -> -0.08134673 | J17: ='P&L ACTUALS+EST'!U11/J5 -> -0.061787043 | K17: ='P&L ACTUALS+EST'!V11/K5 -> -0.045498677 | L17: ='P&L ACTUALS+EST'!W11/L5 -> -0.048682527 | M17: ='P&L ACTUALS+EST'!X11/M5 -> -0.05422274 | N17: ='P&L ACTUALS+EST'!Y11/N5 -> -0.06737431 | O17: ='P&L ACTUALS+EST'!Z11/O5 -> 0 | P17: =SUM('P&L ACTUALS+EST'!B11:G11)/P5 -> -0.061154825
A18: MARKETING / REVENUE | B18: ='P&L ACTUALS+EST'!N12/B5 -> -0.031371043 | C18: ='P&L ACTUALS+EST'!O12/C5 -> -0.025113188 | D18: ='P&L ACTUALS+EST'!P12/D5 -> -0.02355633 | E18: ='P&L ACTUALS+EST'!Q12/E5 -> -0.029644234 | F18: ='P&L ACTUALS+EST'!R12/F5 -> -0.024197024 | G18: ='P&L ACTUALS+EST'!S12/G5 -> -0.026297946 | H18: =SUM('P&L ACTUALS+EST'!N12:S12)/H5 -> -0.026362347 | I18: =SUM('P&L ACTUALS+EST'!T12:Y12)/I5 -> -0.22234328 | J18: =SUM('P&L ACTUALS+EST'!U12:Z12)/J5 -> -0.14502942 | K18: =SUM('P&L ACTUALS+EST'!V12:AA12)/K5 -> -0.087448896 | L18: =SUM('P&L ACTUALS+EST'!W12:AB12)/L5 -> -0.069460166 | M18: =SUM('P&L ACTUALS+EST'!X12:AC12)/M5 -> -0.049231251 | N18: =SUM('P&L ACTUALS+EST'!Y12:AD12)/N5 -> -0.029724006 | O18: =SUM('P&L ACTUALS+EST'!Z12:AE12)/O5 -> 0 | P18: =SUM('P&L ACTUALS+EST'!B12:G12)/P5 -> -0.025814351
A19: PROFITABILITY
A20: EBITDA | B20: =_xlfn.IFNA(INDEX('P&L ACTUALS+EST'!$B$3:$Y$18,MATCH('KPI TRENDS'!$A20,'P&L ACTUALS+EST'!$A$3:$A$18,0),MATCH(B$2,'P&L ACTUALS+EST'!$B$2:$Y$2,0)),0) -> -451763.03 | C20: =_xlfn.IFNA(INDEX('P&L ACTUALS+EST'!$B$3:$Y$18,MATCH('KPI TRENDS'!$A20,'P&L ACTUALS+EST'!$A$3:$A$18,0),MATCH(C$2,'P&L ACTUALS+EST'!$B$2:$Y$2,0)),0) -> 265949.31 | D20: =_xlfn.IFNA(INDEX('P&L ACTUALS+EST'!$B$3:$Y$18,MATCH('KPI TRENDS'!$A20,'P&L ACTUALS+EST'!$A$3:$A$18,0),MATCH(D$2,'P&L ACTUALS+EST'!$B$2:$Y$2,0)),0) -> 1094397.7 | E20: =_xlfn.IFNA(INDEX('P&L ACTUALS+EST'!$B$3:$Y$18,MATCH('KPI TRENDS'!$A20,'P&L ACTUALS+EST'!$A$3:$A$18,0),MATCH(E$2,'P&L ACTUALS+EST'!$B$2:$Y$2,0)),0) -> 393835.88 | F20: =_xlfn.IFNA(INDEX('P&L ACTUALS+EST'!$B$3:$Y$18,MATCH('KPI TRENDS'!$A20,'P&L ACTUALS+EST'!$A$3:$A$18,0),MATCH(F$2,'P&L ACTUALS+EST'!$B$2:$Y$2,0)),0) -> 720552.52 | G20: =_xlfn.IFNA(INDEX('P&L ACTUALS+EST'!$B$3:$Y$18,MATCH('KPI TRENDS'!$A20,'P&L ACTUALS+EST'!$A$3:$A$18,0),MATCH(G$2,'P&L ACTUALS+EST'!$B$2:$Y$2,0)),0) -> 330700.68 | H20: =SUM(B20:G20) -> 2353673.1 | I20: =_xlfn.IFNA(INDEX('P&L ACTUALS+EST'!$B$3:$Y$18,MATCH('KPI TRENDS'!$A20,'P&L ACTUALS+EST'!$A$3:$A$18,0),MATCH(I$2,'P&L ACTUALS+EST'!$B$2:$Y$2,0)),0) -> 157711.02 | J20: =_xlfn.IFNA(INDEX('P&L ACTUALS+EST'!$B$3:$Y$18,MATCH('KPI TRENDS'!$A20,'P&L ACTUALS+EST'!$A$3:$A$18,0),MATCH(J$2,'P&L ACTUALS+EST'!$B$2:$Y$2,0)),0) -> 1070145.6 | K20: =_xlfn.IFNA(INDEX('P&L ACTUALS+EST'!$B$3:$Y$18,MATCH('KPI TRENDS'!$A20,'P&L ACTUALS+EST'!$A$3:$A$18,0),MATCH(K$2,'P&L ACTUALS+EST'!$B$2:$Y$2,0)),0) -> 2310084.2 | L20: =_xlfn.IFNA(INDEX('P&L ACTUALS+EST'!$B$3:$Y$18,MATCH('KPI TRENDS'!$A20,'P&L ACTUALS+EST'!$A$3:$A$18,0),MATCH(L$2,'P&L ACTUALS+EST'!$B$2:$Y$2,0)),0) -> 2099136.6 | M20: =_xlfn.IFNA(INDEX('P&L ACTUALS+EST'!$B$3:$Y$18,MATCH('KPI TRENDS'!$A20,'P&L ACTUALS+EST'!$A$3:$A$18,0),MATCH(M$2,'P&L ACTUALS+EST'!$B$2:$Y$2,0)),0) -> 1756669.3 | N20: =_xlfn.IFNA(INDEX('P&L ACTUALS+EST'!$B$3:$Y$18,MATCH('KPI TRENDS'!$A20,'P&L ACTUALS+EST'!$A$3:$A$18,0),MATCH(N$2,'P&L ACTUALS+EST'!$B$2:$Y$2,0)),0) -> 1027297.8 | O20: =SUM(I20:N20) -> 8421044.4 | P20: =SUM('P&L ACTUALS+EST'!B18:G18) -> 7445420.7
A21: EBITDA profit % | B21: =B20/B5 -> -0.024726801 | C21: =C20/C5 -> 0.011038977 | D21: =D20/D5 -> 0.037659382 | E21: =E20/E5 -> 0.017910025 | F21: =F20/F5 -> 0.030787506 | G21: =G20/G5 -> 0.015643415 | H21: =H20/H5 -> 0.017061027 | I21: =I20/I5 -> 0.0083320948 | ... P21: =P20/P5 -> 0.048865507

Sheet CHARTS
A1: Performance Charts | Jan - Jun 2025
A3: Month | B3: Revenue Act | C3: Revenue Bud | D3: Revenue PY | F3: Month | G3: Gross profit % Act | H3: Gross profit % Bud | I3: Contribution profit % Act | J3: EBITDA% Act | K3: EBITDA% Bud | M3: Month | N3: EBITDA Act | O3: EBITDA Bud | P3: EBITDA PY
A4: Jan | B4: {=_xlfn.XLOOKUP(CHARTS!$S4,TRANSPOSE('P&L ACTUALS+EST'!$N$2:$S$2),TRANSPOSE('P&L ACTUALS+EST'!$N$3:$S$3),0)} -> 18270177 | C4: {=_xlfn.XLOOKUP(T4,TRANSPOSE('P&L ACTUALS+EST'!$T$2:$Y$2),TRANSPOSE('P&L ACTUALS+EST'!$T$3:$Y$3),0)} -> 18928135 | D4: {=_xlfn.XLOOKUP(R4,TRANSPOSE('P&L ACTUALS+EST'!$B$2:$G$2),TRANSPOSE('P&L ACTUALS+EST'!$B$3:$G$3),0)} -> 17902923 | F4: Jan | G4: {=TRANSPOSE('KPI TRENDS'!B7:G7)} -> 0.38804709 | H4: {=TRANSPOSE('KPI TRENDS'!I7:N7)} -> 0.39881764 | I4: {=TRANSPOSE('KPI TRENDS'!B13:G13)} -> 0.10516047 | J4: {=TRANSPOSE('KPI TRENDS'!B21:G21)} -> -0.024726801 | K4: {=TRANSPOSE('KPI TRENDS'!I21:N21 )} -> 0.0083320948 | M4: Jan | N4: {=TRANSPOSE('KPI TRENDS'!B20:G20)} -> -451763.03 | O4: {=TRANSPOSE('KPI TRENDS'!I20:N20)} -> 157711.02 | P4: {=TRANSPOSE('P&L ACTUALS+EST'!B18:G18)} -> 13028.88 | R4: 2024.01_act | S4: 2025.01_act | T4: 2025.01_est
A5: Feb | B5: {=_xlfn.XLOOKUP(CHARTS!$S5,TRANSPOSE('P&L ACTUALS+EST'!$N$2:$S$2),TRANSPOSE('P&L ACTUALS+EST'!$N$3:$S$3),0)} -> 24091845 | C5: {=_xlfn.XLOOKUP(T5,TRANSPOSE('P&L ACTUALS+EST'!$T$2:$Y$2),TRANSPOSE('P&L ACTUALS+EST'!$T$3:$Y$3),0)} -> 24920142 | D5: {=_xlfn.XLOOKUP(R5,TRANSPOSE('P&L ACTUALS+EST'!$B$2:$G$2),TRANSPOSE('P&L ACTUALS+EST'!$B$3:$G$3),0)} -> 23598619 | F5: Feb | G5: 0.38941423 | H5: 0.40045798 | I5: 0.10886367 | J5: 0.011038977 | K5: 0.042942996 | M5: Feb | N5: 265949.31 | O5: 1070145.6 | P5: 873043.63 | R5: 2024.02_act | S5: 2025.02_act | T5: 2025.02_est
A6: Mar | B6: {=_xlfn.XLOOKUP(CHARTS!$S6,TRANSPOSE('P&L ACTUALS+EST'!$N$2:$S$2),TRANSPOSE('P&L ACTUALS+EST'!$N$3:$S$3),0)} -> 29060428 | C6: {=_xlfn.XLOOKUP(T6,TRANSPOSE('P&L ACTUALS+EST'!$T$2:$Y$2),TRANSPOSE('P&L ACTUALS+EST'!$T$3:$Y$3),0)} -> 33841465 | D6: {=_xlfn.XLOOKUP(R6,TRANSPOSE('P&L ACTUALS+EST'!$B$2:$G$2),TRANSPOSE('P&L ACTUALS+EST'!$B$3:$G$3),0)} -> 32077218 | F6: Mar | G6: 0.39371634 | H6: 0.39939364 | I6: 0.12239738 | J6: 0.037659382 | K6: 0.068261942 | M6: Mar | N6: 1094397.7 | O6: 2310084.2 | P6: 2110234.7 | R6: 2024.03_act | S6: 2025.03_act | T6: 2025.03_est
A7: Apr | B7: {=_xlfn.XLOOKUP(CHARTS!$S7,TRANSPOSE('P&L ACTUALS+EST'!$N$2:$S$2),TRANSPOSE('P&L ACTUALS+EST'!$N$3:$S$3),0)} -> 21989689 | C7: {=_xlfn.XLOOKUP(T7,TRANSPOSE('P&L ACTUALS+EST'!$T$2:$Y$2),TRANSPOSE('P&L ACTUALS+EST'!$T$3:$Y$3),0)} -> 31628225 | D7: {=_xlfn.XLOOKUP(R7,TRANSPOSE('P&L ACTUALS+EST'!$B$2:$G$2),TRANSPOSE('P&L ACTUALS+EST'!$B$3:$G$3),0)} -> 30007803 | F7: Apr | G7: 0.39589161 | H7: 0.4000571 | I7: 0.1267112 | J7: 0.017910025 | K7: 0.066369092 | M7: Apr | N7: 393835.88 | O7: 2099136.6 | P7: 2009576 | R7: 2024.04_act | S7: 2025.04_act | T7: 2025.04_est
A8: May | B8: {=_xlfn.XLOOKUP(CHARTS!$S8,TRANSPOSE('P&L ACTUALS+EST'!$N$2:$S$2),TRANSPOSE('P&L ACTUALS+EST'!$N$3:$S$3),0)} -> 23404056 | C8: {=_xlfn.XLOOKUP(T8,TRANSPOSE('P&L ACTUALS+EST'!$T$2:$Y$2),TRANSPOSE('P&L ACTUALS+EST'!$T$3:$Y$3),0)} -> 28396608 | D8: {=_xlfn.XLOOKUP(R8,TRANSPOSE('P&L ACTUALS+EST'!$B$2:$G$2),TRANSPOSE('P&L ACTUALS+EST'!$B$3:$G$3),0)} -> 26992974 | F8: May | G8: 0.39790843 | H8: 0.3994249 | I8: 0.1288348 | J8: 0.030787506 | K8: 0.061861941 | M8: May | N8: 720552.52 | O8: 1756669.3 | P8: 1600280.8 | R8: 2024.05_act | S8: 2025.05_act | T8: 2025.05_est
A9: Jun | B9: {=_xlfn.XLOOKUP(CHARTS!$S9,TRANSPOSE('P&L ACTUALS+EST'!$N$2:$S$2),TRANSPOSE('P&L ACTUALS+EST'!$N$3:$S$3),0)} -> 21139929 | C9: {=_xlfn.XLOOKUP(T9,TRANSPOSE('P&L ACTUALS+EST'!$T$2:$Y$2),TRANSPOSE('P&L ACTUALS+EST'!$T$3:$Y$3),0)} -> 22853546 | D9: {=_xlfn.XLOOKUP(R9,TRANSPOSE('P&L ACTUALS+EST'!$B$2:$G$2),TRANSPOSE('P&L ACTUALS+EST'!$B$3:$G$3),0)} -> 21786031 | F9: Jun | G9: 0.39233102 | H9: 0.3992653 | I9: 0.12488072 | J9: 0.015643415 | K9: 0.044951351 | M9: Jun | N9: 330700.68 | O9: 1027297.8 | P9: 839256.71 | R9: 2024.06_act | S9: 2025.06_act | T9: 2025.06_est
A12: Cost Category | B12: Act 2025 | C12: Budget | D12: PY 2024
A13: COGS | B13: =_xlfn.XLOOKUP($A13,'P&L MONTHLY'!$A$6:$A$24,'P&L MONTHLY'!AF$6:AF$24) -> -83731108 | C13: =_xlfn.XLOOKUP(A13,'P&L MONTHLY'!$A$6:$A$24,'P&L MONTHLY'!$AH$6:$AH$24) -> -96403675 | D13: =_xlfn.XLOOKUP(A13,'P&L MONTHLY'!$A$6:$A$24,'P&L MONTHLY'!$AG$6:$AG$24) -> -93211922
A14: Payment | B14: =_xlfn.XLOOKUP($A14,'P&L MONTHLY'!$A$6:$A$24,'P&L MONTHLY'!AF$6:AF$24) -> -3079470.7 | C14: =_xlfn.XLOOKUP(A14,'P&L MONTHLY'!$A$6:$A$24,'P&L MONTHLY'!$AH$6:$AH$24) -> -3613211 | D14: =_xlfn.XLOOKUP(A14,'P&L MONTHLY'!$A$6:$A$24,'P&L MONTHLY'!$AG$6:$AG$24) -> -3253387.2
A15: Warehouse | B15: =_xlfn.XLOOKUP($A15,'P&L MONTHLY'!$A$6:$A$24,'P&L MONTHLY'!AF$6:AF$24) -> -13273834 | C15: =_xlfn.XLOOKUP(A15,'P&L MONTHLY'!$A$6:$A$24,'P&L MONTHLY'!$AH$6:$AH$24) -> -13439459 | D15: =_xlfn.XLOOKUP(A15,'P&L MONTHLY'!$A$6:$A$24,'P&L MONTHLY'!$AG$6:$AG$24) -> -11867422
A16: Distribution | B16: =_xlfn.XLOOKUP($A16,'P&L MONTHLY'!$A$6:$A$24,'P&L MONTHLY'!AF$6:AF$24) -> -21329197 | C16: =_xlfn.XLOOKUP(A16,'P&L MONTHLY'!$A$6:$A$24,'P&L MONTHLY'!$AH$6:$AH$24) -> -24174955 | D16: =_xlfn.XLOOKUP(A16,'P&L MONTHLY'!$A$6:$A$24,'P&L MONTHLY'!$AG$6:$AG$24) -> -22274813
A17: LABOUR | B17: =_xlfn.XLOOKUP($A17,'P&L MONTHLY'!$A$6:$A$24,'P&L MONTHLY'!AF$6:AF$24) -> -9527315.9 | C17: =_xlfn.XLOOKUP(A17,'P&L MONTHLY'!$A$6:$A$24,'P&L MONTHLY'!$AH$6:$AH$24) -> -9238451.4 | D17: =_xlfn.XLOOKUP(A17,'P&L MONTHLY'!$A$6:$A$24,'P&L MONTHLY'!$AG$6:$AG$24) -> -9317889.7
A18: Marketing | B18: =_xlfn.XLOOKUP($A18,'P&L MONTHLY'!$A$6:$A$24,'P&L MONTHLY'!AF$6:AF$24) -> -3636847.3 | C18: =_xlfn.XLOOKUP(A18,'P&L MONTHLY'!$A$6:$A$24,'P&L MONTHLY'!$AH$6:$AH$24) -> -4208543.6 | D18: =_xlfn.XLOOKUP(A18,'P&L MONTHLY'!$A$6:$A$24,'P&L MONTHLY'!$AG$6:$AG$24) -> -3933218.3
A19: Rent | B19: =_xlfn.XLOOKUP($A19,'P&L MONTHLY'!$A$6:$A$24,'P&L MONTHLY'!AF$6:AF$24) -> -580666.74 | C19: =_xlfn.XLOOKUP(A19,'P&L MONTHLY'!$A$6:$A$24,'P&L MONTHLY'!$AH$6:$AH$24) -> -592019.83 | D19: =_xlfn.XLOOKUP(A19,'P&L MONTHLY'!$A$6:$A$24,'P&L MONTHLY'!$AG$6:$AG$24) -> -586158.24
A20: Travel | B20: =_xlfn.XLOOKUP($A20,'P&L MONTHLY'!$A$6:$A$24,'P&L MONTHLY'!AF$6:AF$24) -> -29259.079 | C20: =_xlfn.XLOOKUP(A20,'P&L MONTHLY'!$A$6:$A$24,'P&L MONTHLY'!$AH$6:$AH$24) -> -46990.114 | D20: =_xlfn.XLOOKUP(A20,'P&L MONTHLY'!$A$6:$A$24,'P&L MONTHLY'!$AG$6:$AG$24) -> -40591.827
A21: Consulting | B21: =_xlfn.XLOOKUP($A21,'P&L MONTHLY'!$A$6:$A$24,'P&L MONTHLY'!AF$6:AF$24) -> -91336.748 | C21: =_xlfn.XLOOKUP(A21,'P&L MONTHLY'!$A$6:$A$24,'P&L MONTHLY'!$AH$6:$AH$24) -> -97242.74 | D21: =_xlfn.XLOOKUP(A21,'P&L MONTHLY'!$A$6:$A$24,'P&L MONTHLY'!$AG$6:$AG$24) -> -118051.02
A22: Insurances | B22: =_xlfn.XLOOKUP($A22,'P&L MONTHLY'!$A$6:$A$24,'P&L MONTHLY'!AF$6:AF$24) -> -323414.85 | C22: =_xlfn.XLOOKUP(A22,'P&L MONTHLY'!$A$6:$A$24,'P&L MONTHLY'!$AH$6:$AH$24) -> -332529.82 | D22: =_xlfn.XLOOKUP(A22,'P&L MONTHLY'!$A$6:$A$24,'P&L MONTHLY'!$AG$6:$AG$24) -> -316695.06

Sheet COMMENTS
A1: Analysis — Deviations, Drivers & Recommendations | YTD Jan–Jun 2025
A3: Category/Period | B3: Act 2025 | C3: PY 2024 | D3: Budget | E3: ∆ vs Budget | F3: % vs Budget
A4: Revenue | B4: =INDEX('P&L MONTHLY'!$AF$6:$AJ$24,MATCH(COMMENTS!$A4,'P&L MONTHLY'!$A$6:$A$24,0),MATCH(COMMENTS!B$3,'P&L MONTHLY'!$AF$5:$AJ$5,0)) -> 1.3795612e+08 | C4: =INDEX('P&L MONTHLY'!$AF$6:$AJ$24,MATCH(COMMENTS!$A4,'P&L MONTHLY'!$A$6:$A$24,0),MATCH(COMMENTS!C$3,'P&L MONTHLY'!$AF$5:$AJ$5,0)) -> 1.5236557e+08 | D4: =INDEX('P&L MONTHLY'!$AF$6:$AJ$24,MATCH(COMMENTS!$A4,'P&L MONTHLY'!$A$6:$A$24,0),MATCH(COMMENTS!D$3,'P&L MONTHLY'!$AF$5:$AJ$5,0)) -> 1.6056812e+08 | E4: =INDEX('P&L MONTHLY'!$AF$6:$AJ$24,MATCH(COMMENTS!$A4,'P&L MONTHLY'!$A$6:$A$24,0),MATCH(COMMENTS!E$3,'P&L MONTHLY'!$AF$5:$AJ$5,0)) -> -14409445 | F4: =INDEX('P&L MONTHLY'!$AF$6:$AJ$24,MATCH(COMMENTS!$A4,'P&L MONTHLY'!$A$6:$A$24,0),MATCH(COMMENTS!F$3,'P&L MONTHLY'!$AF$5:$AJ$5,0)) -> -0.14082495
A5: Gross Profit | B5: =INDEX('P&L MONTHLY'!$AF$6:$AJ$24,MATCH(COMMENTS!$A5,'P&L MONTHLY'!$A$6:$A$24,0),MATCH(COMMENTS!B$3,'P&L MONTHLY'!$AF$5:$AJ$5,0)) -> 54225016 | C5: =INDEX('P&L MONTHLY'!$AF$6:$AJ$24,MATCH(COMMENTS!$A5,'P&L MONTHLY'!$A$6:$A$24,0),MATCH(COMMENTS!C$3,'P&L MONTHLY'!$AF$5:$AJ$5,0)) -> 59153647 | D5: =INDEX('P&L MONTHLY'!$AF$6:$AJ$24,MATCH(COMMENTS!$A5,'P&L MONTHLY'!$A$6:$A$24,0),MATCH(COMMENTS!D$3,'P&L MONTHLY'!$AF$5:$AJ$5,0)) -> 64164446 | E5: =INDEX('P&L MONTHLY'!$AF$6:$AJ$24,MATCH(COMMENTS!$A5,'P&L MONTHLY'!$A$6:$A$24,0),MATCH(COMMENTS!E$3,'P&L MONTHLY'!$AF$5:$AJ$5,0)) -> -4928630.8 | F5: =INDEX('P&L MONTHLY'!$AF$6:$AJ$24,MATCH(COMMENTS!$A5,'P&L MONTHLY'!$A$6:$A$24,0),MATCH(COMMENTS!F$3,'P&L MONTHLY'!$AF$5:$AJ$5,0)) -> -0.15490557
A6: Gross Profit % | B6: =INDEX('P&L MONTHLY'!$AF$6:$AJ$24,MATCH(COMMENTS!$A6,'P&L MONTHLY'!$A$6:$A$24,0),MATCH(COMMENTS!B$3,'P&L MONTHLY'!$AF$5:$AJ$5,0)) -> 0.39305987 | C6: =INDEX('P&L MONTHLY'!$AF$6:$AJ$24,MATCH(COMMENTS!$A6,'P&L MONTHLY'!$A$6:$A$24,0),MATCH(COMMENTS!C$3,'P&L MONTHLY'!$AF$5:$AJ$5,0)) -> 0.388235 | D6: =INDEX('P&L MONTHLY'!$AF$6:$AJ$24,MATCH(COMMENTS!$A6,'P&L MONTHLY'!$A$6:$A$24,0),MATCH(COMMENTS!D$3,'P&L MONTHLY'!$AF$5:$AJ$5,0)) -> 0.39960887 | E6: =INDEX('P&L MONTHLY'!$AF$6:$AJ$24,MATCH(COMMENTS!$A6,'P&L MONTHLY'!$A$6:$A$24,0),MATCH(COMMENTS!E$3,'P&L MONTHLY'!$AF$5:$AJ$5,0)) -> -0.0065490049 | F6: =INDEX('P&L MONTHLY'!$AF$6:$AJ$24,MATCH(COMMENTS!$A6,'P&L MONTHLY'!$A$6:$A$24,0),MATCH(COMMENTS!F$3,'P&L MONTHLY'!$AF$5:$AJ$5,0)) -> -0.016388537
A7: Contribution Profit | B7: =INDEX('P&L MONTHLY'!$AF$6:$AJ$24,MATCH(COMMENTS!$A7,'P&L MONTHLY'!$A$6:$A$24,0),MATCH(COMMENTS!B$3,'P&L MONTHLY'!$AF$5:$AJ$5,0)) -> 16542514 | C7: =INDEX('P&L MONTHLY'!$AF$6:$AJ$24,MATCH(COMMENTS!$A7,'P&L MONTHLY'!$A$6:$A$24,0),MATCH(COMMENTS!C$3,'P&L MONTHLY'!$AF$5:$AJ$5,0)) -> 21758025 | D7: =INDEX('P&L MONTHLY'!$AF$6:$AJ$24,MATCH(COMMENTS!$A7,'P&L MONTHLY'!$A$6:$A$24,0),MATCH(COMMENTS!D$3,'P&L MONTHLY'!$AF$5:$AJ$5,0)) -> 22936822 | E7: =INDEX('P&L MONTHLY'!$AF$6:$AJ$24,MATCH(COMMENTS!$A7,'P&L MONTHLY'!$A$6:$A$24,0),MATCH(COMMENTS!E$3,'P&L MONTHLY'!$AF$5:$AJ$5,0)) -> -5215511.2 | F7: =INDEX('P&L MONTHLY'!$AF$6:$AJ$24,MATCH(COMMENTS!$A7,'P&L MONTHLY'!$A$6:$A$24,0),MATCH(COMMENTS!F$3,'P&L MONTHLY'!$AF$5:$AJ$5,0)) -> -0.27877917
A8: OPEX | B8: =INDEX('P&L MONTHLY'!$AF$6:$AJ$24,MATCH(COMMENTS!$A8,'P&L MONTHLY'!$A$6:$A$24,0),MATCH(COMMENTS!B$3,'P&L MONTHLY'!$AF$5:$AJ$5,0)) -> -14188841 | C8: =INDEX('P&L MONTHLY'!$AF$6:$AJ$24,MATCH(COMMENTS!$A8,'P&L MONTHLY'!$A$6:$A$24,0),MATCH(COMMENTS!C$3,'P&L MONTHLY'!$AF$5:$AJ$5,0)) -> -14312604 | D8: =INDEX('P&L MONTHLY'!$AF$6:$AJ$24,MATCH(COMMENTS!$A8,'P&L MONTHLY'!$A$6:$A$24,0),MATCH(COMMENTS!D$3,'P&L MONTHLY'!$AF$5:$AJ$5,0)) -> -14515777 | E8: =INDEX('P&L MONTHLY'!$AF$6:$AJ$24,MATCH(COMMENTS!$A8,'P&L MONTHLY'!$A$6:$A$24,0),MATCH(COMMENTS!E$3,'P&L MONTHLY'!$AF$5:$AJ$5,0)) -> 123763.62 | F8: =INDEX('P&L MONTHLY'!$AF$6:$AJ$24,MATCH(COMMENTS!$A8,'P&L MONTHLY'!$A$6:$A$24,0),MATCH(COMMENTS!F$3,'P&L MONTHLY'!$AF$5:$AJ$5,0)) -> -0.022522867
A9: EBITDA | B9: =INDEX('P&L MONTHLY'!$AF$6:$AJ$24,MATCH(COMMENTS!$A9,'P&L MONTHLY'!$A$6:$A$24,0),MATCH(COMMENTS!B$3,'P&L MONTHLY'!$AF$5:$AJ$5,0)) -> 2353673.1 | C9: =INDEX('P&L MONTHLY'!$AF$6:$AJ$24,MATCH(COMMENTS!$A9,'P&L MONTHLY'!$A$6:$A$24,0),MATCH(COMMENTS!C$3,'P&L MONTHLY'!$AF$5:$AJ$5,0)) -> 7445420.7 | D9: =INDEX('P&L MONTHLY'!$AF$6:$AJ$24,MATCH(COMMENTS!$A9,'P&L MONTHLY'!$A$6:$A$24,0),MATCH(COMMENTS!D$3,'P&L MONTHLY'!$AF$5:$AJ$5,0)) -> 8421044.4 | E9: =INDEX('P&L MONTHLY'!$AF$6:$AJ$24,MATCH(COMMENTS!$A9,'P&L MONTHLY'!$A$6:$A$24,0),MATCH(COMMENTS!E$3,'P&L MONTHLY'!$AF$5:$AJ$5,0)) -> -5091747.6 | F9: =INDEX('P&L MONTHLY'!$AF$6:$AJ$24,MATCH(COMMENTS!$A9,'P&L MONTHLY'!$A$6:$A$24,0),MATCH(COMMENTS!F$3,'P&L MONTHLY'!$AF$5:$AJ$5,0)) -> -0.72050104
A10: EBITDA margin % | B10: =INDEX('P&L MONTHLY'!$AF$6:$AJ$24,MATCH(COMMENTS!$A10,'P&L MONTHLY'!$A$6:$A$24,0),MATCH(COMMENTS!B$3,'P&L MONTHLY'!$AF$5:$AJ$5,0)) -> 0.017061027 | C10: =INDEX('P&L MONTHLY'!$AF$6:$AJ$24,MATCH(COMMENTS!$A10,'P&L MONTHLY'!$A$6:$A$24,0),MATCH(COMMENTS!C$3,'P&L MONTHLY'!$AF$5:$AJ$5,0)) -> 0.048865507 | D10: =INDEX('P&L MONTHLY'!$AF$6:$AJ$24,MATCH(COMMENTS!$A10,'P&L MONTHLY'!$A$6:$A$24,0),MATCH(COMMENTS!D$3,'P&L MONTHLY'!$AF$5:$AJ$5,0)) -> 0.052445307 | E10: =INDEX('P&L MONTHLY'!$AF$6:$AJ$24,MATCH(COMMENTS!$A10,'P&L MONTHLY'!$A$6:$A$24,0),MATCH(COMMENTS!E$3,'P&L MONTHLY'!$AF$5:$AJ$5,0)) -> -0.03538428 | F10: =INDEX('P&L MONTHLY'!$AF$6:$AJ$24,MATCH(COMMENTS!$A10,'P&L MONTHLY'!$A$6:$A$24,0),MATCH(COMMENTS!F$3,'P&L MONTHLY'!$AF$5:$AJ$5,0)) -> -0.67468916
A13: REVENUE
A14: YTD Revenue 138M -> -22,6M (-14.1%) below budget. No month met the target. April 2025 was the worst (-32% vs budget)
A18: GROSS PROFIT %
A19: Product margins are stable -> OK Gross Profit Act 39,3% vs Budget 40,0% - small deviation (0,7 pp.)
A23: EBITDA
A24: EBITDA ACT 2,35M vs Budget 8,42M -> -5,1M (-72%) below budget. Main reason: stable labour and warehouse costs, they didn't decrease with the decrease of revenue. Future action in this area required
A28: Labour/Revenue
A29: Ratio act 6,9% vs 5,7% in the budget (+1,2 pp). With revenues of 138M this means to approx. 1,7M of additional charge on the final result
A33: STRATEGIC RECOMMENDATIONS
A34: - Conduct an analysis regarding revenue decrease and its budgeting methods
A35: - Review fixed costs, renegotiate prices/capacity
